Workbook
Name Afecta: [1]Maestro!$I$2:$I$3
Name Afecta: Maestro!$I$8:$I$9
Name Res_Falla: [1]Maestro!$H$2:$H$3
Name Res_Falla: Maestro!$H$8:$H$9
Name Tipo_Afect: [1]Maestro!$G$2:$G$3
Name Tipo_Afect: Maestro!$G$8:$G$9

Sheet BD indisponibilidad
C1: 8 | AA1: Código | AB1: FR-GDO-013
C2: FORMATO | AA2: Versión | AB2: 0
C3: BITÁCORA DISPONIBILIDAD DE PRODUCTOS | AA3: Fecha | AB3: 45525
H5: Aplicación Afectada | M5: Empresa(s) Afectada(s) | T5: Producto Afectada(s)
A6: Mes | B6: Producto afectado o aplicación | C6: Incidente | D6: Fecha y hora inicio | E6: Fecha y hora fin | F6: Tiempo falla (en Mintuos) | G6: Tipo de afectación | H6: JADE | I6: SIGA | J6: APLICACIONES WEB GANA | K6: INVICTUS | L6: SALO -LOTERIA | M6: Acertemos - Cauca | N6: Jer - Boyacá | O6: Suchance - Huila | P6: MatrixRedes | Q6: Gana - Antioquia | R6: Gana Gana - Tolima | S6: Santander La Perla | T6: Apuestas - Chance | U6: PAGOS | V6: RECAUDOS | W6: RECARGAS | X6: Responsable Falla | Y6: Descripción | Z6: Causa raiz | AA6: Plan accion | AB6: Analista MDS
A7: Enero | B7: JADE | C7: INC 2026-000722 | D7: 46024.542 | E7: 46024.558 | F7: 60 | G7: caÍda total | H7: SI | I7: NO | J7: NO | K7: SI | L7: NO | M7: NO | N7: NO | O7: NO | P7: NO | Q7: SI | R7: NO | S7: NO | T7: SI | U7: SI | V7: SI | W7: SI | X7: Matrix Tech | Y7: No deja ingresar | Z7: Contension en base de datos | AA7: Sevalida con el area de BD quein escala al proveedor | AB7: NICOLAS QUIROGA
A8: Enero | B8: CAIDA GENERAL JADE | C8: 728296 | D8: 46038.346 | E8: 46038.365 | F8: =+(disponibilidad[[#This Row],[Fecha y hora fin]]-disponibilidad[[#This Row],[Fecha y hora inicio]])*1440 -> 27 | G8: Intermitencia | H8: SI | I8: NO | J8: NO | K8: NO | L8: NO | M8: NO | N8: NO | O8: SI | P8: NO | Q8: NO | R8: NO | S8: NO | T8: SI | U8: SI | V8: SI | W8: SI | X8: Matrix Tech | Y8: intermitencia en el aplicativo | Z8: Res afectada | AA8: Se realiza un reinicio controlado en los servidores de la red para restablecer el servicio | AB8: JORGEN VALDES
A9: Enero | B9: Caida general JADE | C9: 728306 | D9: 46038.458 | E9: 46038.472 | F9: =+(disponibilidad[[#This Row],[Fecha y hora fin]]-disponibilidad[[#This Row],[Fecha y hora inicio]])*1440 -> 20 | G9: caÍda total | H9: SI | I9: NO | J9: NO | K9: NO | L9: NO | M9: NO | N9: NO | O9: NO | P9: NO | Q9: NO | R9: SI | S9: NO | T9: SI | U9: SI | V9: SI | W9: SI | X9: Matrix Tech | Y9: caida general del sistema | Z9: Afectacion el el servidor | AA9: Se realiza un reinicio controlado de los servidores, se restablece el servicio | AB9: JORGEN VALDES
A10: Enero | B10: NOVEDAD JADE - INTERMITENCIA Y/O LENTITUD APLICATIVO | C10: 728344 | D10: 46041.349 | E10: 46041.36 | F10: =+(disponibilidad[[#This Row],[Fecha y hora fin]]-disponibilidad[[#This Row],[Fecha y hora inicio]])*1440 -> 15 | G10: Intermitencia | H10: SI | I10: NO | J10: NO | K10: NO | L10: NO | M10: NO | N10: NO | O10: NO | P10: NO | Q10: NO | R10: NO | S10: SI | T10: SI | U10: SI | V10: SI | W10: SI | X10: Matrix Tech | Y10: intermitencia en el aplicativo | Z10: sw_default con afectacion | AA10: Se realiza un reinicio controlado en los servidores de la red para restablecer el servicio | AB10: JORGEN VALDES
A11: Enero | B11: CAIDA GENERAL DE SIGA Y JADE | C11: 728342 | D11: 46041.347 | E11: 46041.36 | F11: =+(disponibilidad[[#This Row],[Fecha y hora fin]]-disponibilidad[[#This Row],[Fecha y hora inicio]])*1440 -> 18 | G11: Intermitencia | H11: SI | I11: NO | J11: NO | K11: NO | L11: NO | M11: NO | N11: NO | O11: SI | P11: NO | Q11: NO | R11: NO | S11: NO | T11: SI | U11: SI | V11: SI | W11: SI | X11: Matrix Tech | Y11: intermitencia en el aplicativo | Z11: Res afectada | AA11: Se realiza un reinicio controlado en los servidores de la red para restablecer el servicio | AB11: JORGEN VALDES
A12: Enero | B12: Novedad Jade | C12: 728345 | D12: 46041.363 | E12: 46041.372 | F12: =+(disponibilidad[[#This Row],[Fecha y hora fin]]-disponibilidad[[#This Row],[Fecha y hora inicio]])*1440 -> 12 | G12: Intermitencia | H12: SI | I12: NO | J12: NO | K12: NO | L12: NO | M12: SI | N12: NO | O12: NO | P12: NO | Q12: NO | R12: NO | S12: NO | T12: SI | U12: SI | V12: SI | W12: SI | X12: Matrix Tech | Y12: intermitencia en el aplicativo | Z12: Res afectada | AA12: Se realiza un reinicio controlado de los servidores, se restablece el servicio | AB12: JORGEN VALDES
A13: Enero | B13: Novedad Jade | C13: 728381 | D13: 46042.313 | E13: 46042.321 | F13: =+(disponibilidad[[#This Row],[Fecha y hora fin]]-disponibilidad[[#This Row],[Fecha y hora inicio]])*1440 -> 11 | G13: Intermitencia | H13: SI | I13: NO | J13: NO | K13: NO | L13: NO | M13: SI | N13: NO | O13: NO | P13: NO | Q13: NO | R13: NO | S13: NO | T13: SI | U13: SI | V13: SI | W13: SI | X13: Matrix Tech | Y13: intermitencia en el aplicativo | Z13: Res afectada | AA13: Se realiza un reinicio controlado de los servidores, se restablece el servicio | AB13: JORGEN VALDES
A14: Enero | B14: Lentitud JADE | C14: 728382 | D14: 46042.314 | E14: 46042.33 | F14: =+(disponibilidad[[#This Row],[Fecha y hora fin]]-disponibilidad[[#This Row],[Fecha y hora inicio]])*1440 -> 23 | G14: Intermitencia | H14: SI | I14: NO | J14: NO | K14: NO | L14: NO | M14: NO | N14: NO | O14: SI | P14: NO | Q14: NO | R14: NO | S14: NO | T14: SI | U14: SI | V14: SI | W14: SI | X14: Matrix Tech | Y14: intermitencia en el aplicativo | Z14: Res afectada | AA14: Se realiza un reinicio controlado de los servidores, se restablece el servicio | AB14: JORGEN VALDES
A15: Enero | B15: NOVEDAD JADE - LENTITUD Y/O INTERMITENCIA JADE | C15: 728385 | D15: 46042.349 | E15: 46042.404 | F15: =+(disponibilidad[[#This Row],[Fecha y hora fin]]-disponibilidad[[#This Row],[Fecha y hora inicio]])*1440 -> 79 | G15: Intermitencia | H15: SI | I15: NO | J15: NO | K15: NO | L15: NO | M15: NO | N15: NO | O15: NO | P15: NO | Q15: NO | R15: NO | S15: SI | T15: SI | U15: SI | V15: SI | W15: SI | X15: Matrix Tech | Y15: intermitencia en el aplicativo | Z15: backup traslado de copias base de datos | AA15: Se finaliza de forma forzada el traslado de los backup de base de datos servicio se restablece. | AB15: JORGEN VALDES
A16: Enero | B16: recargas metro sin tx | C16: INC 2026-017677 | D16: 46044.387 | E16: 46044.438 | F16: =+(disponibilidad[[#This Row],[Fecha y hora fin]]-disponibilidad[[#This Row],[Fecha y hora inicio]])*1440 -> 72 | G16: caÍda total | H16: SI | I16: NO | J16: NO | K16: NO | L16: NO | M16: NO | N16: NO | O16: NO | P16: NO | Q16: SI | R16: NO | S16: NO | T16: NO | U16: NO | V16: SI | W16: NO | X16: Aliados o terceros | Y16: no se evidencian tx para el producto | Z16: Se identifica que la novedad correspondía a una incidencia general del aliado. | AA16: El aliado informó y gestionó la corrección de la incidencia. Actualmente el servicio se encuentra restablecido y las transacciones se están procesando con normalidad. | AB16: JORGEN VALDES
A17: Enero | B17: Lentitud JADE | C17: 728503 | D17: 46045.6 | E17: 46045.611 | F17: =+(disponibilidad[[#This Row],[Fecha y hora fin]]-disponibilidad[[#This Row],[Fecha y hora inicio]])*1440 -> 16 | G17: Intermitencia | H17: SI | I17: NO | J17: NO | K17: NO | L17: NO | M17: NO | N17: NO | O17: SI | P17: NO | Q17: NO | R17: NO | S17: NO | T17: SI | U17: SI | V17: SI | W17: SI | X17: Matrix Tech | Y17: intermitencia en el aplicativo | Z17: sw_default con afectacion | AA17: Se realiza un reinicio controlado de los servidores, se restablece el servicio | AB17: JORGEN VALDES
A18: Enero | B18: CAIDA GENERAL APLICATIVO JADE | C18: 728576 | D18: 46048.341 | E18: 46048.36 | F18: =+(disponibilidad[[#This Row],[Fecha y hora fin]]-disponibilidad[[#This Row],[Fecha y hora inicio]])*1440 -> 28 | G18: caÍda total | H18: SI | I18: NO | J18: NO | K18: NO | L18: NO | M18: NO | N18: NO | O18: SI | P18: NO | Q18: NO | R18: NO | S18: NO | T18: SI | U18: SI | V18: SI | W18: SI | X18: Matrix Tech | Y18: intermitencia en el aplicativo | Z18: sw_default con afectacion | AA18: Se realiza un reinicio controlado de los servidores, se restablece el servicio | AB18: JORGEN VALDES
A19: Enero | B19: CAIDA GENERAL EN JADE | C19: 728580 | D19: 46048.349 | E19: 46048.36 | F19: =+(disponibilidad[[#This Row],[Fecha y hora fin]]-disponibilidad[[#This Row],[Fecha y hora inicio]])*1440 -> 17 | G19: caÍda total | H19: SI | I19: NO | J19: NO | K19: NO | L19: NO | M19: NO | N19: SI | O19: NO | P19: NO | Q19: NO | R19: NO | S19: NO | T19: SI | U19: SI | V19: SI | W19: SI | X19: Matrix Tech | Y19: intermitencia en el aplicativo | Z19: sw_default con afectacion | AA19: Se realiza un reinicio controlado de los servidores, se restablece el servicio | AB19: JORGEN VALDES
A20: Enero | B20: CAIDA GENERAL CON JADE | C20: 728621 | D20: 46049.282 | E20: 46049.303 | F20: =+(disponibilidad[[#This Row],[Fecha y hora fin]]-disponibilidad[[#This Row],[Fecha y hora inicio]])*1440 -> 30 | G20: caÍda total | H20: SI | I20: NO | J20: NO | K20: NO | L20: NO | M20: NO | N20: SI | O20: NO | P20: NO | Q20: NO | R20: NO | S20: NO | T20: SI | U20: SI | V20: SI | W20: SI | X20: Matrix Tech | Y20: caida general del sistema | Z20: falla en la venta de mantenimiento BD | AA20: Se realiza rollback de proceso para no afectar mas los servicios, se valida con la red indicando normalidad | AB20: JORGEN VALDES
A21: Enero | B21: intermitencia JADE | C21: 728660 | D21: 46049.743 | E21: 46049.752 | F21: =+(disponibilidad[[#This Row],[Fecha y hora fin]]-disponibilidad[[#This Row],[Fecha y hora inicio]])*1440 -> 13 | G21: Intermitencia | H21: SI | I21: NO | J21: NO | K21: NO | L21: NO | M21: NO | N21: NO | O21: NO | P21: NO | Q21: NO | R21: SI | S21: NO | T21: SI | U21: SI | V21: SI | W21: SI | X21: Matrix Tech | Y21: intermitencia en el aplicativo | Z21: Res afectada | AA21: Se realiza un reinicio controlado de los servidores, se restablece el servicio | AB21: JORGEN VALDES
A22: Enero | B22: CAIDA GENERAL JADE | C22: 728682 | D22: 46050.515 | E22: 46050.524 | F22: =+(disponibilidad[[#This Row],[Fecha y hora fin]]-disponibilidad[[#This Row],[Fecha y hora inicio]])*1440 -> 13 | G22: caÍda total | H22: SI | I22: NO | J22: NO | K22: NO | L22: NO | M22: NO | N22: NO | O22: SI | P22: NO | Q22: NO | R22: NO | S22: NO | T22: SI | U22: SI | V22: SI | W22: SI | X22: Matrix Tech | Y22: intermitencia en el aplicativo | Z22: sw_default con afectacion | AA22: Se realiza un reinicio controlado de los servidores, se restablece el servicio | AB22: JORGEN VALDES
A23: Enero | B23: CAIDA GENERAL JADE | C23: 728759 | D23: 46052.345 | E23: 46052.357 | F23: =+(disponibilidad[[#This Row],[Fecha y hora fin]]-disponibilidad[[#This Row],[Fecha y hora inicio]])*1440 -> 17 | G23: caÍda total | H23: SI | I23: NO | J23: NO | K23: NO | L23: NO | M23: NO | N23: NO | O23: SI | P23: NO | Q23: NO | R23: NO | S23: NO | T23: SI | U23: SI | V23: SI | W23: SI | X23: Matrix Tech | Y23: intermitencia en el aplicativo | Z23: sw_default con afectacion | AA23: Se realiza un reinicio controlado de los servidores, se restablece el servicio | AB23: JORGEN VALDES
A24: Enero | B24: Error devolucion de loteria | C24: INC 2026-024889 | D24: 46052.661 | E24: 46052.701 | F24: =+(disponibilidad[[#This Row],[Fecha y hora fin]]-disponibilidad[[#This Row],[Fecha y hora inicio]])*1440 -> 58 | G24: caÍda total | H24: SI | I24: SI | J24: NO | K24: NO | L24: SI | M24: NO | N24: NO | O24: NO | P24: NO | Q24: SI | R24: NO | S24: NO | T24: NO | U24: NO | V24: SI | W24: NO | X24: Matrix Tech | Y24: afectacion de plataformas jade y siga para devolver loterias | Z24: Se identifica error de memoria en el servidor afectador el servicio. | AA24: Se realiza reinicio de la api afectada se procede a validar con la red quedando operativo el servicio | AB24: JORGEN VALDES
A25: Enero | B25: Falla GANA Web. | C25: INC 2026-025209 | D25: 46052.877 | E25: 46052.919 | F25: =+(disponibilidad[[#This Row],[Fecha y hora fin]]-disponibilidad[[#This Row],[Fecha y hora inicio]])*1440 -> 61 | G25: Intermitencia | H25: NO | I25: NO | J25: SI | K25: NO | L25: NO | M25: NO | N25: NO | O25: NO | P25: NO | Q25: SI | R25: NO | S25: NO | T25: SI | U25: NO | V25: NO | W25: NO | X25: Matrix Tech | Y25: intermitencia en el aplicativo | Z25: Se presenta lentitud para generar una compra en la web | AA25: Se realiza un reinicio controlado en el servidor brilliance estabilizando el servicio pruebas en las web quedando operativo. | AB25: JORGEN VALDES
A26: Enero | B26: Recargas y Paquetes TIGO | C26: REQ 2026-025478 | D26: 46053.488 | E26: 46053.535 | F26: =F32+(disponibilidad[[#This Row],[Fecha y hora fin]]-disponibilidad[[#This Row],[Fecha y hora inicio]])*1440 -> 85 | G26: caÍda total | H26: SI | I26: NO | J26: NO | K26: SI | L26: NO | M26: NO | N26: NO | O26: NO | P26: NO | Q26: SI | R26: NO | S26: NO | T26: NO | U26: NO | V26: NO | W26: SI | X26: Aliados o terceros | Y26: No se evidencian tx para el producto | Z26: Error al recibir respuesta por parte del aliado | AA26: Se documenta el caso adjuntando los logs del error, se devuelva a lred para su gestion con el aliado | AB26: JORGEN VALDES
A27: Febrero | B27: PAQUETES CLARO | C27: INC 2026-026131 | D27: 46055.286 | E27: 46055.289 | F27: =+(disponibilidad[[#This Row],[Fecha y hora fin]]-disponibilidad[[#This Row],[Fecha y hora inicio]])*1440 -> 4 | G27: caÍda total | H27: NO | I27: NO | J27: NO | K27: NO | L27: NO | M27: NO | N27: NO | O27: NO | P27: NO | Q27: SI | R27: NO | S27: NO | T27: NO | U27: NO | V27: NO | W27: SI | X27: Aliados o terceros | Y27: no se evidencian tx para el producto | Z27: No se evidencia ninguna afectación en la transmisión de TX | AA27: Se realizan validaciones a nivel de BD y Servidores donde se evidencia la transmisión de TX con total normalidad. | AB27: STEVEN PINTO
A28: Febrero | B28: CAIDA GENERAL CON JADE | C28: 728830 | D28: 46055.301 | E28: 46055.319 | F28: =+(disponibilidad[[#This Row],[Fecha y hora fin]]-disponibilidad[[#This Row],[Fecha y hora inicio]])*1440 -> 26 | G28: caÍda total | H28: SI | I28: NO | J28: NO | K28: NO | L28: NO | M28: NO | N28: SI | O28: NO | P28: NO | Q28: NO | R28: NO | S28: NO | T28: SI | U28: SI | V28: SI | W28: SI | X28: Matrix Tech | Y28: caida general del sistema | Z28: Afectacion en el enlace de comunicacion | AA28: Se realiza validacion por parte del area de telecomunicaciones, una vez solventada la red indica normalidad | AB28: JORGEN VALDES
A29: Febrero | B29: Caida general JADE | C29: 728832 | D29: 46055.337 | E29: 46055.368 | F29: =+(disponibilidad[[#This Row],[Fecha y hora fin]]-disponibilidad[[#This Row],[Fecha y hora inicio]])*1440 -> 45 | G29: caÍda total | H29: SI | I29: NO | J29: NO | K29: NO | L29: NO | M29: NO | N29: NO | O29: SI | P29: NO | Q29: NO | R29: NO | S29: NO | T29: SI | U29: SI | V29: SI | W29: SI | X29: Matrix Tech | Y29: caida general del sistema | Z29: Afectacion por backup en BD | AA29: Se escala novedad al area de BD para validar los BAckup que estan generando lentitud en el servicio, la cual queda solventada | AB29: JORGEN VALDES
A30: Febrero | B30: RECARGAS OPERADORES SIN TX | C30: INC 2026-030741 | D30: 46055.463 | E30: 46055.476 | F30: =+(disponibilidad[[#This Row],[Fecha y hora fin]]-disponibilidad[[#This Row],[Fecha y hora inicio]])*1440 -> 19 | G30: caÍda total | H30: NO | I30: NO | J30: NO | K30: NO | L30: NO | M30: NO | N30: NO | O30: NO | P30: NO | Q30: SI | R30: NO | S30: NO | T30: NO | U30: NO | V30: NO | W30: SI | X30: Aliados o terceros | Y30: NO se evidencian tx para el producto | Z30: Error al recibir respuesta por parte del aliado | AA30: Se documenta el caso adjuntando los logs del error, se devuelva a lred para su gestion con el aliado | AB30: JORGEN VALDES
A31: Febrero | B31: CAIDA GENERAL CON JADE | C31: 728874 | D31: 46055.591 | E31: 46055.633 | F31: =+(disponibilidad[[#This Row],[Fecha y hora fin]]-disponibilidad[[#This Row],[Fecha y hora inicio]])*1440 -> 60 | G31: caÍda total | H31: SI | I31: NO | J31: NO | K31: NO | L31: NO | M31: NO | N31: SI | O31: NO | P31: NO | Q31: NO | R31: NO | S31: NO | T31: SI | U31: SI | V31: SI | W31: SI | X31: Matrix Tech | Y31: caida general del sistema | Z31: Afectacion en el enlace de comunicacion | AA31: Se realiza validacion por parte del area de telecomunicaciones, una vez solventada la red indica normalidad | AB31: JORGEN VALDES
A32: Febrero | B32: VIRGIN Y WOM SIN TX | C32: INC 2026-028413 | D32: 46057.257 | E32: 46057.269 | F32: =+(disponibilidad[[#This Row],[Fecha y hora fin]]-disponibilidad[[#This Row],[Fecha y hora inicio]])*1440 -> 18 | G32: caÍda total | H32: NO | I32: NO | J32: NO | K32: NO | L32: NO | M32: NO | N32: NO | O32: NO | P32: NO | Q32: SI | R32: NO | S32: NO | T32: NO | U32: NO | V32: NO | W32: SI | X32: Aliados o terceros | Y32: No se evidencian tx para el producto | Z32: No se evidencia ninguna afectación en la transmisión de TX | AA32: Se realizan validaciones a nivel de BD y Servidores donde se evidencia la transmisión de TX con total normalidad. | AB32: OSCAR FARID NAIZZIR
A33: Febrero | B33: COLORLOTO SIN TX | C33: INC 2026-028703 | D33: 46057.442 | E33: 46057.447 | F33: =+(disponibilidad[[#This Row],[Fecha y hora fin]]-disponibilidad[[#This Row],[Fecha y hora inicio]])*1440 -> 6 | G33: caÍda total | H33: NO | I33: NO | J33: NO | K33: NO | L33: NO | M33: NO | N33: NO | O33: NO | P33: NO | Q33: SI | R33: NO | S33: NO | T33: SI | U33: NO | V33: NO | W33: NO | X33: Matrix Tech | Y33: No se evidencian tx para el producto | Z33: No se evidencia ninguna afectación en la transmisión de TX | AA33: Se realizan validaciones a nivel de BD y Servidores donde se evidencia la transmisión de TX con total normalidad. | AB33: OSCAR FARID NAIZZIR
A34: Febrero | B34: RECARGAS METRO | C34: INC 2026-035446 | D34: 46065.333 | E34: 46065.368 | F34: =+(disponibilidad[[#This Row],[Fecha y hora fin]]-disponibilidad[[#This Row],[Fecha y hora inicio]])*1440 -> 50 | G34: caÍda total | H34: NO | I34: NO | J34: NO | K34: NO | L34: NO | M34: NO | N34: NO | O34: NO | P34: NO | Q34: SI | R34: NO | S34: NO | T34: NO | U34: NO | V34: NO | W34: SI | X34: Aliados o terceros | Y34: No se evidencian tx para el producto | Z34: Enlace (VPN) caido por parte del aliado | AA34: Se documenta el caso adjuntando los logs del error, se devuelva a lred para su gestion con el aliado | AB34: NICOLAS QUIROGA
A35: Febrero | B35: RECARGAS METRO | C35: INC 2026-026709 | D35: 46055.56 | E35: 46055.569 | F35: =+(disponibilidad[[#This Row],[Fecha y hora fin]]-disponibilidad[[#This Row],[Fecha y hora inicio]])*1440 -> 12 | G35: caÍda total | H35: NO | I35: NO | J35: NO | K35: NO | L35: NO | M35: NO | N35: NO | O35: NO | P35: NO | Q35: SI | R35: NO | S35: NO | T35: NO | U35: NO | V35: SI | W35: NO | X35: Aliados o terceros | Y35: no se evidencian tx para el producto | Z35: No se evidencia ninguna afectación en la transmisión de TX | AA35: Se realizan validaciones a nivel de BD y Servidores donde se evidencia la transmisión de TX con total normalidad. | AB35: STEVEN PINTO
A36: Febrero | B36: Recargas y Paquetes TIGO | C36: INC 2026-027219 | D36: 46056.257 | E36: 46056.269 | F36: =+(disponibilidad[[#This Row],[Fecha y hora fin]]-disponibilidad[[#This Row],[Fecha y hora inicio]])*1440 -> 17 | G36: caÍda total | H36: NO | I36: NO | J36: NO | K36: NO | L36: NO | M36: NO | N36: NO | O36: NO | P36: NO | Q36: SI | R36: NO | S36: NO | T36: NO | U36: NO | V36: NO | W36: SI | X36: Aliados o terceros | Y36: no se evidencian tx para el producto | Z36: No se evidencia ninguna afectación en la transmisión de TX | AA36: Se realizan validaciones a nivel de BD y Servidores donde se evidencia la transmisión de TX con total normalidad. | AB36: STEVEN PINTO
A37: Febrero | B37: RECAUDO EPM SIN TX | C37: INC 2026-027220 | D37: 46056.256 | E37: 46056.269 | F37: =+(disponibilidad[[#This Row],[Fecha y hora fin]]-disponibilidad[[#This Row],[Fecha y hora inicio]])*1440 -> 19 | G37: caÍda total | H37: NO | I37: NO | J37: NO | K37: NO | L37: NO | M37: NO | N37: NO | O37: NO | P37: NO | Q37: SI | R37: NO | S37: NO | T37: NO | U37: NO | V37: SI | W37: NO | X37: Aliados o terceros | Y37: no se evidencian tx para el producto | Z37: No se evidencia ninguna afectación en la transmisión de TX | AA37: Se realizan validaciones a nivel de BD y Servidores donde se evidencia la transmisión de TX con total normalidad. | AB37: STEVEN PINTO
A38: Febrero | B38: Baloto, mi loto y raspa y listo sin tx | C38: REQ 2026-027222 | D38: 46056.256 | E38: 46056.268 | F38: =+(disponibilidad[[#This Row],[Fecha y hora fin]]-disponibilidad[[#This Row],[Fecha y hora inicio]])*1440 -> 17 | G38: caÍda total | H38: NO | I38: NO | J38: NO | K38: NO | L38: NO | M38: NO | N38: NO | O38: NO | P38: NO | Q38: SI | R38: NO | S38: NO | T38: SI | U38: NO | V38: NO | W38: NO | X38: Aliados o terceros | Y38: no se evidencian tx para el producto | Z38: No se evidencia ninguna afectación en la transmisión de TX | AA38: Se realizan validaciones a nivel de BD y Servidores donde se evidencia la transmisión de TX con total normalidad. | AB38: STEVEN PINTO
A39: Febrero | B39: RECARGAS METRO | C39: INC 2026-026505 | D39: 46055.475 | E39: 46055.569 | F39: =+(disponibilidad[[#This Row],[Fecha y hora fin]]-disponibilidad[[#This Row],[Fecha y hora inicio]])*1440 -> 135 | G39: Intermitencia | H39: NO | I39: NO | J39: NO | K39: NO | L39: NO | M39: NO | N39: NO | O39: NO | P39: NO | Q39: SI | R39: NO | S39: NO | T39: NO | U39: NO | V39: SI | W39: NO | X39: Aliados o terceros | Y39: no se evidencian tx para el producto | Z39: No se evidencia ninguna afectación en la transmisión de TX | AA39: Se realizan validaciones a nivel de BD y Servidores donde se evidencia la transmisión de TX con total normalidad. | AB39: STEVEN PINTO
A40: Febrero | B40: operadores wom y virgin sin tx | C40: INC 2026-028413 | D40: 46057.258 | E40: 46057.269 | F40: =+(disponibilidad[[#This Row],[Fecha y hora fin]]-disponibilidad[[#This Row],[Fecha y hora inicio]])*1440 -> 17 | G40: caÍda total | H40: NO | I40: NO | J40: NO | K40: NO | L40: NO | M40: NO | N40: NO | O40: NO | P40: NO | Q40: SI | R40: NO | S40: NO | T40: NO | U40: NO | V40: NO | W40: SI | X40: Aliados o terceros | Y40: no se evidencian tx para el producto | Z40: No se evidencia ninguna afectación en la transmisión de TX | AA40: Se realizan validaciones a nivel de BD y Servidores donde se evidencia la transmisión de TX con total normalidad. | AB40: STEVEN PINTO
A41: Febrero | B41: COLORLOTO SIN TX | C41: INC 2026-028703 | D41: 46057.442 | E41: 46057.449 | F41: =+(disponibilidad[[#This Row],[Fecha y hora fin]]-disponibilidad[[#This Row],[Fecha y hora inicio]])*1440 -> 10 | G41: caÍda total | H41: NO | I41: NO | J41: NO | K41: NO | L41: NO | M41: NO | N41: NO | O41: NO | P41: NO | Q41: SI | R41: NO | S41: NO | T41: SI | U41: NO | V41: NO | W41: NO | X41: Matrix Tech | Y41: No se evidencian tx para el producto | Z41: No se evidencia ninguna afectación en la transmisión de TX | AA41: Se realizan validaciones a nivel de BD y Servidores donde se evidencia la transmisión de TX con total normalidad. | AB41: STEVEN PINTO
A42: Febrero | B42: Baloto, mi lotosin tx | C42: REQ 2026-029372 | D42: 46058.256 | E42: 46058.272 | F42: =+(disponibilidad[[#This Row],[Fecha y hora fin]]-disponibilidad[[#This Row],[Fecha y hora inicio]])*1440 -> 23 | G42: caÍda total | H42: NO | I42: NO | J42: NO | K42: NO | L42: NO | M42: NO | N42: NO | O42: NO | P42: NO | Q42: SI | R42: NO | S42: NO | T42: SI | U42: NO | V42: NO | W42: NO | X42: Aliados o terceros | Y42: no se evidencian tx para el producto | Z42: No se evidencia ninguna afectación en la transmisión de TX | AA42: Se realizan validaciones a nivel de BD y Servidores donde se evidencia la transmisión de TX con total normalidad. | AB42: STEVEN PINTO
A43: Febrero | B43: movil exto sin tx y recargas directv | C43: REQ 2026-029373 | D43: 46058.256 | E43: 46058.272 | F43: =+(disponibilidad[[#This Row],[Fecha y hora fin]]-disponibilidad[[#This Row],[Fecha y hora inicio]])*1440 -> 23 | G43: caÍda total | H43: NO | I43: NO | J43: NO | K43: NO | L43: NO | M43: NO | N43: NO | O43: NO | P43: NO | Q43: SI | R43: NO | S43: NO | T43: NO | U43: NO | V43: NO | W43: SI | X43: Aliados o terceros | Y43: no se evidencian tx para el producto | Z43: No se evidencia ninguna afectación en la transmisión de TX | AA43: Se realizan validaciones a nivel de BD y Servidores donde se evidencia la transmisión de TX con total normalidad. | AB43: STEVEN PINTO
... A45: Febrero | B45: raspa y listo LM sin tx | C45: INC 2026-029551 | D45: 46058.396 | E45: 46058.45 | F45: =+(disponibilidad[[#This Row],[Fecha y hora fin]]-disponibilidad[[#This Row],[Fecha y hora inicio]])*1440 -> 78 | G45: caÍda total | H45: NO | I45: NO | J45: NO | K45: NO | L45: NO | M45: NO | N45: NO | O45: NO | P45: NO | Q45: SI | R45: NO | S45: NO | T45: SI | U45: NO | V45: NO | W45: NO | X45: Aliados o terceros | Y45: no se evidencian tx para el producto | Z45: No se evidencia ninguna afectación en la transmisión de TX | AA45: Se realizan validaciones a nivel de BD y Servidores donde se evidencia la transmisión de TX con total normalidad. | AB45: STEVEN PINTO
A46: Febrero | B46: intermitencia en jade | C46: 729043 | D46: 46058.783 | E46: 46058.807 | F46: =+(disponibilidad[[#This Row],[Fecha y hora fin]]-disponibilidad[[#This Row],[Fecha y hora inicio]])*1440 -> 34 | G46: Intermitencia | H46: SI | I46: NO | J46: NO | K46: NO | L46: NO | M46: NO | N46: NO | O46: NO | P46: NO | Q46: NO | R46: SI | S46: NO | T46: SI | U46: SI | V46: SI | W46: SI | X46: Matrix Tech | Y46: intermitencia en el aplicativo | Z46: sw_default con afectacion | AA46: Se realiza reinicio controlado del sw_default, se procede a validar nuevamente quedando operativo | AB46: JORGEN VALDES
A47: febrero | B47: GANA WEB SIN TX | C47: INC 2026-030339 | D47: 46058.812 | E47: 46058.875 | F47: =+(disponibilidad[[#This Row],[Fecha y hora fin]]-disponibilidad[[#This Row],[Fecha y hora inicio]])*1440 -> 90 | G47: caÍda total | H47: NO | I47: NO | J47: SI | K47: NO | L47: NO | M47: NO | N47: NO | O47: NO | P47: NO | Q47: SI | R47: NO | S47: NO | T47: SI | U47: NO | V47: NO | W47: NO | X47: Matrix Tech | Y47: no se evidencian tx para el producto | Z47: reCAPTCHA Enterprise ya se pasó del cupo gratuito | AA47: Se valida con las diferentes areas para que se realize una activacion a la cuenta de facturacion y seguir utilizando el reCAPTCHA | AB47: JORGEN VALDES
A48: Febrero | B48: CAIDA GENERAL JADE | C48: 729129 | D48: 46062.356 | E48: 46062.366 | F48: =+(disponibilidad[[#This Row],[Fecha y hora fin]]-disponibilidad[[#This Row],[Fecha y hora inicio]])*1440 -> 15 | G48: Intermitencia | H48: SI | I48: NO | J48: NO | K48: NO | L48: NO | M48: NO | N48: NO | O48: SI | P48: NO | Q48: NO | R48: NO | S48: NO | T48: SI | U48: SI | V48: SI | W48: SI | X48: Matrix Tech | Y48: intermitencia en el aplicativo | Z48: Res afectada | AA48: Se realiza reinicio controlado del sw_default, se procede a validar nuevamente quedando operativo | AB48: JORGEN VALDES
A49: Febrero | B49: Caida general JADE | C49: 729154 | D49: 46062.726 | E49: 46062.75 | F49: =+(disponibilidad[[#This Row],[Fecha y hora fin]]-disponibilidad[[#This Row],[Fecha y hora inicio]])*1440 -> 34 | G49: caÍda total | H49: SI | I49: NO | J49: NO | K49: NO | L49: NO | M49: NO | N49: NO | O49: SI | P49: NO | Q49: NO | R49: NO | S49: NO | T49: SI | U49: SI | V49: SI | W49: SI | X49: Matrix Tech | Y49: Caida general del sistema | Z49: Afectacion de internet | AA49: Se realiza validacion por parte de telecomunicaciones, solventando la novedad de la red | AB49: JORGEN VALDES
A50: Febrero | B50: Intermitencia con la platafoma de Jade | C50: 729209 | D50: 46064.356 | E50: 46064.368 | F50: =+(disponibilidad[[#This Row],[Fecha y hora fin]]-disponibilidad[[#This Row],[Fecha y hora inicio]])*1440 -> 18 | G50: Intermitencia | H50: SI | I50: NO | J50: NO | K50: NO | L50: NO | M50: SI | N50: NO | O50: NO | P50: NO | Q50: NO | R50: NO | S50: NO | T50: SI | U50: SI | V50: SI | W50: SI | X50: Matrix Tech | Y50: intermitencia en el aplicativo | Z50: Res afectada | AA50: Se realiza reinicio controlado del sw_default, se procede a validar nuevamente | AB50: JORGEN VALDES
A51: Febrero | B51: VALIDACION JADE | C51: 729225 | D51: 46064.469 | E51: 46064.486 | F51: =+(disponibilidad[[#This Row],[Fecha y hora fin]]-disponibilidad[[#This Row],[Fecha y hora inicio]])*1440 -> 25 | G51: caÍda total | H51: SI | I51: SI | J51: NO | K51: NO | L51: NO | M51: NO | N51: NO | O51: NO | P51: NO | Q51: NO | R51: SI | S51: NO | T51: SI | U51: SI | V51: SI | W51: SI | X51: Matrix Tech | Y51: Caida general del sistema | Z51: Picos de tx ocasionan lentitud e intermitencia del aplicativo | AA51: Se valida con el equipo de base de datos el cual realiza gestion sobre la red, estabilizando la novedad | AB51: JORGEN VALDES
A52: Febrero | B52: CAIDA GENERAL EN JADE | C52: 729236 | D52: 46064.63 | E52: 46064.658 | F52: =+(disponibilidad[[#This Row],[Fecha y hora fin]]-disponibilidad[[#This Row],[Fecha y hora inicio]])*1440 -> 40 | G52: caÍda total | H52: SI | I52: NO | J52: NO | K52: NO | L52: NO | M52: NO | N52: NO | O52: NO | P52: NO | Q52: NO | R52: NO | S52: SI | T52: SI | U52: SI | V52: SI | W52: SI | X52: Matrix Tech | Y52: Caida general del sistema | Z52: Novedad en los SW | AA52: Se realiza reinicio controlado de los sw_default de la red, quedando operativo el sistema | AB52: JORGEN VALDES
A53: Febrero | B53: operador movistar sin tx | C53: INC 2026-046051 | D53: 46077.294 | E53: 46077.308 | F53: =+(disponibilidad[[#This Row],[Fecha y hora fin]]-disponibilidad[[#This Row],[Fecha y hora inicio]])*1440 -> 21 | G53: Intermitencia | H53: NO | I53: NO | J53: NO | K53: NO | L53: NO | M53: NO | N53: NO | O53: NO | P53: NO | Q53: SI | R53: NO | S53: NO | T53: NO | U53: NO | V53: NO | W53: SI | X53: Aliados o terceros | Y53: no se evidencian tx para el producto | Z53: No se evidencia ninguna afectación en la transmisión de TX | AA53: Se realizan validaciones a nivel de BD y Servidores donde se evidencia la transmisión de TX con total normalidad. | AB53: JORGEN VALDES
A54: Marzo | B54: GANA WEB | C54: INC 2026-054865 | D54: 46085.613 | E54: 46085.676 | F54: =+(disponibilidad[[#This Row],[Fecha y hora fin]]-disponibilidad[[#This Row],[Fecha y hora inicio]])*1440 -> 90 | G54: caÍda total | H54: NO | I54: NO | J54: SI | K54: NO | L54: NO | M54: NO | N54: NO | O54: NO | P54: NO | Q54: SI | R54: NO | S54: NO | T54: SI | U54: NO | V54: NO | W54: NO | X54: Aliados o terceros | Y54: no se evidencian tx para el producto | Z54: Error de conexion , fallas de internet del proveedor internet liberty | AA54: Se documenta el caso adjuntando los logs del error, se devuelva a lred para su gestion con el aliado | AB54: NICOLAS QUIROGA
A55: Marzo | B55: JADE | C55: 729948 | D55: 46091.472 | E55: 46091.479 | F55: =+(disponibilidad[[#This Row],[Fecha y hora fin]]-disponibilidad[[#This Row],[Fecha y hora inicio]])*1440 -> 10 | G55: Intermitencia | H55: SI | I55: NO | J55: NO | K55: NO | L55: NO | M55: NO | N55: NO | O55: NO | P55: NO | Q55: NO | R55: SI | S55: NO | T55: SI | U55: SI | V55: SI | W55: SI | X55: Matrix Tech | Y55: Caida general del sistema | Z55: Consumos elevados de recursos de BD debido a la copia del backup de las BD a cinta | AA55: Se realiza reinicio controlado de los sw_default de la red, quedando operativo el sistema | AB55: NICOLAS QUIROGA
A56: marzo | B56: Recargas sin TX | C56: INC 2026-061862 | D56: 46091.621 | F56: =+(disponibilidad[[#This Row],[Fecha y hora fin]]-disponibilidad[[#This Row],[Fecha y hora inicio]])*1440 -> -66371934 | G56: caÍda total | H56: SI | I56: NO | J56: NO | K56: NO | L56: NO | M56: NO | N56: NO | O56: NO | P56: NO | Q56: SI | R56: NO | S56: NO | T56: NO | U56: NO | V56: NO | W56: SI | X56: Aliados o terceros | Y56: no se evidencian tx para el producto
F57: =+(disponibilidad[[#This Row],[Fecha y hora fin]]-disponibilidad[[#This Row],[Fecha y hora inicio]])*1440 -> 0
F58: =+(disponibilidad[[#This Row],[Fecha y hora fin]]-disponibilidad[[#This Row],[Fecha y hora inicio]])*1440 -> 0
F59: =+(disponibilidad[[#This Row],[Fecha y hora fin]]-disponibilidad[[#This Row],[Fecha y hora inicio]])*1440 -> 0
F60: =+(disponibilidad[[#This Row],[Fecha y hora fin]]-disponibilidad[[#This Row],[Fecha y hora inicio]])*1440 -> 0
F61: =+(disponibilidad[[#This Row],[Fecha y hora fin]]-disponibilidad[[#This Row],[Fecha y hora inicio]])*1440 -> 0
F62: =+(disponibilidad[[#This Row],[Fecha y hora fin]]-disponibilidad[[#This Row],[Fecha y hora inicio]])*1440 -> 0
F63: =+(disponibilidad[[#This Row],[Fecha y hora fin]]-disponibilidad[[#This Row],[Fecha y hora inicio]])*1440 -> 0
F64: =+(disponibilidad[[#This Row],[Fecha y hora fin]]-disponibilidad[[#This Row],[Fecha y hora inicio]])*1440 -> 0
F65: =+(disponibilidad[[#This Row],[Fecha y hora fin]]-disponibilidad[[#This Row],[Fecha y hora inicio]])*1440 -> 0
F66: =+(disponibilidad[[#This Row],[Fecha y hora fin]]-disponibilidad[[#This Row],[Fecha y hora inicio]])*1440 -> 0
F67: =+(disponibilidad[[#This Row],[Fecha y hora fin]]-disponibilidad[[#This Row],[Fecha y hora inicio]])*1440 -> 0
F68: =+(disponibilidad[[#This Row],[Fecha y hora fin]]-disponibilidad[[#This Row],[Fecha y hora inicio]])*1440 -> 0
... F6998: =+(disponibilidad[[#This Row],[Fecha y hora fin]]-disponibilidad[[#This Row],[Fecha y hora inicio]])*1440 -> 0

Sheet SuChance - Huila
E1: SGSI | L1: Código | N1: FR-GDO-013
E2: FORMATO | L2: Versión | N2: 0
E3: BITÁCORA DISPONIBILIDAD DE PRODUCTOS | L3: Fecha | N3: 45525
B5: Mes | C5: Minutos Mes | D5: Disponibilidad Individual Aplicación Matrix Tech | F5: Disponibilidad General Aplicación | G5: Disponibilidad Indivudual Producto UX TECHNOLOGY | K5: Disponibilidad General Producto | L5: Disponibilidad Indivudual Producto Aliados o Terceros | O5: Disponibilidad General Producto | P5: UX TECHNOLOGY | R5: Aliados - Terceros
D6: JADE | E6: SIGA | G6: Apuestas - Chance | H6: PAGOS | I6: RECAUDOS | J6: RECARGAS | L6: PAGOS | M6: RECAUDOS | N6: RECARGAS | P6: Tiempo Indisponibiliad | Q6: % Indisponibiliad | R6: Tiempo Indisponibiliad | S6: % Indisponibiliad
C7: AST/Peso | D7: 0.97 | E7: 0.03 | G7: 0.57 | H7: 0.03 | I7: 0.1 | J7: 0.3 | K7: =SUM(G7:J7) -> 1 | X7: MES | Y7: Mayo
B8: Enero | C8: =VLOOKUP(B8,Maestro!$A$7:$D$19,4,FALSE) -> 44640 | D8: =+(($C8-(SUMIFS(disponibilidad[Tiempo falla (en Mintuos)],disponibilidad[JADE],"SI",disponibilidad[Mes],$B8,disponibilidad[[Tipo de afectación ]],"caÍda total",disponibilidad[Responsable Falla],"Matrix Tech",disponibilidad[Suchance - Huila],"SI")))/$C8)*100 -> 99.870072 | E8: =+(($C8-(SUMIFS(disponibilidad[Tiempo falla (en Mintuos)],disponibilidad[SIGA],"SI",disponibilidad[Mes],$B8,disponibilidad[[Tipo de afectación ]],"caÍda total",disponibilidad[Responsable Falla],"Matrix Tech",disponibilidad[Suchance - Huila],"SI")))/$C8)*100 -> 100 | F8: =SUMPRODUCT($D$7:$E$7,D8:E8)/$K$7 -> 99.87397 | G8: =+(($C8-(SUMIFS(disponibilidad[Tiempo falla (en Mintuos)],disponibilidad[Apuestas - Chance],"SI",disponibilidad[Mes],$B8,disponibilidad[[Tipo de afectación ]],"caÍda total",disponibilidad[Responsable Falla],"Matrix Tech",disponibilidad[Suchance - Huila],"SI")))/$C8)*100 -> 99.870072 | H8: =+(($C8-(SUMIFS(disponibilidad[Tiempo falla (en Mintuos)],disponibilidad[PAGOS],"SI",disponibilidad[Mes],$B8,disponibilidad[[Tipo de afectación ]],"caÍda total",disponibilidad[Responsable Falla],"Matrix Tech",disponibilidad[Suchance - Huila],"SI")))/$C8)*100 -> 99.870072 | I8: =+(($C8-(SUMIFS(disponibilidad[Tiempo falla (en Mintuos)],disponibilidad[RECAUDOS],"SI",disponibilidad[Mes],$B8,disponibilidad[[Tipo de afectación ]],"caÍda total",disponibilidad[Responsable Falla],"Matrix Tech",disponibilidad[Suchance - Huila],"SI")))/$C8)*100 -> 99.870072 | J8: =+(($C8-(SUMIFS(disponibilidad[Tiempo falla (en Mintuos)],disponibilidad[RECARGAS],"SI",disponibilidad[Mes],$B8,disponibilidad[[Tipo de afectación ]],"caÍda total",disponibilidad[Responsable Falla],"Matrix Tech",disponibilidad[Suchance - Huila],"SI")))/$C8)*100 -> 99.870072 | K8: =SUMPRODUCT($G$7:$J$7,G8:J8)/$K$7 -> 99.870072 | L8: =+(($C8-(SUMIFS(disponibilidad[Tiempo falla (en Mintuos)],disponibilidad[PAGOS],"SI",disponibilidad[Mes],$B8,disponibilidad[[Tipo de afectación ]],"caÍda total",disponibilidad[Responsable Falla],"Aliados o terceros",disponibilidad[Suchance - Huila],"SI")))/$C8)*100 -> 100 | M8: =+(($C8-(SUMIFS(disponibilidad[Tiempo falla (en Mintuos)],disponibilidad[RECAUDOS],"SI",disponibilidad[Mes],$B8,disponibilidad[[Tipo de afectación ]],"caÍda total",disponibilidad[Responsable Falla],"Aliados o terceros",disponibilidad[Suchance - Huila],"SI")))/$C8)*100 -> 100 | N8: =+(($C8-(SUMIFS(disponibilidad[Tiempo falla (en Mintuos)],disponibilidad[RECARGAS],"SI",disponibilidad[Mes],$B8,disponibilidad[[Tipo de afectación ]],"caÍda total",disponibilidad[Responsable Falla],"Aliados o terceros",disponibilidad[Suchance - Huila],"SI")))/$C8)*100 -> 100 | O8: =AVERAGE(L8:N8) -> 100 | P8: =SUMIFS(disponibilidad[Tiempo falla (en Mintuos)],disponibilidad[Mes],$B8,disponibilidad[[Tipo de afectación ]],"caÍda total",disponibilidad[Responsable Falla],"Matrix Tech",disponibilidad[Suchance - Huila],"SI") -> 58 | Q8: =+$P$8/$C$8 -> 0.0012992832 | R8: =SUMIFS(disponibilidad[Tiempo falla (en Mintuos)],disponibilidad[Mes],$B8,disponibilidad[[Tipo de afectación ]],"caÍda total",disponibilidad[Responsable Falla],"Aliados o terceros",disponibilidad[Acertemos - Cauca],"SI") -> 0 | S8: =+$R$8/$C$8 -> 0
B9: Febrero | C9: =VLOOKUP(B9,Maestro!$A$7:$D$19,4,FALSE) -> 41760 | D9: =+(($C9-(SUMIFS(disponibilidad[Tiempo falla (en Mintuos)],disponibilidad[JADE],"SI",disponibilidad[Mes],$B9,disponibilidad[[Tipo de afectación ]],"caÍda total",disponibilidad[Responsable Falla],"Matrix Tech",disponibilidad[Suchance - Huila],"SI")))/$C9)*100 -> 99.810824 | E9: =+(($C9-(SUMIFS(disponibilidad[Tiempo falla (en Mintuos)],disponibilidad[SIGA],"SI",disponibilidad[Mes],$B9,disponibilidad[[Tipo de afectación ]],"caÍda total",disponibilidad[Responsable Falla],"Matrix Tech",disponibilidad[Suchance - Huila],"SI")))/$C9)*100 -> 100 | F9: =SUMPRODUCT($D$7:$E$7,D9:E9)/$K$7 -> 99.816499 | G9: =+(($C9-(SUMIFS(disponibilidad[Tiempo falla (en Mintuos)],disponibilidad[Apuestas - Chance],"SI",disponibilidad[Mes],$B9,disponibilidad[[Tipo de afectación ]],"caÍda total",disponibilidad[Responsable Falla],"Matrix Tech",disponibilidad[Suchance - Huila],"SI")))/$C9)*100 -> 99.810824 | H9: =+(($C9-(SUMIFS(disponibilidad[Tiempo falla (en Mintuos)],disponibilidad[PAGOS],"SI",disponibilidad[Mes],$B9,disponibilidad[[Tipo de afectación ]],"caÍda total",disponibilidad[Responsable Falla],"Matrix Tech",disponibilidad[Suchance - Huila],"SI")))/$C9)*100 -> 99.810824 | I9: =+(($C9-(SUMIFS(disponibilidad[Tiempo falla (en Mintuos)],disponibilidad[RECAUDOS],"SI",disponibilidad[Mes],$B9,disponibilidad[[Tipo de afectación ]],"caÍda total",disponibilidad[Responsable Falla],"Matrix Tech",disponibilidad[Suchance - Huila],"SI")))/$C9)*100 -> 99.810824 | J9: =+(($C9-(SUMIFS(disponibilidad[Tiempo falla (en Mintuos)],disponibilidad[RECARGAS],"SI",disponibilidad[Mes],$B9,disponibilidad[[Tipo de afectación ]],"caÍda total",disponibilidad[Responsable Falla],"Matrix Tech",disponibilidad[Suchance - Huila],"SI")))/$C9)*100 -> 99.810824 | K9: =SUMPRODUCT($G$7:$J$7,G9:J9)/$K$7 -> 99.810824 | L9: =+(($C9-(SUMIFS(disponibilidad[Tiempo falla (en Mintuos)],disponibilidad[PAGOS],"SI",disponibilidad[Mes],$B9,disponibilidad[[Tipo de afectación ]],"caÍda total",disponibilidad[Responsable Falla],"Aliados o terceros",disponibilidad[Acertemos - Cauca],"SI")))/$C9)*100 -> 100 | M9: =+(($C9-(SUMIFS(disponibilidad[Tiempo falla (en Mintuos)],disponibilidad[RECAUDOS],"SI",disponibilidad[Mes],$B9,disponibilidad[[Tipo de afectación ]],"caÍda total",disponibilidad[Responsable Falla],"Aliados o terceros",disponibilidad[Acertemos - Cauca],"SI")))/$C9)*100 -> 100 | N9: =+(($C9-(SUMIFS(disponibilidad[Tiempo falla (en Mintuos)],disponibilidad[RECARGAS],"SI",disponibilidad[Mes],$B9,disponibilidad[[Tipo de afectación ]],"caÍda total",disponibilidad[Responsable Falla],"Aliados o terceros",disponibilidad[Acertemos - Cauca],"SI")))/$C9)*100 -> 100 | O9: =AVERAGE(L9:N9) -> 100 | P9: =SUMIFS(disponibilidad[Tiempo falla (en Mintuos)],disponibilidad[Mes],$B9,disponibilidad[[Tipo de afectación ]],"caÍda total",disponibilidad[Responsable Falla],"Matrix Tech",disponibilidad[Suchance - Huila],"SI") -> 79 | Q9: =+P9/C9 -> 0.0018917625 | R9: =SUMIFS(disponibilidad[Tiempo falla (en Mintuos)],disponibilidad[Mes],$B9,disponibilidad[[Tipo de afectación ]],"caÍda total",disponibilidad[Responsable Falla],"Aliados o terceros",disponibilidad[Acertemos - Cauca],"SI") -> 0 | S9: =+$R$8/$C$8 -> 0 | X9: JADE | Y9: =VLOOKUP($Y$7,$B$8:$R$17,3,FALSE) -> 100
B10: Marzo | C10: =VLOOKUP(B10,Maestro!$A$7:$D$19,4,FALSE) -> 44640 | D10: =+(($C10-(SUMIFS(disponibilidad[Tiempo falla (en Mintuos)],disponibilidad[JADE],"SI",disponibilidad[Mes],$B10,disponibilidad[[Tipo de afectación ]],"caÍda total",disponibilidad[Responsable Falla],"Matrix Tech",disponibilidad[Suchance - Huila],"SI")))/$C10)*100 -> 100 | E10: =+(($C10-(SUMIFS(disponibilidad[Tiempo falla (en Mintuos)],disponibilidad[SIGA],"SI",disponibilidad[Mes],$B10,disponibilidad[[Tipo de afectación ]],"caÍda total",disponibilidad[Responsable Falla],"Matrix Tech",disponibilidad[Suchance - Huila],"SI")))/$C10)*100 -> 100 | F10: =SUMPRODUCT($D$7:$E$7,D10:E10)/$K$7 -> 100 | G10: =+(($C10-(SUMIFS(disponibilidad[Tiempo falla (en Mintuos)],disponibilidad[Apuestas - Chance],"SI",disponibilidad[Mes],$B10,disponibilidad[[Tipo de afectación ]],"caÍda total",disponibilidad[Responsable Falla],"Matrix Tech",disponibilidad[Suchance - Huila],"SI")))/$C10)*100 -> 100 | H10: =+(($C10-(SUMIFS(disponibilidad[Tiempo falla (en Mintuos)],disponibilidad[PAGOS],"SI",disponibilidad[Mes],$B10,disponibilidad[[Tipo de afectación ]],"caÍda total",disponibilidad[Responsable Falla],"Matrix Tech",disponibilidad[Suchance - Huila],"SI")))/$C10)*100 -> 100 | I10: =+(($C10-(SUMIFS(disponibilidad[Tiempo falla (en Mintuos)],disponibilidad[RECAUDOS],"SI",disponibilidad[Mes],$B10,disponibilidad[[Tipo de afectación ]],"caÍda total",disponibilidad[Responsable Falla],"Matrix Tech",disponibilidad[Suchance - Huila],"SI")))/$C10)*100 -> 100 | J10: =+(($C10-(SUMIFS(disponibilidad[Tiempo falla (en Mintuos)],disponibilidad[RECARGAS],"SI",disponibilidad[Mes],$B10,disponibilidad[[Tipo de afectación ]],"caÍda total",disponibilidad[Responsable Falla],"Matrix Tech",disponibilidad[Suchance - Huila],"SI")))/$C10)*100 -> 100 | K10: =SUMPRODUCT($G$7:$J$7,G10:J10)/$K$7 -> 100 | L10: =+(($C10-(SUMIFS(disponibilidad[Tiempo falla (en Mintuos)],disponibilidad[PAGOS],"SI",disponibilidad[Mes],$B10,disponibilidad[[Tipo de afectación ]],"caÍda total",disponibilidad[Responsable Falla],"Aliados o terceros",disponibilidad[Acertemos - Cauca],"SI")))/$C10)*100 -> 100 | M10: =+(($C10-(SUMIFS(disponibilidad[Tiempo falla (en Mintuos)],disponibilidad[RECAUDOS],"SI",disponibilidad[Mes],$B10,disponibilidad[[Tipo de afectación ]],"caÍda total",disponibilidad[Responsable Falla],"Aliados o terceros",disponibilidad[Acertemos - Cauca],"SI")))/$C10)*100 -> 100 | N10: =+(($C10-(SUMIFS(disponibilidad[Tiempo falla (en Mintuos)],disponibilidad[RECARGAS],"SI",disponibilidad[Mes],$B10,disponibilidad[[Tipo de afectación ]],"caÍda total",disponibilidad[Responsable Falla],"Aliados o terceros",disponibilidad[Acertemos - Cauca],"SI")))/$C10)*100 -> 100 | O10: =AVERAGE(L10:N10) -> 100 | P10: =SUMIFS(disponibilidad[Tiempo falla (en Mintuos)],disponibilidad[Mes],$B10,disponibilidad[[Tipo de afectación ]],"caÍda total",disponibilidad[Responsable Falla],"Matrix Tech",disponibilidad[Suchance - Huila],"SI") -> 0 | Q10: =+P10/C10 -> 0 | R10: =SUMIFS(disponibilidad[Tiempo falla (en Mintuos)],disponibilidad[Mes],$B10,disponibilidad[[Tipo de afectación ]],"caÍda total",disponibilidad[Responsable Falla],"Aliados o terceros",disponibilidad[Acertemos - Cauca],"SI") -> 0 | S10: =+$R$8/$C$8 -> 0 | X10: SIGA | Y10: =VLOOKUP($Y$7,$B$8:$R$17,4,FALSE) -> 100
B11: Abril | C11: =VLOOKUP(B11,Maestro!$A$7:$D$19,4,FALSE) -> 43200 | D11: =+(($C11-(SUMIFS(disponibilidad[Tiempo falla (en Mintuos)],disponibilidad[JADE],"SI",disponibilidad[Mes],$B11,disponibilidad[[Tipo de afectación ]],"caÍda total",disponibilidad[Responsable Falla],"Matrix Tech",disponibilidad[Suchance - Huila],"SI")))/$C11)*100 -> 100 | E11: =+(($C11-(SUMIFS(disponibilidad[Tiempo falla (en Mintuos)],disponibilidad[SIGA],"SI",disponibilidad[Mes],$B11,disponibilidad[[Tipo de afectación ]],"caÍda total",disponibilidad[Responsable Falla],"Matrix Tech",disponibilidad[Suchance - Huila],"SI")))/$C11)*100 -> 100 | F11: =SUMPRODUCT($D$7:$E$7,D11:E11)/$K$7 -> 100 | G11: =+(($C11-(SUMIFS(disponibilidad[Tiempo falla (en Mintuos)],disponibilidad[Apuestas - Chance],"SI",disponibilidad[Mes],$B11,disponibilidad[[Tipo de afectación ]],"caÍda total",disponibilidad[Responsable Falla],"Matrix Tech",disponibilidad[Suchance - Huila],"SI")))/$C11)*100 -> 100 | H11: =+(($C11-(SUMIFS(disponibilidad[Tiempo falla (en Mintuos)],disponibilidad[PAGOS],"SI",disponibilidad[Mes],$B11,disponibilidad[[Tipo de afectación ]],"caÍda total",disponibilidad[Responsable Falla],"Matrix Tech",disponibilidad[Suchance - Huila],"SI")))/$C11)*100 -> 100 | I11: =+(($C11-(SUMIFS(disponibilidad[Tiempo falla (en Mintuos)],disponibilidad[RECAUDOS],"SI",disponibilidad[Mes],$B11,disponibilidad[[Tipo de afectación ]],"caÍda total",disponibilidad[Responsable Falla],"Matrix Tech",disponibilidad[Suchance - Huila],"SI")))/$C11)*100 -> 100 | J11: =+(($C11-(SUMIFS(disponibilidad[Tiempo falla (en Mintuos)],disponibilidad[RECARGAS],"SI",disponibilidad[Mes],$B11,disponibilidad[[Tipo de afectación ]],"caÍda total",disponibilidad[Responsable Falla],"Matrix Tech",disponibilidad[Suchance - Huila],"SI")))/$C11)*100 -> 100 | K11: =SUMPRODUCT($G$7:$J$7,G11:J11)/$K$7 -> 100 | L11: =+(($C11-(SUMIFS(disponibilidad[Tiempo falla (en Mintuos)],disponibilidad[PAGOS],"SI",disponibilidad[Mes],$B11,disponibilidad[[Tipo de afectación ]],"caÍda total",disponibilidad[Responsable Falla],"Aliados o terceros",disponibilidad[Acertemos - Cauca],"SI")))/$C11)*100 -> 100 | M11: =+(($C11-(SUMIFS(disponibilidad[Tiempo falla (en Mintuos)],disponibilidad[RECAUDOS],"SI",disponibilidad[Mes],$B11,disponibilidad[[Tipo de afectación ]],"caÍda total",disponibilidad[Responsable Falla],"Aliados o terceros",disponibilidad[Acertemos - Cauca],"SI")))/$C11)*100 -> 100 | N11: =+(($C11-(SUMIFS(disponibilidad[Tiempo falla (en Mintuos)],disponibilidad[RECARGAS],"SI",disponibilidad[Mes],$B11,disponibilidad[[Tipo de afectación ]],"caÍda total",disponibilidad[Responsable Falla],"Aliados o terceros",disponibilidad[Acertemos - Cauca],"SI")))/$C11)*100 -> 100 | O11: =AVERAGE(L11:N11) -> 100 | P11: =SUMIFS(disponibilidad[Tiempo falla (en Mintuos)],disponibilidad[Mes],$B11,disponibilidad[[Tipo de afectación ]],"caÍda total",disponibilidad[Responsable Falla],"Matrix Tech",disponibilidad[Suchance - Huila],"SI") -> 0 | Q11: =+P11/C11 -> 0 | R11: =SUMIFS(disponibilidad[Tiempo falla (en Mintuos)],disponibilidad[Mes],$B11,disponibilidad[[Tipo de afectación ]],"caÍda total",disponibilidad[Responsable Falla],"Aliados o terceros",disponibilidad[Acertemos - Cauca],"SI") -> 0 | S11: =+$R$8/$C$8 -> 0 | T11: =AVERAGE(F11,K11) -> 100 | X11: General Aplicacion. | Y11: =VLOOKUP($Y$7,$B$8:$R$17,7,FALSE) -> 100
B12: Mayo | C12: =VLOOKUP(B12,Maestro!$A$7:$D$19,4,FALSE) -> 44640 | D12: =+(($C12-(SUMIFS(disponibilidad[Tiempo falla (en Mintuos)],disponibilidad[JADE],"SI",disponibilidad[Mes],$B12,disponibilidad[[Tipo de afectación ]],"caÍda total",disponibilidad[Responsable Falla],"Matrix Tech",disponibilidad[Suchance - Huila],"SI")))/$C12)*100 -> 100 | E12: =+(($C12-(SUMIFS(disponibilidad[Tiempo falla (en Mintuos)],disponibilidad[SIGA],"SI",disponibilidad[Mes],$B12,disponibilidad[[Tipo de afectación ]],"caÍda total",disponibilidad[Responsable Falla],"Matrix Tech",disponibilidad[Suchance - Huila],"SI")))/$C12)*100 -> 100 | F12: =SUMPRODUCT($D$7:$E$7,D12:E12)/$K$7 -> 100 | G12: =+(($C12-(SUMIFS(disponibilidad[Tiempo falla (en Mintuos)],disponibilidad[Apuestas - Chance],"SI",disponibilidad[Mes],$B12,disponibilidad[[Tipo de afectación ]],"caÍda total",disponibilidad[Responsable Falla],"Matrix Tech",disponibilidad[Suchance - Huila],"SI")))/$C12)*100 -> 100 | H12: =+(($C12-(SUMIFS(disponibilidad[Tiempo falla (en Mintuos)],disponibilidad[PAGOS],"SI",disponibilidad[Mes],$B12,disponibilidad[[Tipo de afectación ]],"caÍda total",disponibilidad[Responsable Falla],"Matrix Tech",disponibilidad[Suchance - Huila],"SI")))/$C12)*100 -> 100 | I12: =+(($C12-(SUMIFS(disponibilidad[Tiempo falla (en Mintuos)],disponibilidad[RECAUDOS],"SI",disponibilidad[Mes],$B12,disponibilidad[[Tipo de afectación ]],"caÍda total",disponibilidad[Responsable Falla],"Matrix Tech",disponibilidad[Suchance - Huila],"SI")))/$C12)*100 -> 100 | J12: =+(($C12-(SUMIFS(disponibilidad[Tiempo falla (en Mintuos)],disponibilidad[RECARGAS],"SI",disponibilidad[Mes],$B12,disponibilidad[[Tipo de afectación ]],"caÍda total",disponibilidad[Responsable Falla],"Matrix Tech",disponibilidad[Suchance - Huila],"SI")))/$C12)*100 -> 100 | K12: =SUMPRODUCT($G$7:$J$7,G12:J12)/$K$7 -> 100 | L12: =+(($C12-(SUMIFS(disponibilidad[Tiempo falla (en Mintuos)],disponibilidad[PAGOS],"SI",disponibilidad[Mes],$B12,disponibilidad[[Tipo de afectación ]],"caÍda total",disponibilidad[Responsable Falla],"Aliados o terceros",disponibilidad[Acertemos - Cauca],"SI")))/$C12)*100 -> 100 | M12: =+(($C12-(SUMIFS(disponibilidad[Tiempo falla (en Mintuos)],disponibilidad[RECAUDOS],"SI",disponibilidad[Mes],$B12,disponibilidad[[Tipo de afectación ]],"caÍda total",disponibilidad[Responsable Falla],"Aliados o terceros",disponibilidad[Acertemos - Cauca],"SI")))/$C12)*100 -> 100 | N12: =+(($C12-(SUMIFS(disponibilidad[Tiempo falla (en Mintuos)],disponibilidad[RECARGAS],"SI",disponibilidad[Mes],$B12,disponibilidad[[Tipo de afectación ]],"caÍda total",disponibilidad[Responsable Falla],"Aliados o terceros",disponibilidad[Acertemos - Cauca],"SI")))/$C12)*100 -> 100 | O12: =AVERAGE(L12:N12) -> 100 | P12: =SUMIFS(disponibilidad[Tiempo falla (en Mintuos)],disponibilidad[Mes],$B12,disponibilidad[[Tipo de afectación ]],"caÍda total",disponibilidad[Responsable Falla],"Matrix Tech",disponibilidad[Suchance - Huila],"SI") -> 0 | Q12: =+P12/C12 -> 0 | R12: =SUMIFS(disponibilidad[Tiempo falla (en Mintuos)],disponibilidad[Mes],$B12,disponibilidad[[Tipo de afectación ]],"caÍda total",disponibilidad[Responsable Falla],"Aliados o terceros",disponibilidad[Acertemos - Cauca],"SI") -> 0 | S12: =+$R$8/$C$8 -> 0
B13: Junio | C13: =VLOOKUP(B13,Maestro!$A$7:$D$19,4,FALSE) -> 43200 | D13: =+(($C13-(SUMIFS(disponibilidad[Tiempo falla (en Mintuos)],disponibilidad[JADE],"SI",disponibilidad[Mes],$B13,disponibilidad[[Tipo de afectación ]],"caÍda total",disponibilidad[Responsable Falla],"Matrix Tech",disponibilidad[Suchance - Huila],"SI")))/$C13)*100 -> 100 | E13: =+(($C13-(SUMIFS(disponibilidad[Tiempo falla (en Mintuos)],disponibilidad[SIGA],"SI",disponibilidad[Mes],$B13,disponibilidad[[Tipo de afectación ]],"caÍda total",disponibilidad[Responsable Falla],"Matrix Tech",disponibilidad[Suchance - Huila],"SI")))/$C13)*100 -> 100 | F13: =SUMPRODUCT($D$7:$E$7,D13:E13)/$K$7 -> 100 | G13: =+(($C13-(SUMIFS(disponibilidad[Tiempo falla (en Mintuos)],disponibilidad[Apuestas - Chance],"SI",disponibilidad[Mes],$B13,disponibilidad[[Tipo de afectación ]],"caÍda total",disponibilidad[Responsable Falla],"Matrix Tech",disponibilidad[Suchance - Huila],"SI")))/$C13)*100 -> 100 | H13: =+(($C13-(SUMIFS(disponibilidad[Tiempo falla (en Mintuos)],disponibilidad[PAGOS],"SI",disponibilidad[Mes],$B13,disponibilidad[[Tipo de afectación ]],"caÍda total",disponibilidad[Responsable Falla],"Matrix Tech",disponibilidad[Suchance - Huila],"SI")))/$C13)*100 -> 100 | I13: =+(($C13-(SUMIFS(disponibilidad[Tiempo falla (en Mintuos)],disponibilidad[RECAUDOS],"SI",disponibilidad[Mes],$B13,disponibilidad[[Tipo de afectación ]],"caÍda total",disponibilidad[Responsable Falla],"Matrix Tech",disponibilidad[Suchance - Huila],"SI")))/$C13)*100 -> 100 | J13: =+(($C13-(SUMIFS(disponibilidad[Tiempo falla (en Mintuos)],disponibilidad[RECARGAS],"SI",disponibilidad[Mes],$B13,disponibilidad[[Tipo de afectación ]],"caÍda total",disponibilidad[Responsable Falla],"Matrix Tech",disponibilidad[Suchance - Huila],"SI")))/$C13)*100 -> 100 | K13: =SUMPRODUCT($G$7:$J$7,G13:J13)/$K$7 -> 100 | L13: =+(($C13-(SUMIFS(disponibilidad[Tiempo falla (en Mintuos)],disponibilidad[PAGOS],"SI",disponibilidad[Mes],$B13,disponibilidad[[Tipo de afectación ]],"caÍda total",disponibilidad[Responsable Falla],"Aliados o terceros",disponibilidad[Acertemos - Cauca],"SI")))/$C13)*100 -> 100 | M13: =+(($C13-(SUMIFS(disponibilidad[Tiempo falla (en Mintuos)],disponibilidad[RECAUDOS],"SI",disponibilidad[Mes],$B13,disponibilidad[[Tipo de afectación ]],"caÍda total",disponibilidad[Responsable Falla],"Aliados o terceros",disponibilidad[Acertemos - Cauca],"SI")))/$C13)*100 -> 100 | N13: =+(($C13-(SUMIFS(disponibilidad[Tiempo falla (en Mintuos)],disponibilidad[RECARGAS],"SI",disponibilidad[Mes],$B13,disponibilidad[[Tipo de afectación ]],"caÍda total",disponibilidad[Responsable Falla],"Aliados o terceros",disponibilidad[Acertemos - Cauca],"SI")))/$C13)*100 -> 100 | O13: =AVERAGE(L13:N13) -> 100 | P13: =SUMIFS(disponibilidad[Tiempo falla (en Mintuos)],disponibilidad[Mes],$B13,disponibilidad[[Tipo de afectación ]],"caÍda total",disponibilidad[Responsable Falla],"Matrix Tech",disponibilidad[Suchance - Huila],"SI") -> 0 | Q13: =+P13/C13 -> 0 | R13: =SUMIFS(disponibilidad[Tiempo falla (en Mintuos)],disponibilidad[Mes],$B13,disponibilidad[[Tipo de afectación ]],"caÍda total",disponibilidad[Responsable Falla],"Aliados o terceros",disponibilidad[Acertemos - Cauca],"SI") -> 0 | S13: =+$R$8/$C$8 -> 0
B14: Julio | C14: =VLOOKUP(B14,Maestro!$A$7:$D$19,4,FALSE) -> 44640 | D14: =+(($C14-(SUMIFS(disponibilidad[Tiempo falla (en Mintuos)],disponibilidad[JADE],"SI",disponibilidad[Mes],$B14,disponibilidad[[Tipo de afectación ]],"caÍda total",disponibilidad[Responsable Falla],"Matrix Tech",disponibilidad[Suchance - Huila],"SI")))/$C14)*100 -> 100 | E14: =+(($C14-(SUMIFS(disponibilidad[Tiempo falla (en Mintuos)],disponibilidad[SIGA],"SI",disponibilidad[Mes],$B14,disponibilidad[[Tipo de afectación ]],"caÍda total",disponibilidad[Responsable Falla],"Matrix Tech",disponibilidad[Suchance - Huila],"SI")))/$C14)*100 -> 100 | F14: =SUMPRODUCT($D$7:$E$7,D14:E14)/$K$7 -> 100 | G14: =+(($C14-(SUMIFS(disponibilidad[Tiempo falla (en Mintuos)],disponibilidad[Apuestas - Chance],"SI",disponibilidad[Mes],$B14,disponibilidad[[Tipo de afectación ]],"caÍda total",disponibilidad[Responsable Falla],"Matrix Tech",disponibilidad[Suchance - Huila],"SI")))/$C14)*100 -> 100 | H14: =+(($C14-(SUMIFS(disponibilidad[Tiempo falla (en Mintuos)],disponibilidad[PAGOS],"SI",disponibilidad[Mes],$B14,disponibilidad[[Tipo de afectación ]],"caÍda total",disponibilidad[Responsable Falla],"Matrix Tech",disponibilidad[Suchance - Huila],"SI")))/$C14)*100 -> 100 | I14: =+(($C14-(SUMIFS(disponibilidad[Tiempo falla (en Mintuos)],disponibilidad[RECAUDOS],"SI",disponibilidad[Mes],$B14,disponibilidad[[Tipo de afectación ]],"caÍda total",disponibilidad[Responsable Falla],"Matrix Tech",disponibilidad[Suchance - Huila],"SI")))/$C14)*100 -> 100 | J14: =+(($C14-(SUMIFS(disponibilidad[Tiempo falla (en Mintuos)],disponibilidad[RECARGAS],"SI",disponibilidad[Mes],$B14,disponibilidad[[Tipo de afectación ]],"caÍda total",disponibilidad[Responsable Falla],"Matrix Tech",disponibilidad[Suchance - Huila],"SI")))/$C14)*100 -> 100 | K14: =SUMPRODUCT($G$7:$J$7,G14:J14)/$K$7 -> 100 | L14: =+(($C14-(SUMIFS(disponibilidad[Tiempo falla (en Mintuos)],disponibilidad[PAGOS],"SI",disponibilidad[Mes],$B14,disponibilidad[[Tipo de afectación ]],"caÍda total",disponibilidad[Responsable Falla],"Aliados o terceros",disponibilidad[Acertemos - Cauca],"SI")))/$C14)*100 -> 100 | M14: =+(($C14-(SUMIFS(disponibilidad[Tiempo falla (en Mintuos)],disponibilidad[RECAUDOS],"SI",disponibilidad[Mes],$B14,disponibilidad[[Tipo de afectación ]],"caÍda total",disponibilidad[Responsable Falla],"Aliados o terceros",disponibilidad[Acertemos - Cauca],"SI")))/$C14)*100 -> 100 | N14: =+(($C14-(SUMIFS(disponibilidad[Tiempo falla (en Mintuos)],disponibilidad[RECARGAS],"SI",disponibilidad[Mes],$B14,disponibilidad[[Tipo de afectación ]],"caÍda total",disponibilidad[Responsable Falla],"Aliados o terceros",disponibilidad[Acertemos - Cauca],"SI")))/$C14)*100 -> 100 | O14: =AVERAGE(L14:N14) -> 100 | P14: =SUMIFS(disponibilidad[Tiempo falla (en Mintuos)],disponibilidad[Mes],$B14,disponibilidad[[Tipo de afectación ]],"caÍda total",disponibilidad[Responsable Falla],"Matrix Tech",disponibilidad[Suchance - Huila],"SI") -> 0 | Q14: =+P14/C14 -> 0 | R14: =SUMIFS(disponibilidad[Tiempo falla (en Mintuos)],disponibilidad[Mes],$B14,disponibilidad[[Tipo de afectación ]],"caÍda total",disponibilidad[Responsable Falla],"Aliados o terceros",disponibilidad[Acertemos - Cauca],"SI") -> 0 | S14: =+$R$8/$C$8 -> 0
B15: Agosto | C15: =VLOOKUP(B15,Maestro!$A$7:$D$19,4,FALSE) -> 44640 | D15: =+(($C15-(SUMIFS(disponibilidad[Tiempo falla (en Mintuos)],disponibilidad[JADE],"SI",disponibilidad[Mes],$B15,disponibilidad[[Tipo de afectación ]],"caÍda total",disponibilidad[Responsable Falla],"Matrix Tech",disponibilidad[Suchance - Huila],"SI")))/$C15)*100 -> 100 | E15: =+(($C15-(SUMIFS(disponibilidad[Tiempo falla (en Mintuos)],disponibilidad[SIGA],"SI",disponibilidad[Mes],$B15,disponibilidad[[Tipo de afectación ]],"caÍda total",disponibilidad[Responsable Falla],"Matrix Tech",disponibilidad[Suchance - Huila],"SI")))/$C15)*100 -> 100 | F15: =SUMPRODUCT($D$7:$E$7,D15:E15)/$K$7 -> 100 | G15: =+(($C15-(SUMIFS(disponibilidad[Tiempo falla (en Mintuos)],disponibilidad[Apuestas - Chance],"SI",disponibilidad[Mes],$B15,disponibilidad[[Tipo de afectación ]],"caÍda total",disponibilidad[Responsable Falla],"Matrix Tech",disponibilidad[Suchance - Huila],"SI")))/$C15)*100 -> 100 | H15: =+(($C15-(SUMIFS(disponibilidad[Tiempo falla (en Mintuos)],disponibilidad[PAGOS],"SI",disponibilidad[Mes],$B15,disponibilidad[[Tipo de afectación ]],"caÍda total",disponibilidad[Responsable Falla],"Matrix Tech",disponibilidad[Suchance - Huila],"SI")))/$C15)*100 -> 100 | I15: =+(($C15-(SUMIFS(disponibilidad[Tiempo falla (en Mintuos)],disponibilidad[RECAUDOS],"SI",disponibilidad[Mes],$B15,disponibilidad[[Tipo de afectación ]],"caÍda total",disponibilidad[Responsable Falla],"Matrix Tech",disponibilidad[Suchance - Huila],"SI")))/$C15)*100 -> 100 | J15: =+(($C15-(SUMIFS(disponibilidad[Tiempo falla (en Mintuos)],disponibilidad[RECARGAS],"SI",disponibilidad[Mes],$B15,disponibilidad[[Tipo de afectación ]],"caÍda total",disponibilidad[Responsable Falla],"Matrix Tech",disponibilidad[Suchance - Huila],"SI")))/$C15)*100 -> 100 | K15: =SUMPRODUCT($G$7:$J$7,G15:J15)/$K$7 -> 100 | L15: =+(($C15-(SUMIFS(disponibilidad[Tiempo falla (en Mintuos)],disponibilidad[PAGOS],"SI",disponibilidad[Mes],$B15,disponibilidad[[Tipo de afectación ]],"caÍda total",disponibilidad[Responsable Falla],"Aliados o terceros",disponibilidad[Acertemos - Cauca],"SI")))/$C15)*100 -> 100 | M15: =+(($C15-(SUMIFS(disponibilidad[Tiempo falla (en Mintuos)],disponibilidad[RECAUDOS],"SI",disponibilidad[Mes],$B15,disponibilidad[[Tipo de afectación ]],"caÍda total",disponibilidad[Responsable Falla],"Aliados o terceros",disponibilidad[Acertemos - Cauca],"SI")))/$C15)*100 -> 100 | N15: =+(($C15-(SUMIFS(disponibilidad[Tiempo falla (en Mintuos)],disponibilidad[RECARGAS],"SI",disponibilidad[Mes],$B15,disponibilidad[[Tipo de afectación ]],"caÍda total",disponibilidad[Responsable Falla],"Aliados o terceros",disponibilidad[Acertemos - Cauca],"SI")))/$C15)*100 -> 100 | O15: =AVERAGE(L15:N15) -> 100 | P15: =SUMIFS(disponibilidad[Tiempo falla (en Mintuos)],disponibilidad[Mes],$B15,disponibilidad[[Tipo de afectación ]],"caÍda total",disponibilidad[Responsable Falla],"Matrix Tech",disponibilidad[Suchance - Huila],"SI") -> 0 | Q15: =+P15/C15 -> 0 | R15: =SUMIFS(disponibilidad[Tiempo falla (en Mintuos)],disponibilidad[Mes],$B15,disponibilidad[[Tipo de afectación ]],"caÍda total",disponibilidad[Responsable Falla],"Aliados o terceros",disponibilidad[Acertemos - Cauca],"SI") -> 0 | S15: =+$R$8/$C$8 -> 0 | X15: Apuestas - Chance | Y15: =VLOOKUP($Y$7,$B$8:$R$17,8,FALSE) -> 100
B16: Septiembre | C16: =VLOOKUP(B16,Maestro!$A$7:$D$19,4,FALSE) -> 43200 | D16: =+(($C16-(SUMIFS(disponibilidad[Tiempo falla (en Mintuos)],disponibilidad[JADE],"SI",disponibilidad[Mes],$B16,disponibilidad[[Tipo de afectación ]],"caÍda total",disponibilidad[Responsable Falla],"Matrix Tech",disponibilidad[Suchance - Huila],"SI")))/$C16)*100 -> 100 | E16: =+(($C16-(SUMIFS(disponibilidad[Tiempo falla (en Mintuos)],disponibilidad[SIGA],"SI",disponibilidad[Mes],$B16,disponibilidad[[Tipo de afectación ]],"caÍda total",disponibilidad[Responsable Falla],"Matrix Tech",disponibilidad[Suchance - Huila],"SI")))/$C16)*100 -> 100 | F16: =SUMPRODUCT($D$7:$E$7,D16:E16)/$K$7 -> 100 | G16: =+(($C16-(SUMIFS(disponibilidad[Tiempo falla (en Mintuos)],disponibilidad[Apuestas - Chance],"SI",disponibilidad[Mes],$B16,disponibilidad[[Tipo de afectación ]],"caÍda total",disponibilidad[Responsable Falla],"Matrix Tech",disponibilidad[Suchance - Huila],"SI")))/$C16)*100 -> 100 | H16: =+(($C16-(SUMIFS(disponibilidad[Tiempo falla (en Mintuos)],disponibilidad[PAGOS],"SI",disponibilidad[Mes],$B16,disponibilidad[[Tipo de afectación ]],"caÍda total",disponibilidad[Responsable Falla],"Matrix Tech",disponibilidad[Suchance - Huila],"SI")))/$C16)*100 -> 100 | I16: =+(($C16-(SUMIFS(disponibilidad[Tiempo falla (en Mintuos)],disponibilidad[RECAUDOS],"SI",disponibilidad[Mes],$B16,disponibilidad[[Tipo de afectación ]],"caÍda total",disponibilidad[Responsable Falla],"Matrix Tech",disponibilidad[Suchance - Huila],"SI")))/$C16)*100 -> 100 | J16: =+(($C16-(SUMIFS(disponibilidad[Tiempo falla (en Mintuos)],disponibilidad[RECARGAS],"SI",disponibilidad[Mes],$B16,disponibilidad[[Tipo de afectación ]],"caÍda total",disponibilidad[Responsable Falla],"Matrix Tech",disponibilidad[Suchance - Huila],"SI")))/$C16)*100 -> 100 | K16: =SUMPRODUCT($G$7:$J$7,G16:J16)/$K$7 -> 100 | L16: =+(($C16-(SUMIFS(disponibilidad[Tiempo falla (en Mintuos)],disponibilidad[PAGOS],"SI",disponibilidad[Mes],$B16,disponibilidad[[Tipo de afectación ]],"caÍda total",disponibilidad[Responsable Falla],"Aliados o terceros",disponibilidad[Acertemos - Cauca],"SI")))/$C16)*100 -> 100 | M16: =+(($C16-(SUMIFS(disponibilidad[Tiempo falla (en Mintuos)],disponibilidad[RECAUDOS],"SI",disponibilidad[Mes],$B16,disponibilidad[[Tipo de afectación ]],"caÍda total",disponibilidad[Responsable Falla],"Aliados o terceros",disponibilidad[Acertemos - Cauca],"SI")))/$C16)*100 -> 100 | N16: =+(($C16-(SUMIFS(disponibilidad[Tiempo falla (en Mintuos)],disponibilidad[RECARGAS],"SI",disponibilidad[Mes],$B16,disponibilidad[[Tipo de afectación ]],"caÍda total",disponibilidad[Responsable Falla],"Aliados o terceros",disponibilidad[Acertemos - Cauca],"SI")))/$C16)*100 -> 100 | O16: =AVERAGE(L16:N16) -> 100 | P16: =SUMIFS(disponibilidad[Tiempo falla (en Mintuos)],disponibilidad[Mes],$B16,disponibilidad[[Tipo de afectación ]],"caÍda total",disponibilidad[Responsable Falla],"Matrix Tech",disponibilidad[Suchance - Huila],"SI") -> 0 | Q16: =+P16/C16 -> 0 | R16: =SUMIFS(disponibilidad[Tiempo falla (en Mintuos)],disponibilidad[Mes],$B16,disponibilidad[[Tipo de afectación ]],"caÍda total",disponibilidad[Responsable Falla],"Aliados o terceros",disponibilidad[Acertemos - Cauca],"SI") -> 0 | S16: =+$R$8/$C$8 -> 0 | X16: PAGOS | Y16: =VLOOKUP($Y$7,$B$8:$R$17,9,FALSE) -> 100
B17: Octubre | C17: =VLOOKUP(B17,Maestro!$A$7:$D$19,4,FALSE) -> 44640 | D17: =+(($C17-(SUMIFS(disponibilidad[Tiempo falla (en Mintuos)],disponibilidad[JADE],"SI",disponibilidad[Mes],$B17,disponibilidad[[Tipo de afectación ]],"caÍda total",disponibilidad[Responsable Falla],"Matrix Tech",disponibilidad[Suchance - Huila],"SI")))/$C17)*100 -> 100 | E17: =+(($C17-(SUMIFS(disponibilidad[Tiempo falla (en Mintuos)],disponibilidad[SIGA],"SI",disponibilidad[Mes],$B17,disponibilidad[[Tipo de afectación ]],"caÍda total",disponibilidad[Responsable Falla],"Matrix Tech",disponibilidad[Suchance - Huila],"SI")))/$C17)*100 -> 100 | F17: =SUMPRODUCT($D$7:$E$7,D17:E17)/$K$7 -> 100 | G17: =+(($C17-(SUMIFS(disponibilidad[Tiempo falla (en Mintuos)],disponibilidad[Apuestas - Chance],"SI",disponibilidad[Mes],$B17,disponibilidad[[Tipo de afectación ]],"caÍda total",disponibilidad[Responsable Falla],"Matrix Tech",disponibilidad[Suchance - Huila],"SI")))/$C17)*100 -> 100 | H17: =+(($C17-(SUMIFS(disponibilidad[Tiempo falla (en Mintuos)],disponibilidad[PAGOS],"SI",disponibilidad[Mes],$B17,disponibilidad[[Tipo de afectación ]],"caÍda total",disponibilidad[Responsable Falla],"Matrix Tech",disponibilidad[Suchance - Huila],"SI")))/$C17)*100 -> 100 | I17: =+(($C17-(SUMIFS(disponibilidad[Tiempo falla (en Mintuos)],disponibilidad[RECAUDOS],"SI",disponibilidad[Mes],$B17,disponibilidad[[Tipo de afectación ]],"caÍda total",disponibilidad[Responsable Falla],"Matrix Tech",disponibilidad[Suchance - Huila],"SI")))/$C17)*100 -> 100 | J17: =+(($C17-(SUMIFS(disponibilidad[Tiempo falla (en Mintuos)],disponibilidad[RECARGAS],"SI",disponibilidad[Mes],$B17,disponibilidad[[Tipo de afectación ]],"caÍda total",disponibilidad[Responsable Falla],"Matrix Tech",disponibilidad[Suchance - Huila],"SI")))/$C17)*100 -> 100 | K17: =SUMPRODUCT($G$7:$J$7,G17:J17)/$K$7 -> 100 | L17: =+(($C17-(SUMIFS(disponibilidad[Tiempo falla (en Mintuos)],disponibilidad[PAGOS],"SI",disponibilidad[Mes],$B17,disponibilidad[[Tipo de afectación ]],"caÍda total",disponibilidad[Responsable Falla],"Aliados o terceros",disponibilidad[Acertemos - Cauca],"SI")))/$C17)*100 -> 100 | M17: =+(($C17-(SUMIFS(disponibilidad[Tiempo falla (en Mintuos)],disponibilidad[RECAUDOS],"SI",disponibilidad[Mes],$B17,disponibilidad[[Tipo de afectación ]],"caÍda total",disponibilidad[Responsable Falla],"Aliados o terceros",disponibilidad[Acertemos - Cauca],"SI")))/$C17)*100 -> 100 | N17: =+(($C17-(SUMIFS(disponibilidad[Tiempo falla (en Mintuos)],disponibilidad[RECARGAS],"SI",disponibilidad[Mes],$B17,disponibilidad[[Tipo de afectación ]],"caÍda total",disponibilidad[Responsable Falla],"Aliados o terceros",disponibilidad[Acertemos - Cauca],"SI")))/$C17)*100 -> 100 | O17: =AVERAGE(L17:N17) -> 100 | P17: =SUMIFS(disponibilidad[Tiempo falla (en Mintuos)],disponibilidad[Mes],$B17,disponibilidad[[Tipo de afectación ]],"caÍda total",disponibilidad[Responsable Falla],"Matrix Tech",disponibilidad[Suchance - Huila],"SI") -> 0 | Q17: =+P17/C17 -> 0 | R17: =SUMIFS(disponibilidad[Tiempo falla (en Mintuos)],disponibilidad[Mes],$B17,disponibilidad[[Tipo de afectación ]],"caÍda total",disponibilidad[Responsable Falla],"Aliados o terceros",disponibilidad[Suchance - Huila],"SI") -> 0 | S17: =+$R$8/$C$8 -> 0 | X17: RECAUDOS | Y17: =VLOOKUP($Y$7,$B$8:$R$17,10,FALSE) -> 100
B18: Noviembre | C18: =VLOOKUP(B18,Maestro!$A$7:$D$19,4,FALSE) -> 43200 | D18: =+(($C18-(SUMIFS(disponibilidad[Tiempo falla (en Mintuos)],disponibilidad[JADE],"SI",disponibilidad[Mes],$B18,disponibilidad[[Tipo de afectación ]],"caÍda total",disponibilidad[Responsable Falla],"Matrix Tech",disponibilidad[Suchance - Huila],"SI")))/$C18)*100 -> 100 | E18: =+(($C18-(SUMIFS(disponibilidad[Tiempo falla (en Mintuos)],disponibilidad[SIGA],"SI",disponibilidad[Mes],$B18,disponibilidad[[Tipo de afectación ]],"caÍda total",disponibilidad[Responsable Falla],"Matrix Tech",disponibilidad[Suchance - Huila],"SI")))/$C18)*100 -> 100 | F18: =SUMPRODUCT($D$7:$E$7,D18:E18)/$K$7 -> 100 | G18: =+(($C18-(SUMIFS(disponibilidad[Tiempo falla (en Mintuos)],disponibilidad[Apuestas - Chance],"SI",disponibilidad[Mes],$B18,disponibilidad[[Tipo de afectación ]],"caÍda total",disponibilidad[Responsable Falla],"Matrix Tech",disponibilidad[Suchance - Huila],"SI")))/$C18)*100 -> 100 | H18: =+(($C18-(SUMIFS(disponibilidad[Tiempo falla (en Mintuos)],disponibilidad[PAGOS],"SI",disponibilidad[Mes],$B18,disponibilidad[[Tipo de afectación ]],"caÍda total",disponibilidad[Responsable Falla],"Matrix Tech",disponibilidad[Suchance - Huila],"SI")))/$C18)*100 -> 100 | I18: =+(($C18-(SUMIFS(disponibilidad[Tiempo falla (en Mintuos)],disponibilidad[RECAUDOS],"SI",disponibilidad[Mes],$B18,disponibilidad[[Tipo de afectación ]],"caÍda total",disponibilidad[Responsable Falla],"Matrix Tech",disponibilidad[Suchance - Huila],"SI")))/$C18)*100 -> 100 | J18: =+(($C18-(SUMIFS(disponibilidad[Tiempo falla (en Mintuos)],disponibilidad[RECARGAS],"SI",disponibilidad[Mes],$B18,disponibilidad[[Tipo de afectación ]],"caÍda total",disponibilidad[Responsable Falla],"Matrix Tech",disponibilidad[Suchance - Huila],"SI")))/$C18)*100 -> 100 | K18: =SUMPRODUCT($G$7:$J$7,G18:J18)/$K$7 -> 100 | L18: =+(($C18-(SUMIFS(disponibilidad[Tiempo falla (en Mintuos)],disponibilidad[PAGOS],"SI",disponibilidad[Mes],$B18,disponibilidad[[Tipo de afectación ]],"caÍda total",disponibilidad[Responsable Falla],"Aliados o terceros",disponibilidad[Acertemos - Cauca],"SI")))/$C18)*100 -> 100 | M18: =+(($C18-(SUMIFS(disponibilidad[Tiempo falla (en Mintuos)],disponibilidad[RECAUDOS],"SI",disponibilidad[Mes],$B18,disponibilidad[[Tipo de afectación ]],"caÍda total",disponibilidad[Responsable Falla],"Aliados o terceros",disponibilidad[Acertemos - Cauca],"SI")))/$C18)*100 -> 100 | N18: =+(($C18-(SUMIFS(disponibilidad[Tiempo falla (en Mintuos)],disponibilidad[RECARGAS],"SI",disponibilidad[Mes],$B18,disponibilidad[[Tipo de afectación ]],"caÍda total",disponibilidad[Responsable Falla],"Aliados o terceros",disponibilidad[Acertemos - Cauca],"SI")))/$C18)*100 -> 100 | O18: =AVERAGE(L18:N18) -> 100 | P18: =SUMIFS(disponibilidad[Tiempo falla (en Mintuos)],disponibilidad[Mes],$B18,disponibilidad[[Tipo de afectación ]],"caÍda total",disponibilidad[Responsable Falla],"Matrix Tech",disponibilidad[Suchance - Huila],"SI") -> 0 | Q18: =+P18/C18 -> 0 | R18: =SUMIFS(disponibilidad[Tiempo falla (en Mintuos)],disponibilidad[Mes],$B18,disponibilidad[[Tipo de afectación ]],"caÍda total",disponibilidad[Responsable Falla],"Aliados o terceros",disponibilidad[Suchance - Huila],"SI") -> 0 | S18: =+$R$8/$C$8 -> 0 | X18: RECARGAS | Y18: =VLOOKUP($Y$7,$B$8:$R$17,11,FALSE) -> 100
B19: Diciembre | C19: =VLOOKUP(B19,Maestro!$A$7:$D$19,4,FALSE) -> 44640 | D19: =+(($C19-(SUMIFS(disponibilidad[Tiempo falla (en Mintuos)],disponibilidad[JADE],"SI",disponibilidad[Mes],$B19,disponibilidad[[Tipo de afectación ]],"caÍda total",disponibilidad[Responsable Falla],"Matrix Tech",disponibilidad[Suchance - Huila],"SI")))/$C19)*100 -> 100 | E19: =+(($C19-(SUMIFS(disponibilidad[Tiempo falla (en Mintuos)],disponibilidad[SIGA],"SI",disponibilidad[Mes],$B19,disponibilidad[[Tipo de afectación ]],"caÍda total",disponibilidad[Responsable Falla],"Matrix Tech",disponibilidad[Suchance - Huila],"SI")))/$C19)*100 -> 100 | F19: =SUMPRODUCT($D$7:$E$7,D19:E19)/$K$7 -> 100 | G19: =+(($C19-(SUMIFS(disponibilidad[Tiempo falla (en Mintuos)],disponibilidad[Apuestas - Chance],"SI",disponibilidad[Mes],$B19,disponibilidad[[Tipo de afectación ]],"caÍda total",disponibilidad[Responsable Falla],"Matrix Tech",disponibilidad[Suchance - Huila],"SI")))/$C19)*100 -> 100 | H19: =+(($C19-(SUMIFS(disponibilidad[Tiempo falla (en Mintuos)],disponibilidad[PAGOS],"SI",disponibilidad[Mes],$B19,disponibilidad[[Tipo de afectación ]],"caÍda total",disponibilidad[Responsable Falla],"Matrix Tech",disponibilidad[Suchance - Huila],"SI")))/$C19)*100 -> 100 | I19: =+(($C19-(SUMIFS(disponibilidad[Tiempo falla (en Mintuos)],disponibilidad[RECAUDOS],"SI",disponibilidad[Mes],$B19,disponibilidad[[Tipo de afectación ]],"caÍda total",disponibilidad[Responsable Falla],"Matrix Tech",disponibilidad[Suchance - Huila],"SI")))/$C19)*100 -> 100 | J19: =+(($C19-(SUMIFS(disponibilidad[Tiempo falla (en Mintuos)],disponibilidad[RECARGAS],"SI",disponibilidad[Mes],$B19,disponibilidad[[Tipo de afectación ]],"caÍda total",disponibilidad[Responsable Falla],"Matrix Tech",disponibilidad[Suchance - Huila],"SI")))/$C19)*100 -> 100 | K19: =SUMPRODUCT($G$7:$J$7,G19:J19)/$K$7 -> 100 | L19: =+(($C19-(SUMIFS(disponibilidad[Tiempo falla (en Mintuos)],disponibilidad[PAGOS],"SI",disponibilidad[Mes],$B19,disponibilidad[[Tipo de afectación ]],"caÍda total",disponibilidad[Responsable Falla],"Aliados o terceros",disponibilidad[Acertemos - Cauca],"SI")))/$C19)*100 -> 100 | M19: =+(($C19-(SUMIFS(disponibilidad[Tiempo falla (en Mintuos)],disponibilidad[RECAUDOS],"SI",disponibilidad[Mes],$B19,disponibilidad[[Tipo de afectación ]],"caÍda total",disponibilidad[Responsable Falla],"Aliados o terceros",disponibilidad[Acertemos - Cauca],"SI")))/$C19)*100 -> 100 | N19: =+(($C19-(SUMIFS(disponibilidad[Tiempo falla (en Mintuos)],disponibilidad[RECARGAS],"SI",disponibilidad[Mes],$B19,disponibilidad[[Tipo de afectación ]],"caÍda total",disponibilidad[Responsable Falla],"Aliados o terceros",disponibilidad[Acertemos - Cauca],"SI")))/$C19)*100 -> 100 | O19: =AVERAGE(L19:N19) -> 100 | P19: =SUMIFS(disponibilidad[Tiempo falla (en Mintuos)],disponibilidad[Mes],$B19,disponibilidad[[Tipo de afectación ]],"caÍda total",disponibilidad[Responsable Falla],"Matrix Tech",disponibilidad[Suchance - Huila],"SI") -> 0 | Q19: =+P19/C19 -> 0 | R19: =SUMIFS(disponibilidad[Tiempo falla (en Mintuos)],disponibilidad[Mes],$B19,disponibilidad[[Tipo de afectación ]],"caÍda total",disponibilidad[Responsable Falla],"Aliados o terceros",disponibilidad[Suchance - Huila],"SI") -> 0 | S19: =+$R$8/$C$8 -> 0 | X19: General Prod. | Y19: =VLOOKUP($Y$7,$B$8:$R$17,12,FALSE) -> 100

Sheet Jer - Boyaca
E1: SGSI | L1: Código | N1: FR-GDO-013
E2: FORMATO | L2: Versión | N2: 0
E3: BITÁCORA DISPONIBILIDAD DE PRODUCTOS | L3: Fecha | N3: 45525
B5: Mes | C5: Minutos Mes | D5: Disponibilidad Individual Aplicación Matrix Tech | F5: Disponibilidad General Aplicación | G5: Disponibilidad Indivudual Producto UX TECHNOLOGY | K5: Disponibilidad General Prodcuto | L5: Disponibilidad Indivudual Producto Aliados o Terceros | O5: Disponibilidad General Producto | P5: UX TECHNOLOGY | R5: Aliados - Terceros
D6: JADE | E6: SIGA | G6: Apuestas - Chance | H6: PAGOS | I6: RECAUDOS | J6: RECARGAS | L6: PAGOS | M6: RECAUDOS | N6: RECARGAS | P6: Tiempo Indisponibiliad | Q6: % Indisponibiliad | R6: Tiempo Indisponibiliad | S6: % Indisponibiliad
C7: AST/Peso | D7: 0.97 | E7: 0.03 | G7: 0.57 | H7: 0.03 | I7: 0.1 | J7: 0.3 | K7: =SUM(G7:J7) -> 1 | X7: MES | Y7: Febrero
B8: Enero | C8: =VLOOKUP(B8,Maestro!$A$7:$D$19,4,FALSE) -> 44640 | D8: =+(($C8-(SUMIFS(disponibilidad[Tiempo falla (en Mintuos)],disponibilidad[JADE],"SI",disponibilidad[Mes],$B8,disponibilidad[[Tipo de afectación ]],"caÍda total",disponibilidad[Responsable Falla],"Matrix Tech",disponibilidad[Jer - Boyacá],"SI",disponibilidad[Jer - Boyacá],"SI",disponibilidad[Jer - Boyacá],"SI",disponibilidad[Jer - Boyacá],"SI",disponibilidad[Jer - Boyacá],"SI",disponibilidad[Jer - Boyacá],"SI",disponibilidad[Jer - Boyacá],"SI",disponibilidad[Jer - Boyacá],"SI",disponibilidad[Jer - Boyacá],"SI",disponibilidad[Jer - Boyacá],"SI",disponibilidad[Jer - Boyacá],"SI",disponibilidad[Jer - Boyacá],"SI")))/$C8)*100 -> 99.894713 | E8: =+(($C8-(SUMIFS(disponibilidad[Tiempo falla (en Mintuos)],disponibilidad[SIGA],"SI",disponibilidad[Mes],$B8,disponibilidad[[Tipo de afectación ]],"caÍda total",disponibilidad[Responsable Falla],"Matrix Tech",disponibilidad[Jer - Boyacá],"SI",disponibilidad[Jer - Boyacá],"SI",disponibilidad[Jer - Boyacá],"SI",disponibilidad[Jer - Boyacá],"SI",disponibilidad[Jer - Boyacá],"SI",disponibilidad[Jer - Boyacá],"SI",disponibilidad[Jer - Boyacá],"SI",disponibilidad[Jer - Boyacá],"SI",disponibilidad[Jer - Boyacá],"SI",disponibilidad[Jer - Boyacá],"SI",disponibilidad[Jer - Boyacá],"SI",disponibilidad[Jer - Boyacá],"SI")))/$C8)*100 -> 100 | F8: =SUMPRODUCT($D$7:$E$7,D8:E8)/$K$7 -> 99.897872 | G8: =+(($C8-(SUMIFS(disponibilidad[Tiempo falla (en Mintuos)],disponibilidad[Apuestas - Chance],"SI",disponibilidad[Mes],$B8,disponibilidad[[Tipo de afectación ]],"caÍda total",disponibilidad[Responsable Falla],"Matrix Tech",disponibilidad[Jer - Boyacá],"SI")))/$C8)*100 -> 99.894713 | H8: =+(($C8-(SUMIFS(disponibilidad[Tiempo falla (en Mintuos)],disponibilidad[PAGOS],"SI",disponibilidad[Mes],$B8,disponibilidad[[Tipo de afectación ]],"caÍda total",disponibilidad[Responsable Falla],"Matrix Tech",disponibilidad[Jer - Boyacá],"SI")))/$C8)*100 -> 99.894713 | I8: =+(($C8-(SUMIFS(disponibilidad[Tiempo falla (en Mintuos)],disponibilidad[RECAUDOS],"SI",disponibilidad[Mes],$B8,disponibilidad[[Tipo de afectación ]],"caÍda total",disponibilidad[Responsable Falla],"Matrix Tech",disponibilidad[Jer - Boyacá],"SI")))/$C8)*100 -> 99.894713 | J8: =+(($C8-(SUMIFS(disponibilidad[Tiempo falla (en Mintuos)],disponibilidad[RECARGAS],"SI",disponibilidad[Mes],$B8,disponibilidad[[Tipo de afectación ]],"caÍda total",disponibilidad[Responsable Falla],"Matrix Tech",disponibilidad[Jer - Boyacá],"SI")))/$C8)*100 -> 99.894713 | K8: =SUMPRODUCT($G$7:$J$7,G8:J8)/$K$7 -> 99.894713 | L8: =+(($C8-(SUMIFS(disponibilidad[Tiempo falla (en Mintuos)],disponibilidad[PAGOS],"SI",disponibilidad[Mes],$B8,disponibilidad[[Tipo de afectación ]],"caÍda total",disponibilidad[Responsable Falla],"Aliados o terceros",disponibilidad[Jer - Boyacá],"SI")))/$C8)*100 -> 100 | M8: =+(($C8-(SUMIFS(disponibilidad[Tiempo falla (en Mintuos)],disponibilidad[RECAUDOS],"SI",disponibilidad[Mes],$B8,disponibilidad[[Tipo de afectación ]],"caÍda total",disponibilidad[Responsable Falla],"Aliados o terceros",disponibilidad[Jer - Boyacá],"SI")))/$C8)*100 -> 100 | N8: =+(($C8-(SUMIFS(disponibilidad[Tiempo falla (en Mintuos)],disponibilidad[RECARGAS],"SI",disponibilidad[Mes],$B8,disponibilidad[[Tipo de afectación ]],"caÍda total",disponibilidad[Responsable Falla],"Aliados o terceros",disponibilidad[Jer - Boyacá],"SI")))/$C8)*100 -> 100 | O8: =AVERAGE(L8:N8) -> 100 | P8: =SUMIFS(disponibilidad[Tiempo falla (en Mintuos)],disponibilidad[Mes],$B8,disponibilidad[[Tipo de afectación ]],"caÍda total",disponibilidad[Responsable Falla],"Matrix Tech",disponibilidad[Jer - Boyacá],"SI") -> 47 | Q8: =+P8/C8 -> 0.0010528674 | R8: =SUMIFS(disponibilidad[Tiempo falla (en Mintuos)],disponibilidad[Mes],$B8,disponibilidad[[Tipo de afectación ]],"caÍda total",disponibilidad[Responsable Falla],"Aliados o terceros",disponibilidad[Acertemos - Cauca],"SI") -> 0 | S8: =+R8/C8 -> 0
B9: Febrero | C9: =VLOOKUP(B9,Maestro!$A$7:$D$19,4,FALSE) -> 41760 | D9: =+(($C9-(SUMIFS(disponibilidad[Tiempo falla (en Mintuos)],disponibilidad[JADE],"SI",disponibilidad[Mes],$B9,disponibilidad[[Tipo de afectación ]],"caÍda total",disponibilidad[Responsable Falla],"Matrix Tech",disponibilidad[Jer - Boyacá],"SI",disponibilidad[Jer - Boyacá],"SI",disponibilidad[Jer - Boyacá],"SI",disponibilidad[Jer - Boyacá],"SI",disponibilidad[Jer - Boyacá],"SI",disponibilidad[Jer - Boyacá],"SI",disponibilidad[Jer - Boyacá],"SI",disponibilidad[Jer - Boyacá],"SI",disponibilidad[Jer - Boyacá],"SI",disponibilidad[Jer - Boyacá],"SI",disponibilidad[Jer - Boyacá],"SI",disponibilidad[Jer - Boyacá],"SI")))/$C9)*100 -> 99.794061 | E9: =+(($C9-(SUMIFS(disponibilidad[Tiempo falla (en Mintuos)],disponibilidad[SIGA],"SI",disponibilidad[Mes],$B9,disponibilidad[[Tipo de afectación ]],"caÍda total",disponibilidad[Responsable Falla],"Matrix Tech",disponibilidad[Jer - Boyacá],"SI",disponibilidad[Jer - Boyacá],"SI",disponibilidad[Jer - Boyacá],"SI",disponibilidad[Jer - Boyacá],"SI",disponibilidad[Jer - Boyacá],"SI",disponibilidad[Jer - Boyacá],"SI",disponibilidad[Jer - Boyacá],"SI",disponibilidad[Jer - Boyacá],"SI",disponibilidad[Jer - Boyacá],"SI",disponibilidad[Jer - Boyacá],"SI",disponibilidad[Jer - Boyacá],"SI",disponibilidad[Jer - Boyacá],"SI")))/$C9)*100 -> 100 | F9: =SUMPRODUCT($D$7:$E$7,D9:E9)/$K$7 -> 99.800239 | G9: =+(($C9-(SUMIFS(disponibilidad[Tiempo falla (en Mintuos)],disponibilidad[Apuestas - Chance],"SI",disponibilidad[Mes],$B9,disponibilidad[[Tipo de afectación ]],"caÍda total",disponibilidad[Responsable Falla],"Matrix Tech",disponibilidad[Jer - Boyacá],"SI")))/$C9)*100 -> 99.794061 | H9: =+(($C9-(SUMIFS(disponibilidad[Tiempo falla (en Mintuos)],disponibilidad[PAGOS],"SI",disponibilidad[Mes],$B9,disponibilidad[[Tipo de afectación ]],"caÍda total",disponibilidad[Responsable Falla],"Matrix Tech",disponibilidad[Jer - Boyacá],"SI")))/$C9)*100 -> 99.794061 | I9: =+(($C9-(SUMIFS(disponibilidad[Tiempo falla (en Mintuos)],disponibilidad[RECAUDOS],"SI",disponibilidad[Mes],$B9,disponibilidad[[Tipo de afectación ]],"caÍda total",disponibilidad[Responsable Falla],"Matrix Tech",disponibilidad[Jer - Boyacá],"SI")))/$C9)*100 -> 99.794061 | J9: =+(($C9-(SUMIFS(disponibilidad[Tiempo falla (en Mintuos)],disponibilidad[RECARGAS],"SI",disponibilidad[Mes],$B9,disponibilidad[[Tipo de afectación ]],"caÍda total",disponibilidad[Responsable Falla],"Matrix Tech",disponibilidad[Jer - Boyacá],"SI")))/$C9)*100 -> 99.794061 | K9: =SUMPRODUCT($G$7:$J$7,G9:J9)/$K$7 -> 99.794061 | L9: =+(($C9-(SUMIFS(disponibilidad[Tiempo falla (en Mintuos)],disponibilidad[PAGOS],"SI",disponibilidad[Mes],$B9,disponibilidad[[Tipo de afectación ]],"caÍda total",disponibilidad[Responsable Falla],"Aliados o terceros",disponibilidad[Jer - Boyacá],"SI")))/$C9)*100 -> 100 | M9: =+(($C9-(SUMIFS(disponibilidad[Tiempo falla (en Mintuos)],disponibilidad[RECAUDOS],"SI",disponibilidad[Mes],$B9,disponibilidad[[Tipo de afectación ]],"caÍda total",disponibilidad[Responsable Falla],"Aliados o terceros",disponibilidad[Jer - Boyacá],"SI")))/$C9)*100 -> 100 | N9: =+(($C9-(SUMIFS(disponibilidad[Tiempo falla (en Mintuos)],disponibilidad[RECARGAS],"SI",disponibilidad[Mes],$B9,disponibilidad[[Tipo de afectación ]],"caÍda total",disponibilidad[Responsable Falla],"Aliados o terceros",disponibilidad[Jer - Boyacá],"SI")))/$C9)*100 -> 100 | O9: =AVERAGE(L9:N9) -> 100 | P9: =SUMIFS(disponibilidad[Tiempo falla (en Mintuos)],disponibilidad[Mes],$B9,disponibilidad[[Tipo de afectación ]],"caÍda total",disponibilidad[Responsable Falla],"Matrix Tech",disponibilidad[Jer - Boyacá],"SI") -> 86 | Q9: =+P9/C9 -> 0.002059387 | R9: =SUMIFS(disponibilidad[Tiempo falla (en Mintuos)],disponibilidad[Mes],$B9,disponibilidad[[Tipo de afectación ]],"caÍda total",disponibilidad[Responsable Falla],"Aliados o terceros",disponibilidad[Acertemos - Cauca],"SI") -> 0 | S9: =+R9/C9 -> 0 | X9: JADE | Y9: =VLOOKUP($Y$7,$B$8:$R$17,3,FALSE) -> 99.794061
B10: Marzo | C10: =VLOOKUP(B10,Maestro!$A$7:$D$19,4,FALSE) -> 44640 | D10: =+(($C10-(SUMIFS(disponibilidad[Tiempo falla (en Mintuos)],disponibilidad[JADE],"SI",disponibilidad[Mes],$B10,disponibilidad[[Tipo de afectación ]],"caÍda total",disponibilidad[Responsable Falla],"Matrix Tech",disponibilidad[Jer - Boyacá],"SI",disponibilidad[Jer - Boyacá],"SI",disponibilidad[Jer - Boyacá],"SI",disponibilidad[Jer - Boyacá],"SI",disponibilidad[Jer - Boyacá],"SI",disponibilidad[Jer - Boyacá],"SI",disponibilidad[Jer - Boyacá],"SI",disponibilidad[Jer - Boyacá],"SI",disponibilidad[Jer - Boyacá],"SI",disponibilidad[Jer - Boyacá],"SI",disponibilidad[Jer - Boyacá],"SI",disponibilidad[Jer - Boyacá],"SI")))/$C10)*100 -> 100 | E10: =+(($C10-(SUMIFS(disponibilidad[Tiempo falla (en Mintuos)],disponibilidad[SIGA],"SI",disponibilidad[Mes],$B10,disponibilidad[[Tipo de afectación ]],"caÍda total",disponibilidad[Responsable Falla],"Matrix Tech",disponibilidad[Jer - Boyacá],"SI",disponibilidad[Jer - Boyacá],"SI",disponibilidad[Jer - Boyacá],"SI",disponibilidad[Jer - Boyacá],"SI",disponibilidad[Jer - Boyacá],"SI",disponibilidad[Jer - Boyacá],"SI",disponibilidad[Jer - Boyacá],"SI",disponibilidad[Jer - Boyacá],"SI",disponibilidad[Jer - Boyacá],"SI",disponibilidad[Jer - Boyacá],"SI",disponibilidad[Jer - Boyacá],"SI",disponibilidad[Jer - Boyacá],"SI")))/$C10)*100 -> 100 | F10: =SUMPRODUCT($D$7:$E$7,D10:E10)/$K$7 -> 100 | G10: =+(($C10-(SUMIFS(disponibilidad[Tiempo falla (en Mintuos)],disponibilidad[Apuestas - Chance],"SI",disponibilidad[Mes],$B10,disponibilidad[[Tipo de afectación ]],"caÍda total",disponibilidad[Responsable Falla],"Matrix Tech",disponibilidad[Jer - Boyacá],"SI")))/$C10)*100 -> 100 | H10: =+(($C10-(SUMIFS(disponibilidad[Tiempo falla (en Mintuos)],disponibilidad[PAGOS],"SI",disponibilidad[Mes],$B10,disponibilidad[[Tipo de afectación ]],"caÍda total",disponibilidad[Responsable Falla],"Matrix Tech",disponibilidad[Jer - Boyacá],"SI")))/$C10)*100 -> 100 | I10: =+(($C10-(SUMIFS(disponibilidad[Tiempo falla (en Mintuos)],disponibilidad[RECAUDOS],"SI",disponibilidad[Mes],$B10,disponibilidad[[Tipo de afectación ]],"caÍda total",disponibilidad[Responsable Falla],"Matrix Tech",disponibilidad[Jer - Boyacá],"SI")))/$C10)*100 -> 100 | J10: =+(($C10-(SUMIFS(disponibilidad[Tiempo falla (en Mintuos)],disponibilidad[RECARGAS],"SI",disponibilidad[Mes],$B10,disponibilidad[[Tipo de afectación ]],"caÍda total",disponibilidad[Responsable Falla],"Matrix Tech",disponibilidad[Jer - Boyacá],"SI")))/$C10)*100 -> 100 | K10: =SUMPRODUCT($G$7:$J$7,G10:J10)/$K$7 -> 100 | L10: =+(($C10-(SUMIFS(disponibilidad[Tiempo falla (en Mintuos)],disponibilidad[PAGOS],"SI",disponibilidad[Mes],$B10,disponibilidad[[Tipo de afectación ]],"caÍda total",disponibilidad[Responsable Falla],"Aliados o terceros",disponibilidad[Jer - Boyacá],"SI")))/$C10)*100 -> 100 | M10: =+(($C10-(SUMIFS(disponibilidad[Tiempo falla (en Mintuos)],disponibilidad[RECAUDOS],"SI",disponibilidad[Mes],$B10,disponibilidad[[Tipo de afectación ]],"caÍda total",disponibilidad[Responsable Falla],"Aliados o terceros",disponibilidad[Jer - Boyacá],"SI")))/$C10)*100 -> 100 | N10: =+(($C10-(SUMIFS(disponibilidad[Tiempo falla (en Mintuos)],disponibilidad[RECARGAS],"SI",disponibilidad[Mes],$B10,disponibilidad[[Tipo de afectación ]],"caÍda total",disponibilidad[Responsable Falla],"Aliados o terceros",disponibilidad[Jer - Boyacá],"SI")))/$C10)*100 -> 100 | O10: =AVERAGE(L10:N10) -> 100 | P10: =SUMIFS(disponibilidad[Tiempo falla (en Mintuos)],disponibilidad[Mes],$B10,disponibilidad[[Tipo de afectación ]],"caÍda total",disponibilidad[Responsable Falla],"Matrix Tech",disponibilidad[Jer - Boyacá],"SI") -> 0 | Q10: =+P10/C10 -> 0 | R10: =SUMIFS(disponibilidad[Tiempo falla (en Mintuos)],disponibilidad[Mes],$B10,disponibilidad[[Tipo de afectación ]],"caÍda total",disponibilidad[Responsable Falla],"Aliados o terceros",disponibilidad[Acertemos - Cauca],"SI") -> 0 | S10: =+R10/C10 -> 0 | X10: SIGA | Y10: =VLOOKUP($Y$7,$B$8:$R$17,4,FALSE) -> 100
B11: Abril | C11: =VLOOKUP(B11,Maestro!$A$7:$D$19,4,FALSE) -> 43200 | D11: =+(($C11-(SUMIFS(disponibilidad[Tiempo falla (en Mintuos)],disponibilidad[JADE],"SI",disponibilidad[Mes],$B11,disponibilidad[[Tipo de afectación ]],"caÍda total",disponibilidad[Responsable Falla],"Matrix Tech",disponibilidad[Jer - Boyacá],"SI",disponibilidad[Jer - Boyacá],"SI",disponibilidad[Jer - Boyacá],"SI",disponibilidad[Jer - Boyacá],"SI",disponibilidad[Jer - Boyacá],"SI",disponibilidad[Jer - Boyacá],"SI",disponibilidad[Jer - Boyacá],"SI",disponibilidad[Jer - Boyacá],"SI",disponibilidad[Jer - Boyacá],"SI",disponibilidad[Jer - Boyacá],"SI",disponibilidad[Jer - Boyacá],"SI",disponibilidad[Jer - Boyacá],"SI")))/$C11)*100 -> 100 | E11: =+(($C11-(SUMIFS(disponibilidad[Tiempo falla (en Mintuos)],disponibilidad[SIGA],"SI",disponibilidad[Mes],$B11,disponibilidad[[Tipo de afectación ]],"caÍda total",disponibilidad[Responsable Falla],"Matrix Tech",disponibilidad[Jer - Boyacá],"SI",disponibilidad[Jer - Boyacá],"SI",disponibilidad[Jer - Boyacá],"SI",disponibilidad[Jer - Boyacá],"SI",disponibilidad[Jer - Boyacá],"SI",disponibilidad[Jer - Boyacá],"SI",disponibilidad[Jer - Boyacá],"SI",disponibilidad[Jer - Boyacá],"SI",disponibilidad[Jer - Boyacá],"SI",disponibilidad[Jer - Boyacá],"SI",disponibilidad[Jer - Boyacá],"SI",disponibilidad[Jer - Boyacá],"SI")))/$C11)*100 -> 100 | F11: =SUMPRODUCT($D$7:$E$7,D11:E11)/$K$7 -> 100 | G11: =+(($C11-(SUMIFS(disponibilidad[Tiempo falla (en Mintuos)],disponibilidad[Apuestas - Chance],"SI",disponibilidad[Mes],$B11,disponibilidad[[Tipo de afectación ]],"caÍda total",disponibilidad[Responsable Falla],"Matrix Tech",disponibilidad[Jer - Boyacá],"SI")))/$C11)*100 -> 100 | H11: =+(($C11-(SUMIFS(disponibilidad[Tiempo falla (en Mintuos)],disponibilidad[PAGOS],"SI",disponibilidad[Mes],$B11,disponibilidad[[Tipo de afectación ]],"caÍda total",disponibilidad[Responsable Falla],"Matrix Tech",disponibilidad[Jer - Boyacá],"SI")))/$C11)*100 -> 100 | I11: =+(($C11-(SUMIFS(disponibilidad[Tiempo falla (en Mintuos)],disponibilidad[RECAUDOS],"SI",disponibilidad[Mes],$B11,disponibilidad[[Tipo de afectación ]],"caÍda total",disponibilidad[Responsable Falla],"Matrix Tech",disponibilidad[Jer - Boyacá],"SI")))/$C11)*100 -> 100 | J11: =+(($C11-(SUMIFS(disponibilidad[Tiempo falla (en Mintuos)],disponibilidad[RECARGAS],"SI",disponibilidad[Mes],$B11,disponibilidad[[Tipo de afectación ]],"caÍda total",disponibilidad[Responsable Falla],"Matrix Tech",disponibilidad[Jer - Boyacá],"SI")))/$C11)*100 -> 100 | K11: =SUMPRODUCT($G$7:$J$7,G11:J11)/$K$7 -> 100 | L11: =+(($C11-(SUMIFS(disponibilidad[Tiempo falla (en Mintuos)],disponibilidad[PAGOS],"SI",disponibilidad[Mes],$B11,disponibilidad[[Tipo de afectación ]],"caÍda total",disponibilidad[Responsable Falla],"Aliados o terceros",disponibilidad[Jer - Boyacá],"SI")))/$C11)*100 -> 100 | M11: =+(($C11-(SUMIFS(disponibilidad[Tiempo falla (en Mintuos)],disponibilidad[RECAUDOS],"SI",disponibilidad[Mes],$B11,disponibilidad[[Tipo de afectación ]],"caÍda total",disponibilidad[Responsable Falla],"Aliados o terceros",disponibilidad[Jer - Boyacá],"SI")))/$C11)*100 -> 100 | N11: =+(($C11-(SUMIFS(disponibilidad[Tiempo falla (en Mintuos)],disponibilidad[RECARGAS],"SI",disponibilidad[Mes],$B11,disponibilidad[[Tipo de afectación ]],"caÍda total",disponibilidad[Responsable Falla],"Aliados o terceros",disponibilidad[Jer - Boyacá],"SI")))/$C11)*100 -> 100 | O11: =AVERAGE(L11:N11) -> 100 | P11: =SUMIFS(disponibilidad[Tiempo falla (en Mintuos)],disponibilidad[Mes],$B11,disponibilidad[[Tipo de afectación ]],"caÍda total",disponibilidad[Responsable Falla],"Matrix Tech",disponibilidad[Jer - Boyacá],"SI") -> 0 | Q11: =+P11/C11 -> 0 | R11: =SUMIFS(disponibilidad[Tiempo falla (en Mintuos)],disponibilidad[Mes],$B11,disponibilidad[[Tipo de afectación ]],"caÍda total",disponibilidad[Responsable Falla],"Aliados o terceros",disponibilidad[Acertemos - Cauca],"SI") -> 0 | S11: =+R11/C11 -> 0 | X11: General Aplicacion. | Y11: =VLOOKUP($Y$7,$B$8:$R$17,7,FALSE) -> 99.794061
B12: Mayo | C12: =VLOOKUP(B12,Maestro!$A$7:$D$19,4,FALSE) -> 44640 | D12: =+(($C12-(SUMIFS(disponibilidad[Tiempo falla (en Mintuos)],disponibilidad[JADE],"SI",disponibilidad[Mes],$B12,disponibilidad[[Tipo de afectación ]],"caÍda total",disponibilidad[Responsable Falla],"Matrix Tech",disponibilidad[Jer - Boyacá],"SI",disponibilidad[Jer - Boyacá],"SI",disponibilidad[Jer - Boyacá],"SI",disponibilidad[Jer - Boyacá],"SI",disponibilidad[Jer - Boyacá],"SI",disponibilidad[Jer - Boyacá],"SI",disponibilidad[Jer - Boyacá],"SI",disponibilidad[Jer - Boyacá],"SI",disponibilidad[Jer - Boyacá],"SI",disponibilidad[Jer - Boyacá],"SI",disponibilidad[Jer - Boyacá],"SI",disponibilidad[Jer - Boyacá],"SI")))/$C12)*100 -> 100 | E12: =+(($C12-(SUMIFS(disponibilidad[Tiempo falla (en Mintuos)],disponibilidad[SIGA],"SI",disponibilidad[Mes],$B12,disponibilidad[[Tipo de afectación ]],"caÍda total",disponibilidad[Responsable Falla],"Matrix Tech",disponibilidad[Jer - Boyacá],"SI",disponibilidad[Jer - Boyacá],"SI",disponibilidad[Jer - Boyacá],"SI",disponibilidad[Jer - Boyacá],"SI",disponibilidad[Jer - Boyacá],"SI",disponibilidad[Jer - Boyacá],"SI",disponibilidad[Jer - Boyacá],"SI",disponibilidad[Jer - Boyacá],"SI",disponibilidad[Jer - Boyacá],"SI",disponibilidad[Jer - Boyacá],"SI",disponibilidad[Jer - Boyacá],"SI",disponibilidad[Jer - Boyacá],"SI")))/$C12)*100 -> 100 | F12: =SUMPRODUCT($D$7:$E$7,D12:E12)/$K$7 -> 100 | G12: =+(($C12-(SUMIFS(disponibilidad[Tiempo falla (en Mintuos)],disponibilidad[Apuestas - Chance],"SI",disponibilidad[Mes],$B12,disponibilidad[[Tipo de afectación ]],"caÍda total",disponibilidad[Responsable Falla],"Matrix Tech",disponibilidad[Jer - Boyacá],"SI")))/$C12)*100 -> 100 | H12: =+(($C12-(SUMIFS(disponibilidad[Tiempo falla (en Mintuos)],disponibilidad[PAGOS],"SI",disponibilidad[Mes],$B12,disponibilidad[[Tipo de afectación ]],"caÍda total",disponibilidad[Responsable Falla],"Matrix Tech",disponibilidad[Jer - Boyacá],"SI")))/$C12)*100 -> 100 | I12: =+(($C12-(SUMIFS(disponibilidad[Tiempo falla (en Mintuos)],disponibilidad[RECAUDOS],"SI",disponibilidad[Mes],$B12,disponibilidad[[Tipo de afectación ]],"caÍda total",disponibilidad[Responsable Falla],"Matrix Tech",disponibilidad[Jer - Boyacá],"SI")))/$C12)*100 -> 100 | J12: =+(($C12-(SUMIFS(disponibilidad[Tiempo falla (en Mintuos)],disponibilidad[RECARGAS],"SI",disponibilidad[Mes],$B12,disponibilidad[[Tipo de afectación ]],"caÍda total",disponibilidad[Responsable Falla],"Matrix Tech",disponibilidad[Jer - Boyacá],"SI")))/$C12)*100 -> 100 | K12: =SUMPRODUCT($G$7:$J$7,G12:J12)/$K$7 -> 100 | L12: =+(($C12-(SUMIFS(disponibilidad[Tiempo falla (en Mintuos)],disponibilidad[PAGOS],"SI",disponibilidad[Mes],$B12,disponibilidad[[Tipo de afectación ]],"caÍda total",disponibilidad[Responsable Falla],"Aliados o terceros",disponibilidad[Jer - Boyacá],"SI")))/$C12)*100 -> 100 | M12: =+(($C12-(SUMIFS(disponibilidad[Tiempo falla (en Mintuos)],disponibilidad[RECAUDOS],"SI",disponibilidad[Mes],$B12,disponibilidad[[Tipo de afectación ]],"caÍda total",disponibilidad[Responsable Falla],"Aliados o terceros",disponibilidad[Jer - Boyacá],"SI")))/$C12)*100 -> 100 | N12: =+(($C12-(SUMIFS(disponibilidad[Tiempo falla (en Mintuos)],disponibilidad[RECARGAS],"SI",disponibilidad[Mes],$B12,disponibilidad[[Tipo de afectación ]],"caÍda total",disponibilidad[Responsable Falla],"Aliados o terceros",disponibilidad[Jer - Boyacá],"SI")))/$C12)*100 -> 100 | O12: =AVERAGE(L12:N12) -> 100 | P12: =SUMIFS(disponibilidad[Tiempo falla (en Mintuos)],disponibilidad[Mes],$B12,disponibilidad[[Tipo de afectación ]],"caÍda total",disponibilidad[Responsable Falla],"Matrix Tech",disponibilidad[Jer - Boyacá],"SI") -> 0 | Q12: =+P12/C12 -> 0 | R12: =SUMIFS(disponibilidad[Tiempo falla (en Mintuos)],disponibilidad[Mes],$B12,disponibilidad[[Tipo de afectación ]],"caÍda total",disponibilidad[Responsable Falla],"Aliados o terceros",disponibilidad[Acertemos - Cauca],"SI") -> 0 | S12: =+R12/C12 -> 0
B13: Junio | C13: =VLOOKUP(B13,Maestro!$A$7:$D$19,4,FALSE) -> 43200 | D13: =+(($C13-(SUMIFS(disponibilidad[Tiempo falla (en Mintuos)],disponibilidad[JADE],"SI",disponibilidad[Mes],$B13,disponibilidad[[Tipo de afectación ]],"caÍda total",disponibilidad[Responsable Falla],"Matrix Tech",disponibilidad[Jer - Boyacá],"SI",disponibilidad[Jer - Boyacá],"SI",disponibilidad[Jer - Boyacá],"SI",disponibilidad[Jer - Boyacá],"SI",disponibilidad[Jer - Boyacá],"SI",disponibilidad[Jer - Boyacá],"SI",disponibilidad[Jer - Boyacá],"SI",disponibilidad[Jer - Boyacá],"SI",disponibilidad[Jer - Boyacá],"SI",disponibilidad[Jer - Boyacá],"SI",disponibilidad[Jer - Boyacá],"SI",disponibilidad[Jer - Boyacá],"SI")))/$C13)*100 -> 100 | E13: =+(($C13-(SUMIFS(disponibilidad[Tiempo falla (en Mintuos)],disponibilidad[SIGA],"SI",disponibilidad[Mes],$B13,disponibilidad[[Tipo de afectación ]],"caÍda total",disponibilidad[Responsable Falla],"Matrix Tech",disponibilidad[Jer - Boyacá],"SI",disponibilidad[Jer - Boyacá],"SI",disponibilidad[Jer - Boyacá],"SI",disponibilidad[Jer - Boyacá],"SI",disponibilidad[Jer - Boyacá],"SI",disponibilidad[Jer - Boyacá],"SI",disponibilidad[Jer - Boyacá],"SI",disponibilidad[Jer - Boyacá],"SI",disponibilidad[Jer - Boyacá],"SI",disponibilidad[Jer - Boyacá],"SI",disponibilidad[Jer - Boyacá],"SI",disponibilidad[Jer - Boyacá],"SI")))/$C13)*100 -> 100 | F13: =SUMPRODUCT($D$7:$E$7,D13:E13)/$K$7 -> 100 | G13: =+(($C13-(SUMIFS(disponibilidad[Tiempo falla (en Mintuos)],disponibilidad[Apuestas - Chance],"SI",disponibilidad[Mes],$B13,disponibilidad[[Tipo de afectación ]],"caÍda total",disponibilidad[Responsable Falla],"Matrix Tech",disponibilidad[Jer - Boyacá],"SI")))/$C13)*100 -> 100 | H13: =+(($C13-(SUMIFS(disponibilidad[Tiempo falla (en Mintuos)],disponibilidad[PAGOS],"SI",disponibilidad[Mes],$B13,disponibilidad[[Tipo de afectación ]],"caÍda total",disponibilidad[Responsable Falla],"Matrix Tech",disponibilidad[Jer - Boyacá],"SI")))/$C13)*100 -> 100 | I13: =+(($C13-(SUMIFS(disponibilidad[Tiempo falla (en Mintuos)],disponibilidad[RECAUDOS],"SI",disponibilidad[Mes],$B13,disponibilidad[[Tipo de afectación ]],"caÍda total",disponibilidad[Responsable Falla],"Matrix Tech",disponibilidad[Jer - Boyacá],"SI")))/$C13)*100 -> 100 | J13: =+(($C13-(SUMIFS(disponibilidad[Tiempo falla (en Mintuos)],disponibilidad[RECARGAS],"SI",disponibilidad[Mes],$B13,disponibilidad[[Tipo de afectación ]],"caÍda total",disponibilidad[Responsable Falla],"Matrix Tech",disponibilidad[Jer - Boyacá],"SI")))/$C13)*100 -> 100 | K13: =SUMPRODUCT($G$7:$J$7,G13:J13)/$K$7 -> 100 | L13: =+(($C13-(SUMIFS(disponibilidad[Tiempo falla (en Mintuos)],disponibilidad[PAGOS],"SI",disponibilidad[Mes],$B13,disponibilidad[[Tipo de afectación ]],"caÍda total",disponibilidad[Responsable Falla],"Aliados o terceros",disponibilidad[Jer - Boyacá],"SI")))/$C13)*100 -> 100 | M13: =+(($C13-(SUMIFS(disponibilidad[Tiempo falla (en Mintuos)],disponibilidad[RECAUDOS],"SI",disponibilidad[Mes],$B13,disponibilidad[[Tipo de afectación ]],"caÍda total",disponibilidad[Responsable Falla],"Aliados o terceros",disponibilidad[Jer - Boyacá],"SI")))/$C13)*100 -> 100 | N13: =+(($C13-(SUMIFS(disponibilidad[Tiempo falla (en Mintuos)],disponibilidad[RECARGAS],"SI",disponibilidad[Mes],$B13,disponibilidad[[Tipo de afectación ]],"caÍda total",disponibilidad[Responsable Falla],"Aliados o terceros",disponibilidad[Jer - Boyacá],"SI")))/$C13)*100 -> 100 | O13: =AVERAGE(L13:N13) -> 100 | P13: =SUMIFS(disponibilidad[Tiempo falla (en Mintuos)],disponibilidad[Mes],$B13,disponibilidad[[Tipo de afectación ]],"caÍda total",disponibilidad[Responsable Falla],"Matrix Tech",disponibilidad[Jer - Boyacá],"SI") -> 0 | Q13: =+P13/C13 -> 0 | R13: =SUMIFS(disponibilidad[Tiempo falla (en Mintuos)],disponibilidad[Mes],$B13,disponibilidad[[Tipo de afectación ]],"caÍda total",disponibilidad[Responsable Falla],"Aliados o terceros",disponibilidad[Acertemos - Cauca],"SI") -> 0 | S13: =+R13/C13 -> 0
B14: Julio | C14: =VLOOKUP(B14,Maestro!$A$7:$D$19,4,FALSE) -> 44640 | D14: =+(($C14-(SUMIFS(disponibilidad[Tiempo falla (en Mintuos)],disponibilidad[JADE],"SI",disponibilidad[Mes],$B14,disponibilidad[[Tipo de afectación ]],"caÍda total",disponibilidad[Responsable Falla],"Matrix Tech",disponibilidad[Jer - Boyacá],"SI",disponibilidad[Jer - Boyacá],"SI",disponibilidad[Jer - Boyacá],"SI",disponibilidad[Jer - Boyacá],"SI",disponibilidad[Jer - Boyacá],"SI",disponibilidad[Jer - Boyacá],"SI",disponibilidad[Jer - Boyacá],"SI",disponibilidad[Jer - Boyacá],"SI",disponibilidad[Jer - Boyacá],"SI",disponibilidad[Jer - Boyacá],"SI",disponibilidad[Jer - Boyacá],"SI",disponibilidad[Jer - Boyacá],"SI")))/$C14)*100 -> 100 | E14: =+(($C14-(SUMIFS(disponibilidad[Tiempo falla (en Mintuos)],disponibilidad[SIGA],"SI",disponibilidad[Mes],$B14,disponibilidad[[Tipo de afectación ]],"caÍda total",disponibilidad[Responsable Falla],"Matrix Tech",disponibilidad[Jer - Boyacá],"SI",disponibilidad[Jer - Boyacá],"SI",disponibilidad[Jer - Boyacá],"SI",disponibilidad[Jer - Boyacá],"SI",disponibilidad[Jer - Boyacá],"SI",disponibilidad[Jer - Boyacá],"SI",disponibilidad[Jer - Boyacá],"SI",disponibilidad[Jer - Boyacá],"SI",disponibilidad[Jer - Boyacá],"SI",disponibilidad[Jer - Boyacá],"SI",disponibilidad[Jer - Boyacá],"SI",disponibilidad[Jer - Boyacá],"SI")))/$C14)*100 -> 100 | F14: =SUMPRODUCT($D$7:$E$7,D14:E14)/$K$7 -> 100 | G14: =+(($C14-(SUMIFS(disponibilidad[Tiempo falla (en Mintuos)],disponibilidad[Apuestas - Chance],"SI",disponibilidad[Mes],$B14,disponibilidad[[Tipo de afectación ]],"caÍda total",disponibilidad[Responsable Falla],"Matrix Tech",disponibilidad[Jer - Boyacá],"SI")))/$C14)*100 -> 100 | H14: =+(($C14-(SUMIFS(disponibilidad[Tiempo falla (en Mintuos)],disponibilidad[PAGOS],"SI",disponibilidad[Mes],$B14,disponibilidad[[Tipo de afectación ]],"caÍda total",disponibilidad[Responsable Falla],"Matrix Tech",disponibilidad[Jer - Boyacá],"SI")))/$C14)*100 -> 100 | I14: =+(($C14-(SUMIFS(disponibilidad[Tiempo falla (en Mintuos)],disponibilidad[RECAUDOS],"SI",disponibilidad[Mes],$B14,disponibilidad[[Tipo de afectación ]],"caÍda total",disponibilidad[Responsable Falla],"Matrix Tech",disponibilidad[Jer - Boyacá],"SI")))/$C14)*100 -> 100 | J14: =+(($C14-(SUMIFS(disponibilidad[Tiempo falla (en Mintuos)],disponibilidad[RECARGAS],"SI",disponibilidad[Mes],$B14,disponibilidad[[Tipo de afectación ]],"caÍda total",disponibilidad[Responsable Falla],"Matrix Tech",disponibilidad[Jer - Boyacá],"SI")))/$C14)*100 -> 100 | K14: =SUMPRODUCT($G$7:$J$7,G14:J14)/$K$7 -> 100 | L14: =+(($C14-(SUMIFS(disponibilidad[Tiempo falla (en Mintuos)],disponibilidad[PAGOS],"SI",disponibilidad[Mes],$B14,disponibilidad[[Tipo de afectación ]],"caÍda total",disponibilidad[Responsable Falla],"Aliados o terceros",disponibilidad[Jer - Boyacá],"SI")))/$C14)*100 -> 100 | M14: =+(($C14-(SUMIFS(disponibilidad[Tiempo falla (en Mintuos)],disponibilidad[RECAUDOS],"SI",disponibilidad[Mes],$B14,disponibilidad[[Tipo de afectación ]],"caÍda total",disponibilidad[Responsable Falla],"Aliados o terceros",disponibilidad[Jer - Boyacá],"SI")))/$C14)*100 -> 100 | N14: =+(($C14-(SUMIFS(disponibilidad[Tiempo falla (en Mintuos)],disponibilidad[RECARGAS],"SI",disponibilidad[Mes],$B14,disponibilidad[[Tipo de afectación ]],"caÍda total",disponibilidad[Responsable Falla],"Aliados o terceros",disponibilidad[Jer - Boyacá],"SI")))/$C14)*100 -> 100 | O14: =AVERAGE(L14:N14) -> 100 | P14: =SUMIFS(disponibilidad[Tiempo falla (en Mintuos)],disponibilidad[Mes],$B14,disponibilidad[[Tipo de afectación ]],"caÍda total",disponibilidad[Responsable Falla],"Matrix Tech",disponibilidad[Jer - Boyacá],"SI") -> 0 | Q14: =+P14/C14 -> 0 | R14: =SUMIFS(disponibilidad[Tiempo falla (en Mintuos)],disponibilidad[Mes],$B14,disponibilidad[[Tipo de afectación ]],"caÍda total",disponibilidad[Responsable Falla],"Aliados o terceros",disponibilidad[Acertemos - Cauca],"SI") -> 0 | S14: =+R14/C14 -> 0
B15: Agosto | C15: =VLOOKUP(B15,Maestro!$A$7:$D$19,4,FALSE) -> 44640 | D15: =+(($C15-(SUMIFS(disponibilidad[Tiempo falla (en Mintuos)],disponibilidad[JADE],"SI",disponibilidad[Mes],$B15,disponibilidad[[Tipo de afectación ]],"caÍda total",disponibilidad[Responsable Falla],"Matrix Tech",disponibilidad[Jer - Boyacá],"SI",disponibilidad[Jer - Boyacá],"SI",disponibilidad[Jer - Boyacá],"SI",disponibilidad[Jer - Boyacá],"SI",disponibilidad[Jer - Boyacá],"SI",disponibilidad[Jer - Boyacá],"SI",disponibilidad[Jer - Boyacá],"SI",disponibilidad[Jer - Boyacá],"SI",disponibilidad[Jer - Boyacá],"SI",disponibilidad[Jer - Boyacá],"SI",disponibilidad[Jer - Boyacá],"SI",disponibilidad[Jer - Boyacá],"SI")))/$C15)*100 -> 100 | E15: =+(($C15-(SUMIFS(disponibilidad[Tiempo falla (en Mintuos)],disponibilidad[SIGA],"SI",disponibilidad[Mes],$B15,disponibilidad[[Tipo de afectación ]],"caÍda total",disponibilidad[Responsable Falla],"Matrix Tech",disponibilidad[Jer - Boyacá],"SI",disponibilidad[Jer - Boyacá],"SI",disponibilidad[Jer - Boyacá],"SI",disponibilidad[Jer - Boyacá],"SI",disponibilidad[Jer - Boyacá],"SI",disponibilidad[Jer - Boyacá],"SI",disponibilidad[Jer - Boyacá],"SI",disponibilidad[Jer - Boyacá],"SI",disponibilidad[Jer - Boyacá],"SI",disponibilidad[Jer - Boyacá],"SI",disponibilidad[Jer - Boyacá],"SI",disponibilidad[Jer - Boyacá],"SI")))/$C15)*100 -> 100 | F15: =SUMPRODUCT($D$7:$E$7,D15:E15)/$K$7 -> 100 | G15: =+(($C15-(SUMIFS(disponibilidad[Tiempo falla (en Mintuos)],disponibilidad[Apuestas - Chance],"SI",disponibilidad[Mes],$B15,disponibilidad[[Tipo de afectación ]],"caÍda total",disponibilidad[Responsable Falla],"Matrix Tech",disponibilidad[Jer - Boyacá],"SI")))/$C15)*100 -> 100 | H15: =+(($C15-(SUMIFS(disponibilidad[Tiempo falla (en Mintuos)],disponibilidad[PAGOS],"SI",disponibilidad[Mes],$B15,disponibilidad[[Tipo de afectación ]],"caÍda total",disponibilidad[Responsable Falla],"Matrix Tech",disponibilidad[Jer - Boyacá],"SI")))/$C15)*100 -> 100 | I15: =+(($C15-(SUMIFS(disponibilidad[Tiempo falla (en Mintuos)],disponibilidad[RECAUDOS],"SI",disponibilidad[Mes],$B15,disponibilidad[[Tipo de afectación ]],"caÍda total",disponibilidad[Responsable Falla],"Matrix Tech",disponibilidad[Jer - Boyacá],"SI")))/$C15)*100 -> 100 | J15: =+(($C15-(SUMIFS(disponibilidad[Tiempo falla (en Mintuos)],disponibilidad[RECARGAS],"SI",disponibilidad[Mes],$B15,disponibilidad[[Tipo de afectación ]],"caÍda total",disponibilidad[Responsable Falla],"Matrix Tech",disponibilidad[Jer - Boyacá],"SI")))/$C15)*100 -> 100 | K15: =SUMPRODUCT($G$7:$J$7,G15:J15)/$K$7 -> 100 | L15: =+(($C15-(SUMIFS(disponibilidad[Tiempo falla (en Mintuos)],disponibilidad[PAGOS],"SI",disponibilidad[Mes],$B15,disponibilidad[[Tipo de afectación ]],"caÍda total",disponibilidad[Responsable Falla],"Aliados o terceros",disponibilidad[Jer - Boyacá],"SI")))/$C15)*100 -> 100 | M15: =+(($C15-(SUMIFS(disponibilidad[Tiempo falla (en Mintuos)],disponibilidad[RECAUDOS],"SI",disponibilidad[Mes],$B15,disponibilidad[[Tipo de afectación ]],"caÍda total",disponibilidad[Responsable Falla],"Aliados o terceros",disponibilidad[Jer - Boyacá],"SI")))/$C15)*100 -> 100 | N15: =+(($C15-(SUMIFS(disponibilidad[Tiempo falla (en Mintuos)],disponibilidad[RECARGAS],"SI",disponibilidad[Mes],$B15,disponibilidad[[Tipo de afectación ]],"caÍda total",disponibilidad[Responsable Falla],"Aliados o terceros",disponibilidad[Jer - Boyacá],"SI")))/$C15)*100 -> 100 | O15: =AVERAGE(L15:N15) -> 100 | P15: =SUMIFS(disponibilidad[Tiempo falla (en Mintuos)],disponibilidad[Mes],$B15,disponibilidad[[Tipo de afectación ]],"caÍda total",disponibilidad[Responsable Falla],"Matrix Tech",disponibilidad[Jer - Boyacá],"SI") -> 0 | Q15: =+P15/C15 -> 0 | R15: =SUMIFS(disponibilidad[Tiempo falla (en Mintuos)],disponibilidad[Mes],$B15,disponibilidad[[Tipo de afectación ]],"caÍda total",disponibilidad[Responsable Falla],"Aliados o terceros",disponibilidad[Acertemos - Cauca],"SI") -> 0 | S15: =+R15/C15 -> 0 | X15: Apuestas - Chance | Y15: =VLOOKUP($Y$7,$B$8:$R$17,8,FALSE) -> 99.794061
B16: Septiembre | C16: =VLOOKUP(B16,Maestro!$A$7:$D$19,4,FALSE) -> 43200 | D16: =+(($C16-(SUMIFS(disponibilidad[Tiempo falla (en Mintuos)],disponibilidad[JADE],"SI",disponibilidad[Mes],$B16,disponibilidad[[Tipo de afectación ]],"caÍda total",disponibilidad[Responsable Falla],"Matrix Tech",disponibilidad[Jer - Boyacá],"SI",disponibilidad[Jer - Boyacá],"SI",disponibilidad[Jer - Boyacá],"SI",disponibilidad[Jer - Boyacá],"SI",disponibilidad[Jer - Boyacá],"SI",disponibilidad[Jer - Boyacá],"SI",disponibilidad[Jer - Boyacá],"SI",disponibilidad[Jer - Boyacá],"SI",disponibilidad[Jer - Boyacá],"SI",disponibilidad[Jer - Boyacá],"SI",disponibilidad[Jer - Boyacá],"SI",disponibilidad[Jer - Boyacá],"SI")))/$C16)*100 -> 100 | E16: =+(($C16-(SUMIFS(disponibilidad[Tiempo falla (en Mintuos)],disponibilidad[SIGA],"SI",disponibilidad[Mes],$B16,disponibilidad[[Tipo de afectación ]],"caÍda total",disponibilidad[Responsable Falla],"Matrix Tech",disponibilidad[Jer - Boyacá],"SI",disponibilidad[Jer - Boyacá],"SI",disponibilidad[Jer - Boyacá],"SI",disponibilidad[Jer - Boyacá],"SI",disponibilidad[Jer - Boyacá],"SI",disponibilidad[Jer - Boyacá],"SI",disponibilidad[Jer - Boyacá],"SI",disponibilidad[Jer - Boyacá],"SI",disponibilidad[Jer - Boyacá],"SI",disponibilidad[Jer - Boyacá],"SI",disponibilidad[Jer - Boyacá],"SI",disponibilidad[Jer - Boyacá],"SI")))/$C16)*100 -> 100 | F16: =SUMPRODUCT($D$7:$E$7,D16:E16)/$K$7 -> 100 | G16: =+(($C16-(SUMIFS(disponibilidad[Tiempo falla (en Mintuos)],disponibilidad[Apuestas - Chance],"SI",disponibilidad[Mes],$B16,disponibilidad[[Tipo de afectación ]],"caÍda total",disponibilidad[Responsable Falla],"Matrix Tech",disponibilidad[Jer - Boyacá],"SI")))/$C16)*100 -> 100 | H16: =+(($C16-(SUMIFS(disponibilidad[Tiempo falla (en Mintuos)],disponibilidad[PAGOS],"SI",disponibilidad[Mes],$B16,disponibilidad[[Tipo de afectación ]],"caÍda total",disponibilidad[Responsable Falla],"Matrix Tech",disponibilidad[Jer - Boyacá],"SI")))/$C16)*100 -> 100 | I16: =+(($C16-(SUMIFS(disponibilidad[Tiempo falla (en Mintuos)],disponibilidad[RECAUDOS],"SI",disponibilidad[Mes],$B16,disponibilidad[[Tipo de afectación ]],"caÍda total",disponibilidad[Responsable Falla],"Matrix Tech",disponibilidad[Jer - Boyacá],"SI")))/$C16)*100 -> 100 | J16: =+(($C16-(SUMIFS(disponibilidad[Tiempo falla (en Mintuos)],disponibilidad[RECARGAS],"SI",disponibilidad[Mes],$B16,disponibilidad[[Tipo de afectación ]],"caÍda total",disponibilidad[Responsable Falla],"Matrix Tech",disponibilidad[Jer - Boyacá],"SI")))/$C16)*100 -> 100 | K16: =SUMPRODUCT($G$7:$J$7,G16:J16)/$K$7 -> 100 | L16: =+(($C16-(SUMIFS(disponibilidad[Tiempo falla (en Mintuos)],disponibilidad[PAGOS],"SI",disponibilidad[Mes],$B16,disponibilidad[[Tipo de afectación ]],"caÍda total",disponibilidad[Responsable Falla],"Aliados o terceros",disponibilidad[Jer - Boyacá],"SI")))/$C16)*100 -> 100 | M16: =+(($C16-(SUMIFS(disponibilidad[Tiempo falla (en Mintuos)],disponibilidad[RECAUDOS],"SI",disponibilidad[Mes],$B16,disponibilidad[[Tipo de afectación ]],"caÍda total",disponibilidad[Responsable Falla],"Aliados o terceros",disponibilidad[Jer - Boyacá],"SI")))/$C16)*100 -> 100 | N16: =+(($C16-(SUMIFS(disponibilidad[Tiempo falla (en Mintuos)],disponibilidad[RECARGAS],"SI",disponibilidad[Mes],$B16,disponibilidad[[Tipo de afectación ]],"caÍda total",disponibilidad[Responsable Falla],"Aliados o terceros",disponibilidad[Jer - Boyacá],"SI")))/$C16)*100 -> 100 | O16: =AVERAGE(L16:N16) -> 100 | P16: =SUMIFS(disponibilidad[Tiempo falla (en Mintuos)],disponibilidad[Mes],$B16,disponibilidad[[Tipo de afectación ]],"caÍda total",disponibilidad[Responsable Falla],"Matrix Tech",disponibilidad[Jer - Boyacá],"SI") -> 0 | Q16: =+P16/C16 -> 0 | R16: =SUMIFS(disponibilidad[Tiempo falla (en Mintuos)],disponibilidad[Mes],$B16,disponibilidad[[Tipo de afectación ]],"caÍda total",disponibilidad[Responsable Falla],"Aliados o terceros",disponibilidad[Acertemos - Cauca],"SI") -> 0 | S16: =+R16/C16 -> 0 | X16: PAGOS | Y16: =VLOOKUP($Y$7,$B$8:$R$17,9,FALSE) -> 99.794061
B17: Octubre | C17: =VLOOKUP(B17,Maestro!$A$7:$D$19,4,FALSE) -> 44640 | D17: =+(($C17-(SUMIFS(disponibilidad[Tiempo falla (en Mintuos)],disponibilidad[JADE],"SI",disponibilidad[Mes],$B17,disponibilidad[[Tipo de afectación ]],"caÍda total",disponibilidad[Responsable Falla],"Matrix Tech",disponibilidad[Jer - Boyacá],"SI")))/$C17)*100 -> 100 | E17: =+(($C17-(SUMIFS(disponibilidad[Tiempo falla (en Mintuos)],disponibilidad[SIGA],"SI",disponibilidad[Mes],$B17,disponibilidad[[Tipo de afectación ]],"caÍda total",disponibilidad[Responsable Falla],"Matrix Tech",disponibilidad[Jer - Boyacá],"SI",disponibilidad[Jer - Boyacá],"SI",disponibilidad[Jer - Boyacá],"SI",disponibilidad[Jer - Boyacá],"SI",disponibilidad[Jer - Boyacá],"SI",disponibilidad[Jer - Boyacá],"SI",disponibilidad[Jer - Boyacá],"SI",disponibilidad[Jer - Boyacá],"SI",disponibilidad[Jer - Boyacá],"SI",disponibilidad[Jer - Boyacá],"SI",disponibilidad[Jer - Boyacá],"SI",disponibilidad[Jer - Boyacá],"SI")))/$C17)*100 -> 100 | F17: =SUMPRODUCT($D$7:$E$7,D17:E17)/$K$7 -> 100 | G17: =+(($C17-(SUMIFS(disponibilidad[Tiempo falla (en Mintuos)],disponibilidad[Apuestas - Chance],"SI",disponibilidad[Mes],$B17,disponibilidad[[Tipo de afectación ]],"caÍda total",disponibilidad[Responsable Falla],"Matrix Tech",disponibilidad[Jer - Boyacá],"SI")))/$C17)*100 -> 100 | H17: =+(($C17-(SUMIFS(disponibilidad[Tiempo falla (en Mintuos)],disponibilidad[PAGOS],"SI",disponibilidad[Mes],$B17,disponibilidad[[Tipo de afectación ]],"caÍda total",disponibilidad[Responsable Falla],"Matrix Tech",disponibilidad[Jer - Boyacá],"SI")))/$C17)*100 -> 100 | I17: =+(($C17-(SUMIFS(disponibilidad[Tiempo falla (en Mintuos)],disponibilidad[RECAUDOS],"SI",disponibilidad[Mes],$B17,disponibilidad[[Tipo de afectación ]],"caÍda total",disponibilidad[Responsable Falla],"Matrix Tech",disponibilidad[Jer - Boyacá],"SI")))/$C17)*100 -> 100 | J17: =+(($C17-(SUMIFS(disponibilidad[Tiempo falla (en Mintuos)],disponibilidad[RECARGAS],"SI",disponibilidad[Mes],$B17,disponibilidad[[Tipo de afectación ]],"caÍda total",disponibilidad[Responsable Falla],"Matrix Tech",disponibilidad[Jer - Boyacá],"SI")))/$C17)*100 -> 100 | K17: =SUMPRODUCT($G$7:$J$7,G17:J17)/$K$7 -> 100 | L17: =+(($C17-(SUMIFS(disponibilidad[Tiempo falla (en Mintuos)],disponibilidad[PAGOS],"SI",disponibilidad[Mes],$B17,disponibilidad[[Tipo de afectación ]],"caÍda total",disponibilidad[Responsable Falla],"Aliados o terceros",disponibilidad[Jer - Boyacá],"SI")))/$C17)*100 -> 100 | M17: =+(($C17-(SUMIFS(disponibilidad[Tiempo falla (en Mintuos)],disponibilidad[RECAUDOS],"SI",disponibilidad[Mes],$B17,disponibilidad[[Tipo de afectación ]],"caÍda total",disponibilidad[Responsable Falla],"Aliados o terceros",disponibilidad[Jer - Boyacá],"SI")))/$C17)*100 -> 100 | N17: =+(($C17-(SUMIFS(disponibilidad[Tiempo falla (en Mintuos)],disponibilidad[RECARGAS],"SI",disponibilidad[Mes],$B17,disponibilidad[[Tipo de afectación ]],"caÍda total",disponibilidad[Responsable Falla],"Aliados o terceros",disponibilidad[Jer - Boyacá],"SI")))/$C17)*100 -> 100 | O17: =AVERAGE(L17:N17) -> 100 | P17: =SUMIFS(disponibilidad[Tiempo falla (en Mintuos)],disponibilidad[Mes],$B17,disponibilidad[[Tipo de afectación ]],"caÍda total",disponibilidad[Responsable Falla],"Matrix Tech",disponibilidad[Jer - Boyacá],"SI") -> 0 | Q17: =+P17/C17 -> 0 | R17: =SUMIFS(disponibilidad[Tiempo falla (en Mintuos)],disponibilidad[Mes],$B17,disponibilidad[[Tipo de afectación ]],"caÍda total",disponibilidad[Responsable Falla],"Aliados o terceros",disponibilidad[Acertemos - Cauca],"SI") -> 0 | S17: =+R17/C17 -> 0 | X17: RECAUDOS | Y17: =VLOOKUP($Y$7,$B$8:$R$17,10,FALSE) -> 99.794061
B18: Noviembre | C18: =VLOOKUP(B18,Maestro!$A$7:$D$19,4,FALSE) -> 43200 | D18: =+(($C18-(SUMIFS(disponibilidad[Tiempo falla (en Mintuos)],disponibilidad[JADE],"SI",disponibilidad[Mes],$B18,disponibilidad[[Tipo de afectación ]],"caÍda total",disponibilidad[Responsable Falla],"Matrix Tech",disponibilidad[Jer - Boyacá],"SI")))/$C18)*100 -> 100 | E18: =+(($C18-(SUMIFS(disponibilidad[Tiempo falla (en Mintuos)],disponibilidad[SIGA],"SI",disponibilidad[Mes],$B18,disponibilidad[[Tipo de afectación ]],"caÍda total",disponibilidad[Responsable Falla],"Matrix Tech",disponibilidad[Jer - Boyacá],"SI",disponibilidad[Jer - Boyacá],"SI",disponibilidad[Jer - Boyacá],"SI",disponibilidad[Jer - Boyacá],"SI",disponibilidad[Jer - Boyacá],"SI",disponibilidad[Jer - Boyacá],"SI",disponibilidad[Jer - Boyacá],"SI",disponibilidad[Jer - Boyacá],"SI",disponibilidad[Jer - Boyacá],"SI",disponibilidad[Jer - Boyacá],"SI",disponibilidad[Jer - Boyacá],"SI",disponibilidad[Jer - Boyacá],"SI")))/$C18)*100 -> 100 | F18: =SUMPRODUCT($D$7:$E$7,D18:E18)/$K$7 -> 100 | G18: =+(($C18-(SUMIFS(disponibilidad[Tiempo falla (en Mintuos)],disponibilidad[Apuestas - Chance],"SI",disponibilidad[Mes],$B18,disponibilidad[[Tipo de afectación ]],"caÍda total",disponibilidad[Responsable Falla],"Matrix Tech",disponibilidad[Jer - Boyacá],"SI")))/$C18)*100 -> 100 | H18: =+(($C18-(SUMIFS(disponibilidad[Tiempo falla (en Mintuos)],disponibilidad[PAGOS],"SI",disponibilidad[Mes],$B18,disponibilidad[[Tipo de afectación ]],"caÍda total",disponibilidad[Responsable Falla],"Matrix Tech",disponibilidad[Jer - Boyacá],"SI")))/$C18)*100 -> 100 | I18: =+(($C18-(SUMIFS(disponibilidad[Tiempo falla (en Mintuos)],disponibilidad[RECAUDOS],"SI",disponibilidad[Mes],$B18,disponibilidad[[Tipo de afectación ]],"caÍda total",disponibilidad[Responsable Falla],"Matrix Tech",disponibilidad[Jer - Boyacá],"SI")))/$C18)*100 -> 100 | J18: =+(($C18-(SUMIFS(disponibilidad[Tiempo falla (en Mintuos)],disponibilidad[RECARGAS],"SI",disponibilidad[Mes],$B18,disponibilidad[[Tipo de afectación ]],"caÍda total",disponibilidad[Responsable Falla],"Matrix Tech",disponibilidad[Jer - Boyacá],"SI")))/$C18)*100 -> 100 | K18: =SUMPRODUCT($G$7:$J$7,G18:J18)/$K$7 -> 100 | L18: =+(($C18-(SUMIFS(disponibilidad[Tiempo falla (en Mintuos)],disponibilidad[PAGOS],"SI",disponibilidad[Mes],$B18,disponibilidad[[Tipo de afectación ]],"caÍda total",disponibilidad[Responsable Falla],"Aliados o terceros",disponibilidad[Jer - Boyacá],"SI")))/$C18)*100 -> 100 | M18: =+(($C18-(SUMIFS(disponibilidad[Tiempo falla (en Mintuos)],disponibilidad[RECAUDOS],"SI",disponibilidad[Mes],$B18,disponibilidad[[Tipo de afectación ]],"caÍda total",disponibilidad[Responsable Falla],"Aliados o terceros",disponibilidad[Jer - Boyacá],"SI")))/$C18)*100 -> 100 | N18: =+(($C18-(SUMIFS(disponibilidad[Tiempo falla (en Mintuos)],disponibilidad[RECARGAS],"SI",disponibilidad[Mes],$B18,disponibilidad[[Tipo de afectación ]],"caÍda total",disponibilidad[Responsable Falla],"Aliados o terceros",disponibilidad[Jer - Boyacá],"SI")))/$C18)*100 -> 100 | O18: =AVERAGE(L18:N18) -> 100 | P18: =SUMIFS(disponibilidad[Tiempo falla (en Mintuos)],disponibilidad[Mes],$B18,disponibilidad[[Tipo de afectación ]],"caÍda total",disponibilidad[Responsable Falla],"Matrix Tech",disponibilidad[Jer - Boyacá],"SI") -> 0 | Q18: =+P18/C18 -> 0 | R18: =SUMIFS(disponibilidad[Tiempo falla (en Mintuos)],disponibilidad[Mes],$B18,disponibilidad[[Tipo de afectación ]],"caÍda total",disponibilidad[Responsable Falla],"Aliados o terceros",disponibilidad[Acertemos - Cauca],"SI") -> 0 | S18: =+R18/C18 -> 0 | X18: RECARGAS | Y18: =VLOOKUP($Y$7,$B$8:$R$17,11,FALSE) -> 100
B19: Diciembre | C19: =VLOOKUP(B19,Maestro!$A$7:$D$19,4,FALSE) -> 44640 | D19: =+(($C19-(SUMIFS(disponibilidad[Tiempo falla (en Mintuos)],disponibilidad[JADE],"SI",disponibilidad[Mes],$B19,disponibilidad[[Tipo de afectación ]],"caÍda total",disponibilidad[Responsable Falla],"Matrix Tech",disponibilidad[Jer - Boyacá],"SI")))/$C19)*100 -> 100 | E19: =+(($C19-(SUMIFS(disponibilidad[Tiempo falla (en Mintuos)],disponibilidad[SIGA],"SI",disponibilidad[Mes],$B19,disponibilidad[[Tipo de afectación ]],"caÍda total",disponibilidad[Responsable Falla],"Matrix Tech",disponibilidad[Jer - Boyacá],"SI",disponibilidad[Jer - Boyacá],"SI",disponibilidad[Jer - Boyacá],"SI",disponibilidad[Jer - Boyacá],"SI",disponibilidad[Jer - Boyacá],"SI",disponibilidad[Jer - Boyacá],"SI",disponibilidad[Jer - Boyacá],"SI",disponibilidad[Jer - Boyacá],"SI",disponibilidad[Jer - Boyacá],"SI",disponibilidad[Jer - Boyacá],"SI",disponibilidad[Jer - Boyacá],"SI",disponibilidad[Jer - Boyacá],"SI")))/$C19)*100 -> 100 | F19: =SUMPRODUCT($D$7:$E$7,D19:E19)/$K$7 -> 100 | G19: =+(($C19-(SUMIFS(disponibilidad[Tiempo falla (en Mintuos)],disponibilidad[Apuestas - Chance],"SI",disponibilidad[Mes],$B19,disponibilidad[[Tipo de afectación ]],"caÍda total",disponibilidad[Responsable Falla],"Matrix Tech",disponibilidad[Jer - Boyacá],"SI")))/$C19)*100 -> 100 | H19: =+(($C19-(SUMIFS(disponibilidad[Tiempo falla (en Mintuos)],disponibilidad[PAGOS],"SI",disponibilidad[Mes],$B19,disponibilidad[[Tipo de afectación ]],"caÍda total",disponibilidad[Responsable Falla],"Matrix Tech",disponibilidad[Jer - Boyacá],"SI")))/$C19)*100 -> 100 | I19: =+(($C19-(SUMIFS(disponibilidad[Tiempo falla (en Mintuos)],disponibilidad[RECAUDOS],"SI",disponibilidad[Mes],$B19,disponibilidad[[Tipo de afectación ]],"caÍda total",disponibilidad[Responsable Falla],"Matrix Tech",disponibilidad[Jer - Boyacá],"SI")))/$C19)*100 -> 100 | J19: =+(($C19-(SUMIFS(disponibilidad[Tiempo falla (en Mintuos)],disponibilidad[RECARGAS],"SI",disponibilidad[Mes],$B19,disponibilidad[[Tipo de afectación ]],"caÍda total",disponibilidad[Responsable Falla],"Matrix Tech",disponibilidad[Jer - Boyacá],"SI")))/$C19)*100 -> 100 | K19: =SUMPRODUCT($G$7:$J$7,G19:J19)/$K$7 -> 100 | L19: =+(($C19-(SUMIFS(disponibilidad[Tiempo falla (en Mintuos)],disponibilidad[PAGOS],"SI",disponibilidad[Mes],$B19,disponibilidad[[Tipo de afectación ]],"caÍda total",disponibilidad[Responsable Falla],"Aliados o terceros",disponibilidad[Jer - Boyacá],"SI")))/$C19)*100 -> 100 | M19: =+(($C19-(SUMIFS(disponibilidad[Tiempo falla (en Mintuos)],disponibilidad[RECAUDOS],"SI",disponibilidad[Mes],$B19,disponibilidad[[Tipo de afectación ]],"caÍda total",disponibilidad[Responsable Falla],"Aliados o terceros",disponibilidad[Jer - Boyacá],"SI")))/$C19)*100 -> 100 | N19: =+(($C19-(SUMIFS(disponibilidad[Tiempo falla (en Mintuos)],disponibilidad[RECARGAS],"SI",disponibilidad[Mes],$B19,disponibilidad[[Tipo de afectación ]],"caÍda total",disponibilidad[Responsable Falla],"Aliados o terceros",disponibilidad[Jer - Boyacá],"SI")))/$C19)*100 -> 100 | O19: =AVERAGE(L19:N19) -> 100 | P19: =SUMIFS(disponibilidad[Tiempo falla (en Mintuos)],disponibilidad[Mes],$B19,disponibilidad[[Tipo de afectación ]],"caÍda total",disponibilidad[Responsable Falla],"Matrix Tech",disponibilidad[Jer - Boyacá],"SI") -> 0 | Q19: =+P19/C19 -> 0 | R19: =SUMIFS(disponibilidad[Tiempo falla (en Mintuos)],disponibilidad[Mes],$B19,disponibilidad[[Tipo de afectación ]],"caÍda total",disponibilidad[Responsable Falla],"Aliados o terceros",disponibilidad[Acertemos - Cauca],"SI") -> 0 | S19: =+R19/C19 -> 0 | X19: General Prod. | Y19: =VLOOKUP($Y$7,$B$8:$R$17,12,FALSE) -> 100

Sheet Novedades dia a dia
B1: # Caso | C1: Fecha actividad | D1: Producto | E1: Actividad | F1: Tiempo en minutos | G1: Analista
C2: 44602 | D2: Raspita | E2: VALIDACIONES PARA OBTENER EL CONSOLIDADO DE RASPITAS NO PAGADOS EN LAS REDES EL PASADO 09 DE FEBREO | F2: 240 MINUTOS | G2: Juan Gabriel Vanegas
B3: 329393 | C3: 44602 | D3: Giros | E3: REPLICA EN EL AMBIENTE DE QA CON AIDA PARA TRATAR DE IDENTIFICAR DE DONDE PROVIENE EL BLOQUEO DE LOS GIROS EN LA APP SUPERIOR A 2 MILLONES | F3: 180 MINUTOS | G3: Paola Perez
C4: 44603 | D4: Raspita | E4: VALIDACIONES CON DESARROLLO PARA CONFIRMAR EJECUCION DE UPDATE PARA RASPÍTA | F4: 60 MINUTOS | G4: Juan Gabriel Vanegas
C5: 44603 | D5: Raspita | E5: VALIDACIONES PARA OBTENER EL CONSOLIDADO DE RASPITAS NO PAGADOS EN LAS REDES EL PASADO 09 DE FEBREO | F5: 120 MINUTOS | G5: Laura Millan
C6: 44604 | D6: Raspita | E6: Confimacion de Cantidad de raspas a modificar con base de datos y validacion en bd de Gana de 9 premios pagados notificar a Jorge Cuellar | F6: 30 MINUTOS | G6: Juan Gabriel Vanegas
C7: 44606 | D7: Productos | E7: Apoyo a teleco y jorge de bd para validar la ip de produccion a prisma dos al compañero damian de desarrollo | F7: 30 MINUTOS | G7: Paola Perez
C8: 44606 | D8: Recaudos | E8: Configuracion del beps en matrixredes, enviado por correo tambien se llama a la señora rosy leon para que nos indique si los parametrios del confisys son los mismos que jer, el cual ella afirma que son los mismo | F8: 45 MINUTOS | G8: Paola Perez
C9: 44606 | D9: Recaudos | E9: se recibe llamada de james caro, para mostrarle y explicarle en mi administraciion como se encuentran los productos de los recaudos y en sigaadmin de produccion como se encuentra configurado el bolsillo y mi cuenta | F9: 15 MINUTOS | G9: Paola Perez
C10: 44606 | D10: Recaudos | E10: reunion para coordinar fecha y hora para la prueba que se deber realizar con el area de telecomunicaciones tema balanceadores | F10: 35 MINUTOS | G10: Jorgen Valdes
C11: 44606 | D11: Giros | E11: Apoyo con la configuracion de las nuevas palabras para la promo de giros al señor misael de bogota | F11: 30 MINUTOS | G11: Paola Perez
C12: 44606 | D12: Giros | E12: se apoya a la señora martha de bogota con un error reportado en mi oferta se valida con el ambiente de qa para poder validar en que aplicacion se encontraba el servicio | F12: 20 MINUTOS | G12: Paola Perez
C13: 44242 | D13: Productos | E13: Validacion de la mezcla compartida para huila y tolima con el producto billeton para huila y promocional para tolima para que sean mezclas compartidas esto se realiza en capacitacion se le entrega al cliente se adecua ambas bd de capacitacion en compañia de juan camilo garcia | F13: 240 MINUTOS | G13: Paola Perez
C14: 44608 | D14: Recaudos | E14: Reunion para revisar ausencia de recaudos Emonkey | F14: 60 minutos | G14: Juan Gabriel Vanegas
C15: 44608 | D15: Productos | E15: se capacita al señor edwin jojoba para la creacion de topes a sitios de venta | F15: 30 MINUTOS | G15: Paola Perez
... C18: 44609 | D18: Recargas | E18: Reunion Con Boyaca y CEM para validar diferencias con Recaudos y retiros Betplay | F18: 60 Minutos | G18: Juan Gabriel Vanegas
C19: 44608 | D19: Productos | E19: Reunion con la scrum y QA para revisión de incidente presentado con el ingreso de resultados del producto Suertudo | F19: 60 mINUTOS
C20: 44607 | D20: Productos | E20: Reunión con Personal contabilidad , nómina y Oreida Restrepo (psl )para validar las diferencias en la interfase nomina-contabilidad | F20: 90 minutos | G20: Helver Merchan
C21: 44608 | D21: Productos | E21: Reunión con Gilberto Castrillón y Proveedor del aplicativo Bpms, para dar conexión a bd y solucionar casos pendientes por parte del provvedor | F21: 60 MINUTOS | G21: Helver Merchan
C22: 44608 | D22: Productos | E22: Reunión con Juan Camilo Garcia (Base de datos ) para realizar pruebas de psl en motor oracle19c | F22: 30 minutos | G22: Helver Merchan
C23: 44610 | D23: Productos | E23: Reunión con personal de Réditos, para la presentacion de la nueva ejecutiva de cuenta de psl para Réditos | F23: 60 MINUTOS | G23: Helver Merchan
C24: 44610 | D24: Productos | E24: Reunión de Verficación proceso conciliación entre bpms-psl con personal de Réditos-Desarollo-Pol | F24: 30 miNUTOS | G24: Helver Merchan
C25: 44610 | D25: Productos | E25: Se apoya a mi compañera rosy a validar un caso en capacitacion GANA con chance EVENTO | F25: 240 MINUTOS | G25: Paola Perez
C26: 44612 | D26: Productos | E26: Validacion de correcto funcionamiento de URL migradas ('Autorizadores','Intermediario','migiro') | F26: 90 Minutos | G26: Juan Gabriel Vanegas
C27: 44613 | D27: Productos | E27: Generacion de consulta para Matrixgiros y servicios donde se observen las solicitudes de exoneracion desde el 01 de enero del 2017 a la fecha | F27: 40 miNUTOS | G27: Juan Gabriel Vanegas
C28: 44613 | D28: Productos | E28: reunion con personal de banco agrario y matrixtech prueba de concepto para habilitar contigencia -servicio su red por balanceadores, se acordo nuevamente reunion para el dia de mañana 22 de febrero 2022 a las 06:00 am | F28: 180 MINUTOS | G28: Jorgen Valdes
C29: 44613 | D29: Productos | E29: Se realiza acompañamiento de la prueba piloto de pagos internacionales con JER | F29: 45 MINUTOS | G29: Paola Perez
C30: 44613 | D30: Productos | E30: se realiza acompañamiento de la problemas de impresion en jer con los productos banco agrario | F30: 50 MINUTOS | G30: Paola Perez
C31: 44613 | D31: Productos | E31: Reunión sostenida con Yaira Montoya (analista ciberseguridad de Réditos) y Beatriz Villamizar (coordinadora recursos financieros de Réditos) para levantar perfil en psl para el proceso de auditoria | F31: 30 MINUTOS | G31: Helver Merchan
... C33: 44614 | D33: Productos | E33: Se realiza validacion con seguridad en plataforma sobre un incidente de mi seguirdad en produccion que no dejaba ingresar | F33: 60 MINUTOS | G33: Paola Perez
B34: 334861 | C34: 44614 | D34: Productos | E34: se valida con base de datos el caso 334861 | F34: 10 MINUTOS | G34: Paola Perez
C35: 44614 | D35: Productos | E35: reunion con personal de banco agrario y matrixtech prueba de concepto para habilitar contigencia -servicio su red por balanceadores, se realiza contacto con putumayo para proceder con prueba de consulkta de obligaciones Banco agrario | F35: 20 MINUTOS | G35: Juan Gabriel Vanegas
C36: 44614 | D36: Productos | E36: Busquedaen logs y reporte de novedad con aplicativo MIpos "Server returned HTTP response code: 403 for URL: https://prisma2-miseguridad.matrixtech.com.co/main/login | F36: 50 MINUTOS | G36: Juan Gabriel Vanegas
C37: 44614 | D37: Productos | E37: Conexión remota con psl y coordinadora de nómina de Réditos, sobre tema de certifacados de ingresos y retenciones año 2021 | F37: 30 MINUTOS | G37: Helver Merchan
B38: 328939 | C38: 44615 | D38: Recaudos | F38: 16 MINUTOS | G38: Paola Perez
C39: 44615 | D39: Productos | E39: Reportar novedad con envio de mensajeria para registro en la ASPPSUred A textobit (validacion en BD Busqueda de logs contactar al proveedor y enviar correo) | F39: 30 MINUTOS | G39: Juan Gabriel Vanegas
C40: 44615 | D40: Productos | E40: Reunión con equipo de la scrum Darcy para realizar pruebas sobre el producto Suertudo | F40: 30 MINUTOS | G40: Rossiris Mejia
C41: 44615 | D41: Productos | E41: Reunión con equipo de la scrum Darcy y el negocio para validar incidente con el identificador Suertudo | F41: 30 MINUTOS | G41: Rossiris Mejia
C42: 44615 | D42: Productos | E42: reunion con comercial de bogota y jjpita para validar el promocional de girod | F42: 20 MINUTOS | G42: Paola Perez
C43: 44616 | D43: Productos | E43: Verificacion de procesamiendo de archivo Avon y construccion de manual para futuras validaciones | F43: 60 MINUTOS | G43: Juan Gabriel Vanegas
C44: 44617 | D44: Productos | E44: Se realiza una reunion con direccion sistemas de jer y escrutinio de jer para la entrega de tareas automaticas | F44: 120 MINUTOS | G44: Paola Perez
C45: 44620 | D45: Giros | E45: Se realiza reunion con matrixredes con un tema de un descuadre de una asesora con unos giros de mipos | F45: 30 MINUTOS | G45: Paola Perez
C46: 44621 | D46: Productos | E46: Reunion con el cliente para validar incidente con la carga de bonos Oki por el aplicativo Siga (casos 345132-345349-345341-345088) | F46: 30 MINUTOS | G46: Rossiris Mejia
C47: 44621 | D47: Productos | E47: Revision de recargas en Gana sigt_transacciones_web where cod_confirmacion is null | F47: 120 MINUTOS | G47: Juan Gabriel Vanegas
C48: 44622 | D48: Productos | E48: Revision temas de auditoria de psl pendientes por resolver con Segio Bohorquez | F48: 20 MINUTOS | G48: Helver Merchan
C49: 44622 | D49: Productos | E49: Reunión con el desarrollador Miguel Angel Díaz, para validar servicio 9 de bpms que genera error en Sp de psl | F49: 20 MINUTOS | G49: Helver Merchan
C50: 44622 | D50: Recargas | E50: se realiza una reunion con direccion sistemas de jer, desarrollo y edwin para validar error de pines movilred en JER | F50: 10 MINUTOS | G50: Paola Perez
... C55: 44623 | D55: Productos | E55: Reunion validación conexión remota psl por webapp con la red tolima | F55: 120 MINUTOS | G55: Helver Merchan
B56: 361532 | C56: 44624 | D56: Recaudos | E56: se realiza una reunion con Jeer para la explicacion del incidente del calculo en la comision de beps | F56: 45 MINUTOS | G56: Paola Perez
C57: 44627 | D57: Productos | E57: Reunión con psl, para solucionar el error en la interface nomna contabilidad en Réditos | F57: 90 MINUTOS | G57: Helver Merchan
C58: 44627 | D58: Productos | E58: Reunión con proceso de tesoreria de Réditos para realizar notas automaticas en el modulo de tesoreria en psl | F58: 90 MINUTOS | G58: Helver Merchan
C59: 44628 | D59: Giros | E59: validacion de ambiente de capacitacion | F59: 210 MINUTOS | G59: Paola Perez
C60: 44629 | D60: Productos | E60: Reunión con la coordinadora de nómina de la red Tolima, se valida el nuevo estado de confirmación de la DIAN que muestra psl al transmitir la nómina electrónica | F60: 30 MINUTOS | G60: Helver Merchan
C61: 44629 | D61: Productos | E61: Reunión para Revisar los proceso de conciliaciones del aplicativo bpms para réditos | F61: 30 MINUTOS | G61: Helver Merchan
C62: 44629 | D62: Giros | E62: validacion de ambiente de capacitacion | F62: TODO EL DIA | G62: Paola Perez
C63: 44629 | D63: Recaudos | E63: Validacion de ambiente de capacitacion | F63: 390 MINUTOS | G63: Juan Gabriel Vanegas
C64: 44630 | D64: Giros | E64: validacion de ambiente de capacitacion | F64: 360 MINUTOS | G64: Paola Perez
C65: 44630 | D65: Recaudos | E65: validacion de errores que banco agrarip no esta guardando en la red, reunion con james la scrum, jhon rico el desarrollador y gustavo | F65: 15 MINUTOS | G65: Paola Perez
C66: 44630 | D66: Productos | E66: reunion con reditos sobre el tema de beps | F66: 45 MINUTOS | G66: Paola Perez
C67: 44630 | D67: Productos | E67: Reunion validación conexión remota psl por webapp con la red tolima y johan restrepo de telecomuicaciones matrixtech | F67: 48 MINUTOS | G67: Helver Merchan
C68: 44630 | D68: Productos | E68: Validacion de jerarquias para la perla | F68: 60 MINUTOS | G68: Paola Perez
... C98: 44646 | D98: Productos | E98: Actualización psl(erp, sipe) de Réditos ambiente de producción | F98: 180 MINUTOS | G98: Helver Merchan
B99: ID 397470 | C99: 44647 | D99: Giros | E99: Se realiza una mesa de trabajo para el cambio del trafico de giros de pagatodo de datacenter colombia para los JBOSS de terramark | F99: 210 MINUTOS | G99: JULIAN ANDRES CASTAÑEDA
C100: 44648 | D100: Productos | E100: Reunión con Camilo Garcia de Bd, validar conexión psl a oracle 19 | F100: 120 MINUTOS | G100: Helber Merchán
C101: 44649 | D101: Productos | E101: Conexión remota a usuario katherin Acevedo de Réditos, error al generar facturas en Psl | F101: 60 MINUTOS | G101: Helber Merchán
C102: 44649 | D102: Productos | E102: Reunión Con personal de Desarrollo de Matrixtech, para validar el servicio 9 de bpms-psl, ya que genera inconsistencia en los datos | F102: 60 MINUTOS | G102: Helber Merchán
C103: 44650 | D103: Productos | E103: Conexión remota con Soporte de Réditos, para validar instalació equipo nuevo de la coordinadora de nómina | F103: 160 MINTOS | G103: Helber Merchán
C104: 44651 | D104: Productos | E104: Reunión Con personal de Desarrollo de Matrixtech, para validar el servicio 9 de bpms-psl, ya que genera inconsistencia en los datos | F104: 60 MINUTOS | G104: Hebler Merchán
C105: 44651 | D105: Productos | E105: Conexión remota con Soporte de Réditos, para validar instalació equipo nuevo de la coordinadora de nómina y Laura Jaramillo | F105: 120 MINUTOS | G105: Helber Merchán
C106: 44652 | D106: Productos | E106: Solicitud de asignación usuario de luisa agudelo de Réditos a sipe | F106: 30 MINUTOS | G106: Helber Merchán
C107: 44653 | D107: Productos | E107: Actualización psl(erp, sipe) para todas las redes en ambiente de producción | F107: 200 MINUTOS | G107: Helber Merchán
C108: 44653 | D108: SIVICAL | E108: Validacion con Infra, desarrollo , BD y centro de gestion de error en Syncrocauca (Se ha encontrado una posible CONEXION sin CERRAR!!! 475720665) | F108: 75 MINUTOS | G108: Juan Gabriel Vanegas
C109: 44657 | D109: Productos | E109: Actualización manuales de psl y biable al proceso de soporte de Réditos, estos manuales estaban deactualizados | F109: 120 MINUTOS | G109: Helber Merchán
C110: 44657 | D110: Productos | E110: Validación y solución saldos de cuentas en Reditos con Patrica Carvajal y Margarita Sanchez | F110: 60 MINUTOS | G110: Helber Merchán
C111: 44657 | D111: Productos | E111: Reunión con proceso desarrollo y qa de matrixtech, validar servicio 9 bpms | F111: 60 MINUTOS | G111: Helber Merchán
... C123: 44684 | D123: Productos | E123: creación usuario mariana terrano en psl y sipe para reditos | F123: 30 MINUTOS | G123: Helber Merchán

Sheet Gana Gana - Tolima1
B2: Mes | C2: Minutos Mes | D2: Disponibilidad Individual Aplicación Matrix Tech | H2: Disponibilidad General Aplicación | I2: Disponibilidad Indivudual Producto Matrix Tech | O2: Disponibilidad General Producto | P2: Disponibilidad Indivudual Aplicación Aliados o Terceros | U2: Disponibilidad General Producto | V2: Matrix Tech | X2: Aliados - Terceros
D3: JADE | E3: SIGA | F3: MI POS - PRISMA 2 | G3: APP | I3: Apuestas - Chance | J3: GIROS | K3: PAGOS | L3: RECAUDOS | M3: RECARGAS | N3: SEGUROS | P3: GIROS | Q3: PAGOS | R3: RECAUDOS | S3: RECARGAS | T3: SEGUROS | V3: Tiempo Indisponibiliad | W3: % Indisponibiliad | X3: Tiempo Indisponibiliad | Y3: % Indisponibiliad
C4: AST/Peso | D4: 0.99 | E4: 0 | F4: 0 | G4: 0.01 | I4: 0.59691968 | J4: 0.086519543 | K4: 0.025875234 | L4: 0.18998599 | M4: 0.10042974 | N4: 0.00026981477 | O4: =SUM(I4:N4) -> 1
B5: Enero | C5: =VLOOKUP(B5,Maestro!$A$7:$D$19,4,FALSE) -> 44640 | D5: =+(($C5-(SUMIFS(disponibilidad[Tiempo falla (en Mintuos)],disponibilidad[JADE],"SI",disponibilidad[Mes],$B5,disponibilidad[[Tipo de afectación ]],"caÍda total",disponibilidad[Responsable Falla],"Matrix Tech",disponibilidad[Gana Gana - Tolima],"SI")))/$C5)*100 -> 99.955197 | E5: =+(($C5-(SUMIFS(disponibilidad[Tiempo falla (en Mintuos)],disponibilidad[JADE],"SI",disponibilidad[Mes],$B5,disponibilidad[[Tipo de afectación ]],"caÍda total",disponibilidad[Responsable Falla],"Matrix Tech",disponibilidad[Gana Gana - Tolima],"SI")))/$C5)*100 -> 99.955197 | F5: =+(($C5-(SUMIFS(disponibilidad[Tiempo falla (en Mintuos)],disponibilidad[JADE],"SI",disponibilidad[Mes],$B5,disponibilidad[[Tipo de afectación ]],"caÍda total",disponibilidad[Responsable Falla],"Matrix Tech",disponibilidad[Gana Gana - Tolima],"SI")))/$C5)*100 -> 99.955197 | G5: =+(($C5-(SUMIFS(disponibilidad[Tiempo falla (en Mintuos)],disponibilidad[JADE],"SI",disponibilidad[Mes],$B5,disponibilidad[[Tipo de afectación ]],"caÍda total",disponibilidad[Responsable Falla],"Matrix Tech",disponibilidad[Gana Gana - Tolima],"SI")))/$C5)*100 -> 99.955197 | H5: =SUMPRODUCT($D$4:$G$4,D5:G5)/$O$4 -> 99.955197 | I5: =+(($C5-(SUMIFS(disponibilidad[Tiempo falla (en Mintuos)],disponibilidad[Apuestas - Chance],"SI",disponibilidad[Mes],$B5,disponibilidad[[Tipo de afectación ]],"caÍda total",disponibilidad[Responsable Falla],"Matrix Tech",disponibilidad[Gana Gana - Tolima],"SI")))/$C5)*100 -> 99.955197 | J5: =+(($C5-(SUMIFS(disponibilidad[Tiempo falla (en Mintuos)],#REF!,"SI",disponibilidad[Mes],$B5,disponibilidad[[Tipo de afectación ]],"caÍda total",disponibilidad[Responsable Falla],"Matrix Tech",disponibilidad[Gana Gana - Tolima],"SI")))/$C5)*100 -> #REF! | K5: =+(($C5-(SUMIFS(disponibilidad[Tiempo falla (en Mintuos)],disponibilidad[PAGOS],"SI",disponibilidad[Mes],$B5,disponibilidad[[Tipo de afectación ]],"caÍda total",disponibilidad[Responsable Falla],"Matrix Tech",disponibilidad[Gana Gana - Tolima],"SI")))/$C5)*100 -> 99.955197 | L5: =+(($C5-(SUMIFS(disponibilidad[Tiempo falla (en Mintuos)],disponibilidad[RECAUDOS],"SI",disponibilidad[Mes],$B5,disponibilidad[[Tipo de afectación ]],"caÍda total",disponibilidad[Responsable Falla],"Matrix Tech",disponibilidad[Gana Gana - Tolima],"SI")))/$C5)*100 -> 99.955197 | M5: =+(($C5-(SUMIFS(disponibilidad[Tiempo falla (en Mintuos)],disponibilidad[RECARGAS],"SI",disponibilidad[Mes],$B5,disponibilidad[[Tipo de afectación ]],"caÍda total",disponibilidad[Responsable Falla],"Matrix Tech",disponibilidad[Gana Gana - Tolima],"SI")))/$C5)*100 -> 99.955197 | N5: =+(($C5-(SUMIFS(disponibilidad[Tiempo falla (en Mintuos)],#REF!,"SI",disponibilidad[Mes],$B5,disponibilidad[[Tipo de afectación ]],"caÍda total",disponibilidad[Responsable Falla],"Matrix Tech",disponibilidad[Gana Gana - Tolima],"SI")))/$C5)*100 -> #REF! | O5: =SUMPRODUCT($I$4:$N$4,I5:N5)/$O$4 -> #REF! | P5: =+(($C5-(SUMIFS(disponibilidad[Tiempo falla (en Mintuos)],#REF!,"SI",disponibilidad[Mes],$B5,disponibilidad[[Tipo de afectación ]],"caÍda total",disponibilidad[Responsable Falla],"Aliados o terceros",disponibilidad[Gana Gana - Tolima],"SI")))/$C5)*100 -> #REF! | Q5: =+(($C5-(SUMIFS(disponibilidad[Tiempo falla (en Mintuos)],disponibilidad[PAGOS],"SI",disponibilidad[Mes],$B5,disponibilidad[[Tipo de afectación ]],"caÍda total",disponibilidad[Responsable Falla],"Aliados o terceros",disponibilidad[Gana Gana - Tolima],"SI")))/$C5)*100 -> 100 | R5: =+(($C5-(SUMIFS(disponibilidad[Tiempo falla (en Mintuos)],disponibilidad[RECAUDOS],"SI",disponibilidad[Mes],$B5,disponibilidad[[Tipo de afectación ]],"caÍda total",disponibilidad[Responsable Falla],"Aliados o terceros",disponibilidad[Gana Gana - Tolima],"SI")))/$C5)*100 -> 100 | S5: =+(($C5-(SUMIFS(disponibilidad[Tiempo falla (en Mintuos)],disponibilidad[RECARGAS],"SI",disponibilidad[Mes],$B5,disponibilidad[[Tipo de afectación ]],"caÍda total",disponibilidad[Responsable Falla],"Aliados o terceros",disponibilidad[Gana Gana - Tolima],"SI")))/$C5)*100 -> 100 | T5: =+(($C5-(SUMIFS(disponibilidad[Tiempo falla (en Mintuos)],#REF!,"SI",disponibilidad[Mes],$B5,disponibilidad[[Tipo de afectación ]],"caÍda total",disponibilidad[Responsable Falla],"Aliados o terceros",disponibilidad[Gana Gana - Tolima],"SI")))/$C5)*100 -> #REF! | U5: =AVERAGE(P5:T5) -> #REF! | V5: =SUMIFS(disponibilidad[Tiempo falla (en Mintuos)],disponibilidad[Mes],$B5,disponibilidad[[Tipo de afectación ]],"caÍda total",disponibilidad[Responsable Falla],"Matrix Tech",disponibilidad[Gana Gana - Tolima],"SI") -> 20 | W5: =+$V$5/$C$5 -> 0.00044802867 | X5: =SUMIFS(disponibilidad[Tiempo falla (en Mintuos)],disponibilidad[Mes],$B5,disponibilidad[[Tipo de afectación ]],"caÍda total",disponibilidad[Responsable Falla],"Aliados o terceros",disponibilidad[Acertemos - Cauca],"SI") -> 0 | Y5: =+$X$5/$C$5 -> 0
B6: Febrero | C6: =VLOOKUP(B6,Maestro!$A$7:$D$19,4,FALSE) -> 41760 | D6: =+(($C6-(SUMIFS(disponibilidad[Tiempo falla (en Mintuos)],disponibilidad[JADE],"SI",disponibilidad[Mes],$B6,disponibilidad[[Tipo de afectación ]],"caÍda total",disponibilidad[Responsable Falla],"Matrix Tech",disponibilidad[Gana Gana - Tolima],"SI")))/$C6)*100 -> 99.940134 | E6: =+(($C6-(SUMIFS(disponibilidad[Tiempo falla (en Mintuos)],disponibilidad[JADE],"SI",disponibilidad[Mes],$B6,disponibilidad[[Tipo de afectación ]],"caÍda total",disponibilidad[Responsable Falla],"Matrix Tech",disponibilidad[Gana Gana - Tolima],"SI")))/$C6)*100 -> 99.940134 | F6: =+(($C6-(SUMIFS(disponibilidad[Tiempo falla (en Mintuos)],disponibilidad[JADE],"SI",disponibilidad[Mes],$B6,disponibilidad[[Tipo de afectación ]],"caÍda total",disponibilidad[Responsable Falla],"Matrix Tech",disponibilidad[Gana Gana - Tolima],"SI")))/$C6)*100 -> 99.940134 | G6: =+(($C6-(SUMIFS(disponibilidad[Tiempo falla (en Mintuos)],disponibilidad[JADE],"SI",disponibilidad[Mes],$B6,disponibilidad[[Tipo de afectación ]],"caÍda total",disponibilidad[Responsable Falla],"Matrix Tech",disponibilidad[Gana Gana - Tolima],"SI")))/$C6)*100 -> 99.940134 | H6: =SUMPRODUCT($D$4:$G$4,D6:G6)/$O$4 -> 99.940134 | I6: =+(($C6-(SUMIFS(disponibilidad[Tiempo falla (en Mintuos)],disponibilidad[Apuestas - Chance],"SI",disponibilidad[Mes],$B6,disponibilidad[[Tipo de afectación ]],"caÍda total",disponibilidad[Responsable Falla],"Matrix Tech",disponibilidad[Gana Gana - Tolima],"SI")))/$C6)*100 -> 99.940134 | J6: =+(($C6-(SUMIFS(disponibilidad[Tiempo falla (en Mintuos)],#REF!,"SI",disponibilidad[Mes],$B6,disponibilidad[[Tipo de afectación ]],"caÍda total",disponibilidad[Responsable Falla],"Matrix Tech",disponibilidad[Gana Gana - Tolima],"SI")))/$C6)*100 -> #REF! | K6: =+(($C6-(SUMIFS(disponibilidad[Tiempo falla (en Mintuos)],disponibilidad[PAGOS],"SI",disponibilidad[Mes],$B6,disponibilidad[[Tipo de afectación ]],"caÍda total",disponibilidad[Responsable Falla],"Matrix Tech",disponibilidad[Gana Gana - Tolima],"SI")))/$C6)*100 -> 99.940134 | L6: =+(($C6-(SUMIFS(disponibilidad[Tiempo falla (en Mintuos)],disponibilidad[RECAUDOS],"SI",disponibilidad[Mes],$B6,disponibilidad[[Tipo de afectación ]],"caÍda total",disponibilidad[Responsable Falla],"Matrix Tech",disponibilidad[Gana Gana - Tolima],"SI")))/$C6)*100 -> 99.940134 | M6: =+(($C6-(SUMIFS(disponibilidad[Tiempo falla (en Mintuos)],disponibilidad[RECARGAS],"SI",disponibilidad[Mes],$B6,disponibilidad[[Tipo de afectación ]],"caÍda total",disponibilidad[Responsable Falla],"Matrix Tech",disponibilidad[Gana Gana - Tolima],"SI")))/$C6)*100 -> 99.940134 | N6: =+(($C6-(SUMIFS(disponibilidad[Tiempo falla (en Mintuos)],#REF!,"SI",disponibilidad[Mes],$B6,disponibilidad[[Tipo de afectación ]],"caÍda total",disponibilidad[Responsable Falla],"Matrix Tech",disponibilidad[Gana Gana - Tolima],"SI")))/$C6)*100 -> #REF! | O6: =SUMPRODUCT($I$4:$N$4,I6:N6)/$O$4 -> #REF! | P6: =+(($C6-(SUMIFS(disponibilidad[Tiempo falla (en Mintuos)],#REF!,"SI",disponibilidad[Mes],$B6,disponibilidad[[Tipo de afectación ]],"caÍda total",disponibilidad[Responsable Falla],"Aliados o terceros",disponibilidad[Gana Gana - Tolima],"SI")))/$C6)*100 -> #REF! | Q6: =+(($C6-(SUMIFS(disponibilidad[Tiempo falla (en Mintuos)],disponibilidad[PAGOS],"SI",disponibilidad[Mes],$B6,disponibilidad[[Tipo de afectación ]],"caÍda total",disponibilidad[Responsable Falla],"Aliados o terceros",disponibilidad[Gana Gana - Tolima],"SI")))/$C6)*100 -> 100 | R6: =+(($C6-(SUMIFS(disponibilidad[Tiempo falla (en Mintuos)],disponibilidad[RECAUDOS],"SI",disponibilidad[Mes],$B6,disponibilidad[[Tipo de afectación ]],"caÍda total",disponibilidad[Responsable Falla],"Aliados o terceros",disponibilidad[Gana Gana - Tolima],"SI")))/$C6)*100 -> 100 | S6: =+(($C6-(SUMIFS(disponibilidad[Tiempo falla (en Mintuos)],disponibilidad[RECARGAS],"SI",disponibilidad[Mes],$B6,disponibilidad[[Tipo de afectación ]],"caÍda total",disponibilidad[Responsable Falla],"Aliados o terceros",disponibilidad[Gana Gana - Tolima],"SI")))/$C6)*100 -> 100 | T6: =+(($C6-(SUMIFS(disponibilidad[Tiempo falla (en Mintuos)],#REF!,"SI",disponibilidad[Mes],$B6,disponibilidad[[Tipo de afectación ]],"caÍda total",disponibilidad[Responsable Falla],"Aliados o terceros",disponibilidad[Gana Gana - Tolima],"SI")))/$C6)*100 -> #REF! | U6: =AVERAGE(P6:T6) -> #REF! | V6: =SUMIFS(disponibilidad[Tiempo falla (en Mintuos)],disponibilidad[Mes],$B6,disponibilidad[[Tipo de afectación ]],"caÍda total",disponibilidad[Responsable Falla],"Matrix Tech",disponibilidad[Gana Gana - Tolima],"SI") -> 25 | W6: =+V6/C6 -> 0.000598659 | X6: =SUMIFS(disponibilidad[Tiempo falla (en Mintuos)],disponibilidad[Mes],$B6,disponibilidad[[Tipo de afectación ]],"caÍda total",disponibilidad[Responsable Falla],"Aliados o terceros",disponibilidad[Acertemos - Cauca],"SI") -> 0 | Y6: =+$X$5/$C$5 -> 0
B7: Marzo | C7: =VLOOKUP(B7,Maestro!$A$7:$D$19,4,FALSE) -> 44640 | D7: =+(($C7-(SUMIFS(disponibilidad[Tiempo falla (en Mintuos)],disponibilidad[JADE],"SI",disponibilidad[Mes],$B7,disponibilidad[[Tipo de afectación ]],"caÍda total",disponibilidad[Responsable Falla],"Matrix Tech",disponibilidad[Gana Gana - Tolima],"SI")))/$C7)*100 -> 100 | E7: =+(($C7-(SUMIFS(disponibilidad[Tiempo falla (en Mintuos)],disponibilidad[JADE],"SI",disponibilidad[Mes],$B7,disponibilidad[[Tipo de afectación ]],"caÍda total",disponibilidad[Responsable Falla],"Matrix Tech",disponibilidad[Gana Gana - Tolima],"SI")))/$C7)*100 -> 100 | F7: =+(($C7-(SUMIFS(disponibilidad[Tiempo falla (en Mintuos)],disponibilidad[JADE],"SI",disponibilidad[Mes],$B7,disponibilidad[[Tipo de afectación ]],"caÍda total",disponibilidad[Responsable Falla],"Matrix Tech",disponibilidad[Gana Gana - Tolima],"SI")))/$C7)*100 -> 100 | G7: =+(($C7-(SUMIFS(disponibilidad[Tiempo falla (en Mintuos)],disponibilidad[JADE],"SI",disponibilidad[Mes],$B7,disponibilidad[[Tipo de afectación ]],"caÍda total",disponibilidad[Responsable Falla],"Matrix Tech",disponibilidad[Gana Gana - Tolima],"SI")))/$C7)*100 -> 100 | H7: =SUMPRODUCT($D$4:$G$4,D7:G7)/$O$4 -> 100 | I7: =+(($C7-(SUMIFS(disponibilidad[Tiempo falla (en Mintuos)],disponibilidad[Apuestas - Chance],"SI",disponibilidad[Mes],$B7,disponibilidad[[Tipo de afectación ]],"caÍda total",disponibilidad[Responsable Falla],"Matrix Tech",disponibilidad[Gana Gana - Tolima],"SI")))/$C7)*100 -> 100 | J7: =+(($C7-(SUMIFS(disponibilidad[Tiempo falla (en Mintuos)],#REF!,"SI",disponibilidad[Mes],$B7,disponibilidad[[Tipo de afectación ]],"caÍda total",disponibilidad[Responsable Falla],"Matrix Tech",disponibilidad[Gana Gana - Tolima],"SI")))/$C7)*100 -> #REF! | K7: =+(($C7-(SUMIFS(disponibilidad[Tiempo falla (en Mintuos)],disponibilidad[PAGOS],"SI",disponibilidad[Mes],$B7,disponibilidad[[Tipo de afectación ]],"caÍda total",disponibilidad[Responsable Falla],"Matrix Tech",disponibilidad[Gana Gana - Tolima],"SI")))/$C7)*100 -> 100 | L7: =+(($C7-(SUMIFS(disponibilidad[Tiempo falla (en Mintuos)],disponibilidad[RECAUDOS],"SI",disponibilidad[Mes],$B7,disponibilidad[[Tipo de afectación ]],"caÍda total",disponibilidad[Responsable Falla],"Matrix Tech",disponibilidad[Gana Gana - Tolima],"SI")))/$C7)*100 -> 100 | M7: =+(($C7-(SUMIFS(disponibilidad[Tiempo falla (en Mintuos)],disponibilidad[RECARGAS],"SI",disponibilidad[Mes],$B7,disponibilidad[[Tipo de afectación ]],"caÍda total",disponibilidad[Responsable Falla],"Matrix Tech",disponibilidad[Gana Gana - Tolima],"SI")))/$C7)*100 -> 100 | N7: =+(($C7-(SUMIFS(disponibilidad[Tiempo falla (en Mintuos)],#REF!,"SI",disponibilidad[Mes],$B7,disponibilidad[[Tipo de afectación ]],"caÍda total",disponibilidad[Responsable Falla],"Matrix Tech",disponibilidad[Gana Gana - Tolima],"SI")))/$C7)*100 -> #REF! | O7: =SUMPRODUCT($I$4:$N$4,I7:N7)/$O$4 -> #REF! | P7: =+(($C7-(SUMIFS(disponibilidad[Tiempo falla (en Mintuos)],#REF!,"SI",disponibilidad[Mes],$B7,disponibilidad[[Tipo de afectación ]],"caÍda total",disponibilidad[Responsable Falla],"Aliados o terceros",disponibilidad[Gana Gana - Tolima],"SI")))/$C7)*100 -> #REF! | Q7: =+(($C7-(SUMIFS(disponibilidad[Tiempo falla (en Mintuos)],disponibilidad[PAGOS],"SI",disponibilidad[Mes],$B7,disponibilidad[[Tipo de afectación ]],"caÍda total",disponibilidad[Responsable Falla],"Aliados o terceros",disponibilidad[Gana Gana - Tolima],"SI")))/$C7)*100 -> 100 | R7: =+(($C7-(SUMIFS(disponibilidad[Tiempo falla (en Mintuos)],disponibilidad[RECAUDOS],"SI",disponibilidad[Mes],$B7,disponibilidad[[Tipo de afectación ]],"caÍda total",disponibilidad[Responsable Falla],"Aliados o terceros",disponibilidad[Gana Gana - Tolima],"SI")))/$C7)*100 -> 100 | S7: =+(($C7-(SUMIFS(disponibilidad[Tiempo falla (en Mintuos)],disponibilidad[RECARGAS],"SI",disponibilidad[Mes],$B7,disponibilidad[[Tipo de afectación ]],"caÍda total",disponibilidad[Responsable Falla],"Aliados o terceros",disponibilidad[Gana Gana - Tolima],"SI")))/$C7)*100 -> 100 | T7: =+(($C7-(SUMIFS(disponibilidad[Tiempo falla (en Mintuos)],#REF!,"SI",disponibilidad[Mes],$B7,disponibilidad[[Tipo de afectación ]],"caÍda total",disponibilidad[Responsable Falla],"Aliados o terceros",disponibilidad[Gana Gana - Tolima],"SI")))/$C7)*100 -> #REF! | U7: =AVERAGE(P7:T7) -> #REF! | V7: =SUMIFS(disponibilidad[Tiempo falla (en Mintuos)],disponibilidad[Mes],$B7,disponibilidad[[Tipo de afectación ]],"caÍda total",disponibilidad[Responsable Falla],"Matrix Tech",disponibilidad[Gana Gana - Tolima],"SI") -> 0 | W7: =+V7/C7 -> 0 | X7: =SUMIFS(disponibilidad[Tiempo falla (en Mintuos)],disponibilidad[Mes],$B7,disponibilidad[[Tipo de afectación ]],"caÍda total",disponibilidad[Responsable Falla],"Aliados o terceros",disponibilidad[Acertemos - Cauca],"SI") -> 0 | Y7: =+$X$5/$C$5 -> 0
B8: Abril | C8: =VLOOKUP(B8,Maestro!$A$7:$D$19,4,FALSE) -> 43200 | D8: =+(($C8-(SUMIFS(disponibilidad[Tiempo falla (en Mintuos)],disponibilidad[JADE],"SI",disponibilidad[Mes],$B8,disponibilidad[[Tipo de afectación ]],"caÍda total",disponibilidad[Responsable Falla],"Matrix Tech",disponibilidad[Gana Gana - Tolima],"SI")))/$C8)*100 -> 100 | E8: =+(($C8-(SUMIFS(disponibilidad[Tiempo falla (en Mintuos)],disponibilidad[JADE],"SI",disponibilidad[Mes],$B8,disponibilidad[[Tipo de afectación ]],"caÍda total",disponibilidad[Responsable Falla],"Matrix Tech",disponibilidad[Gana Gana - Tolima],"SI")))/$C8)*100 -> 100 | F8: =+(($C8-(SUMIFS(disponibilidad[Tiempo falla (en Mintuos)],disponibilidad[JADE],"SI",disponibilidad[Mes],$B8,disponibilidad[[Tipo de afectación ]],"caÍda total",disponibilidad[Responsable Falla],"Matrix Tech",disponibilidad[Gana Gana - Tolima],"SI")))/$C8)*100 -> 100 | G8: =+(($C8-(SUMIFS(disponibilidad[Tiempo falla (en Mintuos)],disponibilidad[JADE],"SI",disponibilidad[Mes],$B8,disponibilidad[[Tipo de afectación ]],"caÍda total",disponibilidad[Responsable Falla],"Matrix Tech",disponibilidad[Gana Gana - Tolima],"SI")))/$C8)*100 -> 100 | H8: =SUMPRODUCT($D$4:$G$4,D8:G8)/$O$4 -> 100 | I8: =+(($C8-(SUMIFS(disponibilidad[Tiempo falla (en Mintuos)],disponibilidad[Apuestas - Chance],"SI",disponibilidad[Mes],$B8,disponibilidad[[Tipo de afectación ]],"caÍda total",disponibilidad[Responsable Falla],"Matrix Tech",disponibilidad[Gana Gana - Tolima],"SI")))/$C8)*100 -> 100 | J8: =+(($C8-(SUMIFS(disponibilidad[Tiempo falla (en Mintuos)],#REF!,"SI",disponibilidad[Mes],$B8,disponibilidad[[Tipo de afectación ]],"caÍda total",disponibilidad[Responsable Falla],"Matrix Tech",disponibilidad[Gana Gana - Tolima],"SI")))/$C8)*100 -> #REF! | K8: =+(($C8-(SUMIFS(disponibilidad[Tiempo falla (en Mintuos)],disponibilidad[PAGOS],"SI",disponibilidad[Mes],$B8,disponibilidad[[Tipo de afectación ]],"caÍda total",disponibilidad[Responsable Falla],"Matrix Tech",disponibilidad[Gana Gana - Tolima],"SI")))/$C8)*100 -> 100 | L8: =+(($C8-(SUMIFS(disponibilidad[Tiempo falla (en Mintuos)],disponibilidad[RECAUDOS],"SI",disponibilidad[Mes],$B8,disponibilidad[[Tipo de afectación ]],"caÍda total",disponibilidad[Responsable Falla],"Matrix Tech",disponibilidad[Gana Gana - Tolima],"SI")))/$C8)*100 -> 100 | M8: =+(($C8-(SUMIFS(disponibilidad[Tiempo falla (en Mintuos)],disponibilidad[RECARGAS],"SI",disponibilidad[Mes],$B8,disponibilidad[[Tipo de afectación ]],"caÍda total",disponibilidad[Responsable Falla],"Matrix Tech",disponibilidad[Gana Gana - Tolima],"SI")))/$C8)*100 -> 100 | N8: =+(($C8-(SUMIFS(disponibilidad[Tiempo falla (en Mintuos)],#REF!,"SI",disponibilidad[Mes],$B8,disponibilidad[[Tipo de afectación ]],"caÍda total",disponibilidad[Responsable Falla],"Matrix Tech",disponibilidad[Gana Gana - Tolima],"SI")))/$C8)*100 -> #REF! | O8: =SUMPRODUCT($I$4:$N$4,I8:N8)/$O$4 -> #REF! | P8: =+(($C8-(SUMIFS(disponibilidad[Tiempo falla (en Mintuos)],#REF!,"SI",disponibilidad[Mes],$B8,disponibilidad[[Tipo de afectación ]],"caÍda total",disponibilidad[Responsable Falla],"Aliados o terceros",disponibilidad[Gana Gana - Tolima],"SI")))/$C8)*100 -> #REF! | Q8: =+(($C8-(SUMIFS(disponibilidad[Tiempo falla (en Mintuos)],disponibilidad[PAGOS],"SI",disponibilidad[Mes],$B8,disponibilidad[[Tipo de afectación ]],"caÍda total",disponibilidad[Responsable Falla],"Aliados o terceros",disponibilidad[Gana Gana - Tolima],"SI")))/$C8)*100 -> 100 | R8: =+(($C8-(SUMIFS(disponibilidad[Tiempo falla (en Mintuos)],disponibilidad[RECAUDOS],"SI",disponibilidad[Mes],$B8,disponibilidad[[Tipo de afectación ]],"caÍda total",disponibilidad[Responsable Falla],"Aliados o terceros",disponibilidad[Gana Gana - Tolima],"SI")))/$C8)*100 -> 100 | S8: =+(($C8-(SUMIFS(disponibilidad[Tiempo falla (en Mintuos)],disponibilidad[RECARGAS],"SI",disponibilidad[Mes],$B8,disponibilidad[[Tipo de afectación ]],"caÍda total",disponibilidad[Responsable Falla],"Aliados o terceros",disponibilidad[Gana Gana - Tolima],"SI")))/$C8)*100 -> 100 | T8: =+(($C8-(SUMIFS(disponibilidad[Tiempo falla (en Mintuos)],#REF!,"SI",disponibilidad[Mes],$B8,disponibilidad[[Tipo de afectación ]],"caÍda total",disponibilidad[Responsable Falla],"Aliados o terceros",disponibilidad[Gana Gana - Tolima],"SI")))/$C8)*100 -> #REF! | U8: =AVERAGE(P8:T8) -> #REF! | V8: =SUMIFS(disponibilidad[Tiempo falla (en Mintuos)],disponibilidad[Mes],$B8,disponibilidad[[Tipo de afectación ]],"caÍda total",disponibilidad[Responsable Falla],"Matrix Tech",disponibilidad[Gana Gana - Tolima],"SI") -> 0 | W8: =+V8/C8 -> 0 | X8: =SUMIFS(disponibilidad[Tiempo falla (en Mintuos)],disponibilidad[Mes],$B8,disponibilidad[[Tipo de afectación ]],"caÍda total",disponibilidad[Responsable Falla],"Aliados o terceros",disponibilidad[Acertemos - Cauca],"SI") -> 0 | Y8: =+$X$5/$C$5 -> 0
B9: Mayo | C9: =VLOOKUP(B9,Maestro!$A$7:$D$19,4,FALSE) -> 44640 | D9: =+(($C9-(SUMIFS(disponibilidad[Tiempo falla (en Mintuos)],disponibilidad[JADE],"SI",disponibilidad[Mes],$B9,disponibilidad[[Tipo de afectación ]],"caÍda total",disponibilidad[Responsable Falla],"Matrix Tech",disponibilidad[Gana Gana - Tolima],"SI")))/$C9)*100 -> 100 | E9: =+(($C9-(SUMIFS(disponibilidad[Tiempo falla (en Mintuos)],disponibilidad[JADE],"SI",disponibilidad[Mes],$B9,disponibilidad[[Tipo de afectación ]],"caÍda total",disponibilidad[Responsable Falla],"Matrix Tech",disponibilidad[Gana Gana - Tolima],"SI")))/$C9)*100 -> 100 | F9: =+(($C9-(SUMIFS(disponibilidad[Tiempo falla (en Mintuos)],disponibilidad[JADE],"SI",disponibilidad[Mes],$B9,disponibilidad[[Tipo de afectación ]],"caÍda total",disponibilidad[Responsable Falla],"Matrix Tech",disponibilidad[Gana Gana - Tolima],"SI")))/$C9)*100 -> 100 | G9: =+(($C9-(SUMIFS(disponibilidad[Tiempo falla (en Mintuos)],disponibilidad[JADE],"SI",disponibilidad[Mes],$B9,disponibilidad[[Tipo de afectación ]],"caÍda total",disponibilidad[Responsable Falla],"Matrix Tech",disponibilidad[Gana Gana - Tolima],"SI")))/$C9)*100 -> 100 | H9: =SUMPRODUCT($D$4:$G$4,D9:G9)/$O$4 -> 100 | I9: =+(($C9-(SUMIFS(disponibilidad[Tiempo falla (en Mintuos)],disponibilidad[Apuestas - Chance],"SI",disponibilidad[Mes],$B9,disponibilidad[[Tipo de afectación ]],"caÍda total",disponibilidad[Responsable Falla],"Matrix Tech",disponibilidad[Gana Gana - Tolima],"SI")))/$C9)*100 -> 100 | J9: =+(($C9-(SUMIFS(disponibilidad[Tiempo falla (en Mintuos)],#REF!,"SI",disponibilidad[Mes],$B9,disponibilidad[[Tipo de afectación ]],"caÍda total",disponibilidad[Responsable Falla],"Matrix Tech",disponibilidad[Gana Gana - Tolima],"SI")))/$C9)*100 -> #REF! | K9: =+(($C9-(SUMIFS(disponibilidad[Tiempo falla (en Mintuos)],disponibilidad[PAGOS],"SI",disponibilidad[Mes],$B9,disponibilidad[[Tipo de afectación ]],"caÍda total",disponibilidad[Responsable Falla],"Matrix Tech",disponibilidad[Gana Gana - Tolima],"SI")))/$C9)*100 -> 100 | L9: =+(($C9-(SUMIFS(disponibilidad[Tiempo falla (en Mintuos)],disponibilidad[RECAUDOS],"SI",disponibilidad[Mes],$B9,disponibilidad[[Tipo de afectación ]],"caÍda total",disponibilidad[Responsable Falla],"Matrix Tech",disponibilidad[Gana Gana - Tolima],"SI")))/$C9)*100 -> 100 | M9: =+(($C9-(SUMIFS(disponibilidad[Tiempo falla (en Mintuos)],disponibilidad[RECARGAS],"SI",disponibilidad[Mes],$B9,disponibilidad[[Tipo de afectación ]],"caÍda total",disponibilidad[Responsable Falla],"Matrix Tech",disponibilidad[Gana Gana - Tolima],"SI")))/$C9)*100 -> 100 | N9: =+(($C9-(SUMIFS(disponibilidad[Tiempo falla (en Mintuos)],#REF!,"SI",disponibilidad[Mes],$B9,disponibilidad[[Tipo de afectación ]],"caÍda total",disponibilidad[Responsable Falla],"Matrix Tech",disponibilidad[Gana Gana - Tolima],"SI")))/$C9)*100 -> #REF! | O9: =SUMPRODUCT($I$4:$N$4,I9:N9)/$O$4 -> #REF! | P9: =+(($C9-(SUMIFS(disponibilidad[Tiempo falla (en Mintuos)],#REF!,"SI",disponibilidad[Mes],$B9,disponibilidad[[Tipo de afectación ]],"caÍda total",disponibilidad[Responsable Falla],"Aliados o terceros",disponibilidad[Gana Gana - Tolima],"SI")))/$C9)*100 -> #REF! | Q9: =+(($C9-(SUMIFS(disponibilidad[Tiempo falla (en Mintuos)],disponibilidad[PAGOS],"SI",disponibilidad[Mes],$B9,disponibilidad[[Tipo de afectación ]],"caÍda total",disponibilidad[Responsable Falla],"Aliados o terceros",disponibilidad[Gana Gana - Tolima],"SI")))/$C9)*100 -> 100 | R9: =+(($C9-(SUMIFS(disponibilidad[Tiempo falla (en Mintuos)],disponibilidad[RECAUDOS],"SI",disponibilidad[Mes],$B9,disponibilidad[[Tipo de afectación ]],"caÍda total",disponibilidad[Responsable Falla],"Aliados o terceros",disponibilidad[Gana Gana - Tolima],"SI")))/$C9)*100 -> 100 | S9: =+(($C9-(SUMIFS(disponibilidad[Tiempo falla (en Mintuos)],disponibilidad[RECARGAS],"SI",disponibilidad[Mes],$B9,disponibilidad[[Tipo de afectación ]],"caÍda total",disponibilidad[Responsable Falla],"Aliados o terceros",disponibilidad[Gana Gana - Tolima],"SI")))/$C9)*100 -> 100 | T9: =+(($C9-(SUMIFS(disponibilidad[Tiempo falla (en Mintuos)],#REF!,"SI",disponibilidad[Mes],$B9,disponibilidad[[Tipo de afectación ]],"caÍda total",disponibilidad[Responsable Falla],"Aliados o terceros",disponibilidad[Gana Gana - Tolima],"SI")))/$C9)*100 -> #REF! | U9: =AVERAGE(P9:T9) -> #REF! | V9: =SUMIFS(disponibilidad[Tiempo falla (en Mintuos)],disponibilidad[Mes],$B9,disponibilidad[[Tipo de afectación ]],"caÍda total",disponibilidad[Responsable Falla],"Matrix Tech",disponibilidad[Gana Gana - Tolima],"SI") -> 0 | W9: =+V9/C9 -> 0 | X9: =SUMIFS(disponibilidad[Tiempo falla (en Mintuos)],disponibilidad[Mes],$B9,disponibilidad[[Tipo de afectación ]],"caÍda total",disponibilidad[Responsable Falla],"Aliados o terceros",disponibilidad[Acertemos - Cauca],"SI") -> 0 | Y9: =+$X$5/$C$5 -> 0
B10: Junio | C10: =VLOOKUP(B10,Maestro!$A$7:$D$19,4,FALSE) -> 43200 | D10: =+(($C10-(SUMIFS(disponibilidad[Tiempo falla (en Mintuos)],disponibilidad[JADE],"SI",disponibilidad[Mes],$B10,disponibilidad[[Tipo de afectación ]],"caÍda total",disponibilidad[Responsable Falla],"Matrix Tech",disponibilidad[Gana Gana - Tolima],"SI")))/$C10)*100 -> 100 | E10: =+(($C10-(SUMIFS(disponibilidad[Tiempo falla (en Mintuos)],disponibilidad[JADE],"SI",disponibilidad[Mes],$B10,disponibilidad[[Tipo de afectación ]],"caÍda total",disponibilidad[Responsable Falla],"Matrix Tech",disponibilidad[Gana Gana - Tolima],"SI")))/$C10)*100 -> 100 | F10: =+(($C10-(SUMIFS(disponibilidad[Tiempo falla (en Mintuos)],disponibilidad[JADE],"SI",disponibilidad[Mes],$B10,disponibilidad[[Tipo de afectación ]],"caÍda total",disponibilidad[Responsable Falla],"Matrix Tech",disponibilidad[Gana Gana - Tolima],"SI")))/$C10)*100 -> 100 | G10: =+(($C10-(SUMIFS(disponibilidad[Tiempo falla (en Mintuos)],disponibilidad[JADE],"SI",disponibilidad[Mes],$B10,disponibilidad[[Tipo de afectación ]],"caÍda total",disponibilidad[Responsable Falla],"Matrix Tech",disponibilidad[Gana Gana - Tolima],"SI")))/$C10)*100 -> 100 | H10: =SUMPRODUCT($D$4:$G$4,D10:G10)/$O$4 -> 100 | I10: =+(($C10-(SUMIFS(disponibilidad[Tiempo falla (en Mintuos)],disponibilidad[Apuestas - Chance],"SI",disponibilidad[Mes],$B10,disponibilidad[[Tipo de afectación ]],"caÍda total",disponibilidad[Responsable Falla],"Matrix Tech",disponibilidad[Gana Gana - Tolima],"SI")))/$C10)*100 -> 100 | J10: =+(($C10-(SUMIFS(disponibilidad[Tiempo falla (en Mintuos)],#REF!,"SI",disponibilidad[Mes],$B10,disponibilidad[[Tipo de afectación ]],"caÍda total",disponibilidad[Responsable Falla],"Matrix Tech",disponibilidad[Gana Gana - Tolima],"SI")))/$C10)*100 -> #REF! | K10: =+(($C10-(SUMIFS(disponibilidad[Tiempo falla (en Mintuos)],disponibilidad[PAGOS],"SI",disponibilidad[Mes],$B10,disponibilidad[[Tipo de afectación ]],"caÍda total",disponibilidad[Responsable Falla],"Matrix Tech",disponibilidad[Gana Gana - Tolima],"SI")))/$C10)*100 -> 100 | L10: =+(($C10-(SUMIFS(disponibilidad[Tiempo falla (en Mintuos)],disponibilidad[RECAUDOS],"SI",disponibilidad[Mes],$B10,disponibilidad[[Tipo de afectación ]],"caÍda total",disponibilidad[Responsable Falla],"Matrix Tech",disponibilidad[Gana Gana - Tolima],"SI")))/$C10)*100 -> 100 | M10: =+(($C10-(SUMIFS(disponibilidad[Tiempo falla (en Mintuos)],disponibilidad[RECARGAS],"SI",disponibilidad[Mes],$B10,disponibilidad[[Tipo de afectación ]],"caÍda total",disponibilidad[Responsable Falla],"Matrix Tech",disponibilidad[Gana Gana - Tolima],"SI")))/$C10)*100 -> 100 | N10: =+(($C10-(SUMIFS(disponibilidad[Tiempo falla (en Mintuos)],#REF!,"SI",disponibilidad[Mes],$B10,disponibilidad[[Tipo de afectación ]],"caÍda total",disponibilidad[Responsable Falla],"Matrix Tech",disponibilidad[Gana Gana - Tolima],"SI")))/$C10)*100 -> #REF! | O10: =SUMPRODUCT($I$4:$N$4,I10:N10)/$O$4 -> #REF! | P10: =+(($C10-(SUMIFS(disponibilidad[Tiempo falla (en Mintuos)],#REF!,"SI",disponibilidad[Mes],$B10,disponibilidad[[Tipo de afectación ]],"caÍda total",disponibilidad[Responsable Falla],"Aliados o terceros",disponibilidad[Gana Gana - Tolima],"SI")))/$C10)*100 -> #REF! | Q10: =+(($C10-(SUMIFS(disponibilidad[Tiempo falla (en Mintuos)],disponibilidad[PAGOS],"SI",disponibilidad[Mes],$B10,disponibilidad[[Tipo de afectación ]],"caÍda total",disponibilidad[Responsable Falla],"Aliados o terceros",disponibilidad[Gana Gana - Tolima],"SI")))/$C10)*100 -> 100 | R10: =+(($C10-(SUMIFS(disponibilidad[Tiempo falla (en Mintuos)],disponibilidad[RECAUDOS],"SI",disponibilidad[Mes],$B10,disponibilidad[[Tipo de afectación ]],"caÍda total",disponibilidad[Responsable Falla],"Aliados o terceros",disponibilidad[Gana Gana - Tolima],"SI")))/$C10)*100 -> 100 | S10: =+(($C10-(SUMIFS(disponibilidad[Tiempo falla (en Mintuos)],disponibilidad[RECARGAS],"SI",disponibilidad[Mes],$B10,disponibilidad[[Tipo de afectación ]],"caÍda total",disponibilidad[Responsable Falla],"Aliados o terceros",disponibilidad[Gana Gana - Tolima],"SI")))/$C10)*100 -> 100 | T10: =+(($C10-(SUMIFS(disponibilidad[Tiempo falla (en Mintuos)],#REF!,"SI",disponibilidad[Mes],$B10,disponibilidad[[Tipo de afectación ]],"caÍda total",disponibilidad[Responsable Falla],"Aliados o terceros",disponibilidad[Gana Gana - Tolima],"SI")))/$C10)*100 -> #REF! | U10: =AVERAGE(P10:T10) -> #REF! | V10: =SUMIFS(disponibilidad[Tiempo falla (en Mintuos)],disponibilidad[Mes],$B10,disponibilidad[[Tipo de afectación ]],"caÍda total",disponibilidad[Responsable Falla],"Matrix Tech",disponibilidad[Gana Gana - Tolima],"SI") -> 0 | W10: =+V10/C10 -> 0 | X10: =SUMIFS(disponibilidad[Tiempo falla (en Mintuos)],disponibilidad[Mes],$B10,disponibilidad[[Tipo de afectación ]],"caÍda total",disponibilidad[Responsable Falla],"Aliados o terceros",disponibilidad[Acertemos - Cauca],"SI") -> 0 | Y10: =+$X$5/$C$5 -> 0
B11: Julio | C11: =VLOOKUP(B11,Maestro!$A$7:$D$19,4,FALSE) -> 44640 | D11: =+(($C11-(SUMIFS(disponibilidad[Tiempo falla (en Mintuos)],disponibilidad[JADE],"SI",disponibilidad[Mes],$B11,disponibilidad[[Tipo de afectación ]],"caÍda total",disponibilidad[Responsable Falla],"Matrix Tech",disponibilidad[Gana Gana - Tolima],"SI")))/$C11)*100 -> 100 | E11: =+(($C11-(SUMIFS(disponibilidad[Tiempo falla (en Mintuos)],disponibilidad[JADE],"SI",disponibilidad[Mes],$B11,disponibilidad[[Tipo de afectación ]],"caÍda total",disponibilidad[Responsable Falla],"Matrix Tech",disponibilidad[Gana Gana - Tolima],"SI")))/$C11)*100 -> 100 | F11: =+(($C11-(SUMIFS(disponibilidad[Tiempo falla (en Mintuos)],disponibilidad[JADE],"SI",disponibilidad[Mes],$B11,disponibilidad[[Tipo de afectación ]],"caÍda total",disponibilidad[Responsable Falla],"Matrix Tech",disponibilidad[Gana Gana - Tolima],"SI")))/$C11)*100 -> 100 | G11: =+(($C11-(SUMIFS(disponibilidad[Tiempo falla (en Mintuos)],disponibilidad[JADE],"SI",disponibilidad[Mes],$B11,disponibilidad[[Tipo de afectación ]],"caÍda total",disponibilidad[Responsable Falla],"Matrix Tech",disponibilidad[Gana Gana - Tolima],"SI")))/$C11)*100 -> 100 | H11: =SUMPRODUCT($D$4:$G$4,D11:G11)/$O$4 -> 100 | I11: =+(($C11-(SUMIFS(disponibilidad[Tiempo falla (en Mintuos)],disponibilidad[Apuestas - Chance],"SI",disponibilidad[Mes],$B11,disponibilidad[[Tipo de afectación ]],"caÍda total",disponibilidad[Responsable Falla],"Matrix Tech",disponibilidad[Gana Gana - Tolima],"SI")))/$C11)*100 -> 100 | J11: =+(($C11-(SUMIFS(disponibilidad[Tiempo falla (en Mintuos)],#REF!,"SI",disponibilidad[Mes],$B11,disponibilidad[[Tipo de afectación ]],"caÍda total",disponibilidad[Responsable Falla],"Matrix Tech",disponibilidad[Gana Gana - Tolima],"SI")))/$C11)*100 -> #REF! | K11: =+(($C11-(SUMIFS(disponibilidad[Tiempo falla (en Mintuos)],disponibilidad[PAGOS],"SI",disponibilidad[Mes],$B11,disponibilidad[[Tipo de afectación ]],"caÍda total",disponibilidad[Responsable Falla],"Matrix Tech",disponibilidad[Gana Gana - Tolima],"SI")))/$C11)*100 -> 100 | L11: =+(($C11-(SUMIFS(disponibilidad[Tiempo falla (en Mintuos)],disponibilidad[RECAUDOS],"SI",disponibilidad[Mes],$B11,disponibilidad[[Tipo de afectación ]],"caÍda total",disponibilidad[Responsable Falla],"Matrix Tech",disponibilidad[Gana Gana - Tolima],"SI")))/$C11)*100 -> 100 | M11: =+(($C11-(SUMIFS(disponibilidad[Tiempo falla (en Mintuos)],disponibilidad[RECARGAS],"SI",disponibilidad[Mes],$B11,disponibilidad[[Tipo de afectación ]],"caÍda total",disponibilidad[Responsable Falla],"Matrix Tech",disponibilidad[Gana Gana - Tolima],"SI")))/$C11)*100 -> 100 | N11: =+(($C11-(SUMIFS(disponibilidad[Tiempo falla (en Mintuos)],#REF!,"SI",disponibilidad[Mes],$B11,disponibilidad[[Tipo de afectación ]],"caÍda total",disponibilidad[Responsable Falla],"Matrix Tech",disponibilidad[Gana Gana - Tolima],"SI")))/$C11)*100 -> #REF! | O11: =SUMPRODUCT($I$4:$N$4,I11:N11)/$O$4 -> #REF! | P11: =+(($C11-(SUMIFS(disponibilidad[Tiempo falla (en Mintuos)],#REF!,"SI",disponibilidad[Mes],$B11,disponibilidad[[Tipo de afectación ]],"caÍda total",disponibilidad[Responsable Falla],"Aliados o terceros",disponibilidad[Gana Gana - Tolima],"SI")))/$C11)*100 -> #REF! | Q11: =+(($C11-(SUMIFS(disponibilidad[Tiempo falla (en Mintuos)],disponibilidad[PAGOS],"SI",disponibilidad[Mes],$B11,disponibilidad[[Tipo de afectación ]],"caÍda total",disponibilidad[Responsable Falla],"Aliados o terceros",disponibilidad[Gana Gana - Tolima],"SI")))/$C11)*100 -> 100 | R11: =+(($C11-(SUMIFS(disponibilidad[Tiempo falla (en Mintuos)],disponibilidad[RECAUDOS],"SI",disponibilidad[Mes],$B11,disponibilidad[[Tipo de afectación ]],"caÍda total",disponibilidad[Responsable Falla],"Aliados o terceros",disponibilidad[Gana Gana - Tolima],"SI")))/$C11)*100 -> 100 | S11: =+(($C11-(SUMIFS(disponibilidad[Tiempo falla (en Mintuos)],disponibilidad[RECARGAS],"SI",disponibilidad[Mes],$B11,disponibilidad[[Tipo de afectación ]],"caÍda total",disponibilidad[Responsable Falla],"Aliados o terceros",disponibilidad[Gana Gana - Tolima],"SI")))/$C11)*100 -> 100 | T11: =+(($C11-(SUMIFS(disponibilidad[Tiempo falla (en Mintuos)],#REF!,"SI",disponibilidad[Mes],$B11,disponibilidad[[Tipo de afectación ]],"caÍda total",disponibilidad[Responsable Falla],"Aliados o terceros",disponibilidad[Gana Gana - Tolima],"SI")))/$C11)*100 -> #REF! | U11: =AVERAGE(P11:T11) -> #REF! | V11: =SUMIFS(disponibilidad[Tiempo falla (en Mintuos)],disponibilidad[Mes],$B11,disponibilidad[[Tipo de afectación ]],"caÍda total",disponibilidad[Responsable Falla],"Matrix Tech",disponibilidad[Gana Gana - Tolima],"SI") -> 0 | W11: =+V11/C11 -> 0 | X11: =SUMIFS(disponibilidad[Tiempo falla (en Mintuos)],disponibilidad[Mes],$B11,disponibilidad[[Tipo de afectación ]],"caÍda total",disponibilidad[Responsable Falla],"Aliados o terceros",disponibilidad[Acertemos - Cauca],"SI") -> 0 | Y11: =+$X$5/$C$5 -> 0
B12: Agosto | C12: =VLOOKUP(B12,Maestro!$A$7:$D$19,4,FALSE) -> 44640 | D12: =+(($C12-(SUMIFS(disponibilidad[Tiempo falla (en Mintuos)],disponibilidad[JADE],"SI",disponibilidad[Mes],$B12,disponibilidad[[Tipo de afectación ]],"caÍda total",disponibilidad[Responsable Falla],"Matrix Tech",disponibilidad[Gana Gana - Tolima],"SI")))/$C12)*100 -> 100 | E12: =+(($C12-(SUMIFS(disponibilidad[Tiempo falla (en Mintuos)],disponibilidad[JADE],"SI",disponibilidad[Mes],$B12,disponibilidad[[Tipo de afectación ]],"caÍda total",disponibilidad[Responsable Falla],"Matrix Tech",disponibilidad[Gana Gana - Tolima],"SI")))/$C12)*100 -> 100 | F12: =+(($C12-(SUMIFS(disponibilidad[Tiempo falla (en Mintuos)],disponibilidad[JADE],"SI",disponibilidad[Mes],$B12,disponibilidad[[Tipo de afectación ]],"caÍda total",disponibilidad[Responsable Falla],"Matrix Tech",disponibilidad[Gana Gana - Tolima],"SI")))/$C12)*100 -> 100 | G12: =+(($C12-(SUMIFS(disponibilidad[Tiempo falla (en Mintuos)],disponibilidad[JADE],"SI",disponibilidad[Mes],$B12,disponibilidad[[Tipo de afectación ]],"caÍda total",disponibilidad[Responsable Falla],"Matrix Tech",disponibilidad[Gana Gana - Tolima],"SI")))/$C12)*100 -> 100 | H12: =SUMPRODUCT($D$4:$G$4,D12:G12)/$O$4 -> 100 | I12: =+(($C12-(SUMIFS(disponibilidad[Tiempo falla (en Mintuos)],disponibilidad[Apuestas - Chance],"SI",disponibilidad[Mes],$B12,disponibilidad[[Tipo de afectación ]],"caÍda total",disponibilidad[Responsable Falla],"Matrix Tech",disponibilidad[Gana Gana - Tolima],"SI")))/$C12)*100 -> 100 | J12: =+(($C12-(SUMIFS(disponibilidad[Tiempo falla (en Mintuos)],#REF!,"SI",disponibilidad[Mes],$B12,disponibilidad[[Tipo de afectación ]],"caÍda total",disponibilidad[Responsable Falla],"Matrix Tech",disponibilidad[Gana Gana - Tolima],"SI")))/$C12)*100 -> #REF! | K12: =+(($C12-(SUMIFS(disponibilidad[Tiempo falla (en Mintuos)],disponibilidad[PAGOS],"SI",disponibilidad[Mes],$B12,disponibilidad[[Tipo de afectación ]],"caÍda total",disponibilidad[Responsable Falla],"Matrix Tech",disponibilidad[Gana Gana - Tolima],"SI")))/$C12)*100 -> 100 | L12: =+(($C12-(SUMIFS(disponibilidad[Tiempo falla (en Mintuos)],disponibilidad[RECAUDOS],"SI",disponibilidad[Mes],$B12,disponibilidad[[Tipo de afectación ]],"caÍda total",disponibilidad[Responsable Falla],"Matrix Tech",disponibilidad[Gana Gana - Tolima],"SI")))/$C12)*100 -> 100 | M12: =+(($C12-(SUMIFS(disponibilidad[Tiempo falla (en Mintuos)],disponibilidad[RECARGAS],"SI",disponibilidad[Mes],$B12,disponibilidad[[Tipo de afectación ]],"caÍda total",disponibilidad[Responsable Falla],"Matrix Tech",disponibilidad[Gana Gana - Tolima],"SI")))/$C12)*100 -> 100 | N12: =+(($C12-(SUMIFS(disponibilidad[Tiempo falla (en Mintuos)],#REF!,"SI",disponibilidad[Mes],$B12,disponibilidad[[Tipo de afectación ]],"caÍda total",disponibilidad[Responsable Falla],"Matrix Tech",disponibilidad[Gana Gana - Tolima],"SI")))/$C12)*100 -> #REF! | O12: =SUMPRODUCT($I$4:$N$4,I12:N12)/$O$4 -> #REF! | P12: =+(($C12-(SUMIFS(disponibilidad[Tiempo falla (en Mintuos)],#REF!,"SI",disponibilidad[Mes],$B12,disponibilidad[[Tipo de afectación ]],"caÍda total",disponibilidad[Responsable Falla],"Aliados o terceros",disponibilidad[Gana Gana - Tolima],"SI")))/$C12)*100 -> #REF! | Q12: =+(($C12-(SUMIFS(disponibilidad[Tiempo falla (en Mintuos)],disponibilidad[PAGOS],"SI",disponibilidad[Mes],$B12,disponibilidad[[Tipo de afectación ]],"caÍda total",disponibilidad[Responsable Falla],"Aliados o terceros",disponibilidad[Gana Gana - Tolima],"SI")))/$C12)*100 -> 100 | R12: =+(($C12-(SUMIFS(disponibilidad[Tiempo falla (en Mintuos)],disponibilidad[RECAUDOS],"SI",disponibilidad[Mes],$B12,disponibilidad[[Tipo de afectación ]],"caÍda total",disponibilidad[Responsable Falla],"Aliados o terceros",disponibilidad[Gana Gana - Tolima],"SI")))/$C12)*100 -> 100 | S12: =+(($C12-(SUMIFS(disponibilidad[Tiempo falla (en Mintuos)],disponibilidad[RECARGAS],"SI",disponibilidad[Mes],$B12,disponibilidad[[Tipo de afectación ]],"caÍda total",disponibilidad[Responsable Falla],"Aliados o terceros",disponibilidad[Gana Gana - Tolima],"SI")))/$C12)*100 -> 100 | T12: =+(($C12-(SUMIFS(disponibilidad[Tiempo falla (en Mintuos)],#REF!,"SI",disponibilidad[Mes],$B12,disponibilidad[[Tipo de afectación ]],"caÍda total",disponibilidad[Responsable Falla],"Aliados o terceros",disponibilidad[Gana Gana - Tolima],"SI")))/$C12)*100 -> #REF! | U12: =AVERAGE(P12:T12) -> #REF! | V12: =SUMIFS(disponibilidad[Tiempo falla (en Mintuos)],disponibilidad[Mes],$B12,disponibilidad[[Tipo de afectación ]],"caÍda total",disponibilidad[Responsable Falla],"Matrix Tech",disponibilidad[Gana Gana - Tolima],"SI") -> 0 | W12: =+V12/C12 -> 0 | X12: =SUMIFS(disponibilidad[Tiempo falla (en Mintuos)],disponibilidad[Mes],$B12,disponibilidad[[Tipo de afectación ]],"caÍda total",disponibilidad[Responsable Falla],"Aliados o terceros",disponibilidad[Acertemos - Cauca],"SI") -> 0 | Y12: =+$X$5/$C$5 -> 0
B13: Septiembre | C13: =VLOOKUP(B13,Maestro!$A$7:$D$19,4,FALSE) -> 43200 | D13: =+(($C13-(SUMIFS(disponibilidad[Tiempo falla (en Mintuos)],disponibilidad[JADE],"SI",disponibilidad[Mes],$B13,disponibilidad[[Tipo de afectación ]],"caÍda total",disponibilidad[Responsable Falla],"Matrix Tech",disponibilidad[Gana Gana - Tolima],"SI")))/$C13)*100 -> 100 | E13: =+(($C13-(SUMIFS(disponibilidad[Tiempo falla (en Mintuos)],disponibilidad[JADE],"SI",disponibilidad[Mes],$B13,disponibilidad[[Tipo de afectación ]],"caÍda total",disponibilidad[Responsable Falla],"Matrix Tech",disponibilidad[Gana Gana - Tolima],"SI")))/$C13)*100 -> 100 | F13: =+(($C13-(SUMIFS(disponibilidad[Tiempo falla (en Mintuos)],disponibilidad[JADE],"SI",disponibilidad[Mes],$B13,disponibilidad[[Tipo de afectación ]],"caÍda total",disponibilidad[Responsable Falla],"Matrix Tech",disponibilidad[Gana Gana - Tolima],"SI")))/$C13)*100 -> 100 | G13: =+(($C13-(SUMIFS(disponibilidad[Tiempo falla (en Mintuos)],disponibilidad[JADE],"SI",disponibilidad[Mes],$B13,disponibilidad[[Tipo de afectación ]],"caÍda total",disponibilidad[Responsable Falla],"Matrix Tech",disponibilidad[Gana Gana - Tolima],"SI")))/$C13)*100 -> 100 | H13: =SUMPRODUCT($D$4:$G$4,D13:G13)/$O$4 -> 100 | I13: =+(($C13-(SUMIFS(disponibilidad[Tiempo falla (en Mintuos)],disponibilidad[Apuestas - Chance],"SI",disponibilidad[Mes],$B13,disponibilidad[[Tipo de afectación ]],"caÍda total",disponibilidad[Responsable Falla],"Matrix Tech",disponibilidad[Gana Gana - Tolima],"SI")))/$C13)*100 -> 100 | J13: =+(($C13-(SUMIFS(disponibilidad[Tiempo falla (en Mintuos)],#REF!,"SI",disponibilidad[Mes],$B13,disponibilidad[[Tipo de afectación ]],"caÍda total",disponibilidad[Responsable Falla],"Matrix Tech",disponibilidad[Gana Gana - Tolima],"SI")))/$C13)*100 -> #REF! | K13: =+(($C13-(SUMIFS(disponibilidad[Tiempo falla (en Mintuos)],disponibilidad[PAGOS],"SI",disponibilidad[Mes],$B13,disponibilidad[[Tipo de afectación ]],"caÍda total",disponibilidad[Responsable Falla],"Matrix Tech",disponibilidad[Gana Gana - Tolima],"SI")))/$C13)*100 -> 100 | L13: =+(($C13-(SUMIFS(disponibilidad[Tiempo falla (en Mintuos)],disponibilidad[RECAUDOS],"SI",disponibilidad[Mes],$B13,disponibilidad[[Tipo de afectación ]],"caÍda total",disponibilidad[Responsable Falla],"Matrix Tech",disponibilidad[Gana Gana - Tolima],"SI")))/$C13)*100 -> 100 | M13: =+(($C13-(SUMIFS(disponibilidad[Tiempo falla (en Mintuos)],disponibilidad[RECARGAS],"SI",disponibilidad[Mes],$B13,disponibilidad[[Tipo de afectación ]],"caÍda total",disponibilidad[Responsable Falla],"Matrix Tech",disponibilidad[Gana Gana - Tolima],"SI")))/$C13)*100 -> 100 | N13: =+(($C13-(SUMIFS(disponibilidad[Tiempo falla (en Mintuos)],#REF!,"SI",disponibilidad[Mes],$B13,disponibilidad[[Tipo de afectación ]],"caÍda total",disponibilidad[Responsable Falla],"Matrix Tech",disponibilidad[Gana Gana - Tolima],"SI")))/$C13)*100 -> #REF! | O13: =SUMPRODUCT($I$4:$N$4,I13:N13)/$O$4 -> #REF! | P13: =+(($C13-(SUMIFS(disponibilidad[Tiempo falla (en Mintuos)],#REF!,"SI",disponibilidad[Mes],$B13,disponibilidad[[Tipo de afectación ]],"caÍda total",disponibilidad[Responsable Falla],"Aliados o terceros",disponibilidad[Gana Gana - Tolima],"SI")))/$C13)*100 -> #REF! | Q13: =+(($C13-(SUMIFS(disponibilidad[Tiempo falla (en Mintuos)],disponibilidad[PAGOS],"SI",disponibilidad[Mes],$B13,disponibilidad[[Tipo de afectación ]],"caÍda total",disponibilidad[Responsable Falla],"Aliados o terceros",disponibilidad[Gana Gana - Tolima],"SI")))/$C13)*100 -> 100 | R13: =+(($C13-(SUMIFS(disponibilidad[Tiempo falla (en Mintuos)],disponibilidad[RECAUDOS],"SI",disponibilidad[Mes],$B13,disponibilidad[[Tipo de afectación ]],"caÍda total",disponibilidad[Responsable Falla],"Aliados o terceros",disponibilidad[Gana Gana - Tolima],"SI")))/$C13)*100 -> 100 | S13: =+(($C13-(SUMIFS(disponibilidad[Tiempo falla (en Mintuos)],disponibilidad[RECARGAS],"SI",disponibilidad[Mes],$B13,disponibilidad[[Tipo de afectación ]],"caÍda total",disponibilidad[Responsable Falla],"Aliados o terceros",disponibilidad[Gana Gana - Tolima],"SI")))/$C13)*100 -> 100 | T13: =+(($C13-(SUMIFS(disponibilidad[Tiempo falla (en Mintuos)],#REF!,"SI",disponibilidad[Mes],$B13,disponibilidad[[Tipo de afectación ]],"caÍda total",disponibilidad[Responsable Falla],"Aliados o terceros",disponibilidad[Gana Gana - Tolima],"SI")))/$C13)*100 -> #REF! | U13: =AVERAGE(P13:T13) -> #REF! | V13: =SUMIFS(disponibilidad[Tiempo falla (en Mintuos)],disponibilidad[Mes],$B13,disponibilidad[[Tipo de afectación ]],"caÍda total",disponibilidad[Responsable Falla],"Matrix Tech",disponibilidad[Gana Gana - Tolima],"SI") -> 0 | W13: =+V13/C13 -> 0 | X13: =SUMIFS(disponibilidad[Tiempo falla (en Mintuos)],disponibilidad[Mes],$B13,disponibilidad[[Tipo de afectación ]],"caÍda total",disponibilidad[Responsable Falla],"Aliados o terceros",disponibilidad[Acertemos - Cauca],"SI") -> 0 | Y13: =+$X$5/$C$5 -> 0
B14: Octubre | C14: =VLOOKUP(B14,Maestro!$A$7:$D$19,4,FALSE) -> 44640 | D14: =+(($C14-(SUMIFS(disponibilidad[Tiempo falla (en Mintuos)],disponibilidad[JADE],"SI",disponibilidad[Mes],$B14,disponibilidad[[Tipo de afectación ]],"caÍda total",disponibilidad[Responsable Falla],"Matrix Tech",disponibilidad[Gana Gana - Tolima],"SI")))/$C14)*100 -> 100 | E14: =+(($C14-(SUMIFS(disponibilidad[Tiempo falla (en Mintuos)],disponibilidad[JADE],"SI",disponibilidad[Mes],$B14,disponibilidad[[Tipo de afectación ]],"caÍda total",disponibilidad[Responsable Falla],"Matrix Tech",disponibilidad[Gana Gana - Tolima],"SI")))/$C14)*100 -> 100 | F14: =+(($C14-(SUMIFS(disponibilidad[Tiempo falla (en Mintuos)],disponibilidad[JADE],"SI",disponibilidad[Mes],$B14,disponibilidad[[Tipo de afectación ]],"caÍda total",disponibilidad[Responsable Falla],"Matrix Tech",disponibilidad[Gana Gana - Tolima],"SI")))/$C14)*100 -> 100 | G14: =+(($C14-(SUMIFS(disponibilidad[Tiempo falla (en Mintuos)],disponibilidad[JADE],"SI",disponibilidad[Mes],$B14,disponibilidad[[Tipo de afectación ]],"caÍda total",disponibilidad[Responsable Falla],"Matrix Tech",disponibilidad[Gana Gana - Tolima],"SI")))/$C14)*100 -> 100 | H14: =SUMPRODUCT($D$4:$G$4,D14:G14)/$O$4 -> 100 | I14: =+(($C14-(SUMIFS(disponibilidad[Tiempo falla (en Mintuos)],disponibilidad[Apuestas - Chance],"SI",disponibilidad[Mes],$B14,disponibilidad[[Tipo de afectación ]],"caÍda total",disponibilidad[Responsable Falla],"Matrix Tech",disponibilidad[Gana Gana - Tolima],"SI")))/$C14)*100 -> 100 | J14: =+(($C14-(SUMIFS(disponibilidad[Tiempo falla (en Mintuos)],#REF!,"SI",disponibilidad[Mes],$B14,disponibilidad[[Tipo de afectación ]],"caÍda total",disponibilidad[Responsable Falla],"Matrix Tech",disponibilidad[Gana Gana - Tolima],"SI")))/$C14)*100 -> #REF! | K14: =+(($C14-(SUMIFS(disponibilidad[Tiempo falla (en Mintuos)],disponibilidad[PAGOS],"SI",disponibilidad[Mes],$B14,disponibilidad[[Tipo de afectación ]],"caÍda total",disponibilidad[Responsable Falla],"Matrix Tech",disponibilidad[Gana Gana - Tolima],"SI")))/$C14)*100 -> 100 | L14: =+(($C14-(SUMIFS(disponibilidad[Tiempo falla (en Mintuos)],disponibilidad[RECAUDOS],"SI",disponibilidad[Mes],$B14,disponibilidad[[Tipo de afectación ]],"caÍda total",disponibilidad[Responsable Falla],"Matrix Tech",disponibilidad[Gana Gana - Tolima],"SI")))/$C14)*100 -> 100 | M14: =+(($C14-(SUMIFS(disponibilidad[Tiempo falla (en Mintuos)],disponibilidad[RECARGAS],"SI",disponibilidad[Mes],$B14,disponibilidad[[Tipo de afectación ]],"caÍda total",disponibilidad[Responsable Falla],"Matrix Tech",disponibilidad[Gana Gana - Tolima],"SI")))/$C14)*100 -> 100 | N14: =+(($C14-(SUMIFS(disponibilidad[Tiempo falla (en Mintuos)],#REF!,"SI",disponibilidad[Mes],$B14,disponibilidad[[Tipo de afectación ]],"caÍda total",disponibilidad[Responsable Falla],"Matrix Tech",disponibilidad[Gana Gana - Tolima],"SI")))/$C14)*100 -> #REF! | O14: =SUMPRODUCT($I$4:$N$4,I14:N14)/$O$4 -> #REF! | P14: =+(($C14-(SUMIFS(disponibilidad[Tiempo falla (en Mintuos)],#REF!,"SI",disponibilidad[Mes],$B14,disponibilidad[[Tipo de afectación ]],"caÍda total",disponibilidad[Responsable Falla],"Aliados o terceros",disponibilidad[Gana Gana - Tolima],"SI")))/$C14)*100 -> #REF! | Q14: =+(($C14-(SUMIFS(disponibilidad[Tiempo falla (en Mintuos)],disponibilidad[PAGOS],"SI",disponibilidad[Mes],$B14,disponibilidad[[Tipo de afectación ]],"caÍda total",disponibilidad[Responsable Falla],"Aliados o terceros",disponibilidad[Gana Gana - Tolima],"SI")))/$C14)*100 -> 100 | R14: =+(($C14-(SUMIFS(disponibilidad[Tiempo falla (en Mintuos)],disponibilidad[RECAUDOS],"SI",disponibilidad[Mes],$B14,disponibilidad[[Tipo de afectación ]],"caÍda total",disponibilidad[Responsable Falla],"Aliados o terceros",disponibilidad[Gana Gana - Tolima],"SI")))/$C14)*100 -> 100 | S14: =+(($C14-(SUMIFS(disponibilidad[Tiempo falla (en Mintuos)],disponibilidad[RECARGAS],"SI",disponibilidad[Mes],$B14,disponibilidad[[Tipo de afectación ]],"caÍda total",disponibilidad[Responsable Falla],"Aliados o terceros",disponibilidad[Gana Gana - Tolima],"SI")))/$C14)*100 -> 100 | T14: =+(($C14-(SUMIFS(disponibilidad[Tiempo falla (en Mintuos)],#REF!,"SI",disponibilidad[Mes],$B14,disponibilidad[[Tipo de afectación ]],"caÍda total",disponibilidad[Responsable Falla],"Aliados o terceros",disponibilidad[Gana Gana - Tolima],"SI")))/$C14)*100 -> #REF! | U14: =AVERAGE(P14:T14) -> #REF! | V14: =SUMIFS(disponibilidad[Tiempo falla (en Mintuos)],disponibilidad[Mes],$B14,disponibilidad[[Tipo de afectación ]],"caÍda total",disponibilidad[Responsable Falla],"Matrix Tech",disponibilidad[Gana Gana - Tolima],"SI") -> 0 | W14: =+V14/C14 -> 0 | X14: =SUMIFS(disponibilidad[Tiempo falla (en Mintuos)],disponibilidad[Mes],$B14,disponibilidad[[Tipo de afectación ]],"caÍda total",disponibilidad[Responsable Falla],"Aliados o terceros",disponibilidad[Gana Gana - Tolima],"SI") -> 0 | Y14: =+$X$5/$C$5 -> 0
B15: Noviembre | C15: =VLOOKUP(B15,Maestro!$A$7:$D$19,4,FALSE) -> 43200 | D15: =+(($C15-(SUMIFS(disponibilidad[Tiempo falla (en Mintuos)],disponibilidad[JADE],"SI",disponibilidad[Mes],$B15,disponibilidad[[Tipo de afectación ]],"caÍda total",disponibilidad[Responsable Falla],"Matrix Tech",disponibilidad[Gana Gana - Tolima],"SI")))/$C15)*100 -> 100 | E15: =+(($C15-(SUMIFS(disponibilidad[Tiempo falla (en Mintuos)],disponibilidad[JADE],"SI",disponibilidad[Mes],$B15,disponibilidad[[Tipo de afectación ]],"caÍda total",disponibilidad[Responsable Falla],"Matrix Tech",disponibilidad[Gana Gana - Tolima],"SI")))/$C15)*100 -> 100 | F15: =+(($C15-(SUMIFS(disponibilidad[Tiempo falla (en Mintuos)],disponibilidad[JADE],"SI",disponibilidad[Mes],$B15,disponibilidad[[Tipo de afectación ]],"caÍda total",disponibilidad[Responsable Falla],"Matrix Tech",disponibilidad[Gana Gana - Tolima],"SI")))/$C15)*100 -> 100 | G15: =+(($C15-(SUMIFS(disponibilidad[Tiempo falla (en Mintuos)],disponibilidad[JADE],"SI",disponibilidad[Mes],$B15,disponibilidad[[Tipo de afectación ]],"caÍda total",disponibilidad[Responsable Falla],"Matrix Tech",disponibilidad[Gana Gana - Tolima],"SI")))/$C15)*100 -> 100 | H15: =SUMPRODUCT($D$4:$G$4,D15:G15)/$O$4 -> 100 | I15: =+(($C15-(SUMIFS(disponibilidad[Tiempo falla (en Mintuos)],disponibilidad[Apuestas - Chance],"SI",disponibilidad[Mes],$B15,disponibilidad[[Tipo de afectación ]],"caÍda total",disponibilidad[Responsable Falla],"Matrix Tech",disponibilidad[Gana Gana - Tolima],"SI")))/$C15)*100 -> 100 | J15: =+(($C15-(SUMIFS(disponibilidad[Tiempo falla (en Mintuos)],#REF!,"SI",disponibilidad[Mes],$B15,disponibilidad[[Tipo de afectación ]],"caÍda total",disponibilidad[Responsable Falla],"Matrix Tech",disponibilidad[Gana Gana - Tolima],"SI")))/$C15)*100 -> #REF! | K15: =+(($C15-(SUMIFS(disponibilidad[Tiempo falla (en Mintuos)],disponibilidad[PAGOS],"SI",disponibilidad[Mes],$B15,disponibilidad[[Tipo de afectación ]],"caÍda total",disponibilidad[Responsable Falla],"Matrix Tech",disponibilidad[Gana Gana - Tolima],"SI")))/$C15)*100 -> 100 | L15: =+(($C15-(SUMIFS(disponibilidad[Tiempo falla (en Mintuos)],disponibilidad[RECAUDOS],"SI",disponibilidad[Mes],$B15,disponibilidad[[Tipo de afectación ]],"caÍda total",disponibilidad[Responsable Falla],"Matrix Tech",disponibilidad[Gana Gana - Tolima],"SI")))/$C15)*100 -> 100 | M15: =+(($C15-(SUMIFS(disponibilidad[Tiempo falla (en Mintuos)],disponibilidad[RECARGAS],"SI",disponibilidad[Mes],$B15,disponibilidad[[Tipo de afectación ]],"caÍda total",disponibilidad[Responsable Falla],"Matrix Tech",disponibilidad[Gana Gana - Tolima],"SI")))/$C15)*100 -> 100 | N15: =+(($C15-(SUMIFS(disponibilidad[Tiempo falla (en Mintuos)],#REF!,"SI",disponibilidad[Mes],$B15,disponibilidad[[Tipo de afectación ]],"caÍda total",disponibilidad[Responsable Falla],"Matrix Tech",disponibilidad[Gana Gana - Tolima],"SI")))/$C15)*100 -> #REF! | O15: =SUMPRODUCT($I$4:$N$4,I15:N15)/$O$4 -> #REF! | P15: =+(($C15-(SUMIFS(disponibilidad[Tiempo falla (en Mintuos)],#REF!,"SI",disponibilidad[Mes],$B15,disponibilidad[[Tipo de afectación ]],"caÍda total",disponibilidad[Responsable Falla],"Aliados o terceros",disponibilidad[Gana Gana - Tolima],"SI")))/$C15)*100 -> #REF! | Q15: =+(($C15-(SUMIFS(disponibilidad[Tiempo falla (en Mintuos)],disponibilidad[PAGOS],"SI",disponibilidad[Mes],$B15,disponibilidad[[Tipo de afectación ]],"caÍda total",disponibilidad[Responsable Falla],"Aliados o terceros",disponibilidad[Gana Gana - Tolima],"SI")))/$C15)*100 -> 100 | R15: =+(($C15-(SUMIFS(disponibilidad[Tiempo falla (en Mintuos)],disponibilidad[RECAUDOS],"SI",disponibilidad[Mes],$B15,disponibilidad[[Tipo de afectación ]],"caÍda total",disponibilidad[Responsable Falla],"Aliados o terceros",disponibilidad[Gana Gana - Tolima],"SI")))/$C15)*100 -> 100 | S15: =+(($C15-(SUMIFS(disponibilidad[Tiempo falla (en Mintuos)],disponibilidad[RECARGAS],"SI",disponibilidad[Mes],$B15,disponibilidad[[Tipo de afectación ]],"caÍda total",disponibilidad[Responsable Falla],"Aliados o terceros",disponibilidad[Gana Gana - Tolima],"SI")))/$C15)*100 -> 100 | T15: =+(($C15-(SUMIFS(disponibilidad[Tiempo falla (en Mintuos)],#REF!,"SI",disponibilidad[Mes],$B15,disponibilidad[[Tipo de afectación ]],"caÍda total",disponibilidad[Responsable Falla],"Aliados o terceros",disponibilidad[Gana Gana - Tolima],"SI")))/$C15)*100 -> #REF! | U15: =AVERAGE(P15:T15) -> #REF! | V15: =SUMIFS(disponibilidad[Tiempo falla (en Mintuos)],disponibilidad[Mes],$B15,disponibilidad[[Tipo de afectación ]],"caÍda total",disponibilidad[Responsable Falla],"Matrix Tech",disponibilidad[Gana Gana - Tolima],"SI") -> 0 | W15: =+V15/C15 -> 0 | X15: =SUMIFS(disponibilidad[Tiempo falla (en Mintuos)],disponibilidad[Mes],$B15,disponibilidad[[Tipo de afectación ]],"caÍda total",disponibilidad[Responsable Falla],"Aliados o terceros",disponibilidad[Gana Gana - Tolima],"SI") -> 0 | Y15: =+$X$5/$C$5 -> 0
B16: Diciembre | C16: =VLOOKUP(B16,Maestro!$A$7:$D$19,4,FALSE) -> 44640 | D16: =+(($C16-(SUMIFS(disponibilidad[Tiempo falla (en Mintuos)],disponibilidad[JADE],"SI",disponibilidad[Mes],$B16,disponibilidad[[Tipo de afectación ]],"caÍda total",disponibilidad[Responsable Falla],"Matrix Tech",disponibilidad[Gana Gana - Tolima],"SI")))/$C16)*100 -> 100 | E16: =+(($C16-(SUMIFS(disponibilidad[Tiempo falla (en Mintuos)],disponibilidad[JADE],"SI",disponibilidad[Mes],$B16,disponibilidad[[Tipo de afectación ]],"caÍda total",disponibilidad[Responsable Falla],"Matrix Tech",disponibilidad[Gana Gana - Tolima],"SI")))/$C16)*100 -> 100 | F16: =+(($C16-(SUMIFS(disponibilidad[Tiempo falla (en Mintuos)],disponibilidad[JADE],"SI",disponibilidad[Mes],$B16,disponibilidad[[Tipo de afectación ]],"caÍda total",disponibilidad[Responsable Falla],"Matrix Tech",disponibilidad[Gana Gana - Tolima],"SI")))/$C16)*100 -> 100 | G16: =+(($C16-(SUMIFS(disponibilidad[Tiempo falla (en Mintuos)],disponibilidad[JADE],"SI",disponibilidad[Mes],$B16,disponibilidad[[Tipo de afectación ]],"caÍda total",disponibilidad[Responsable Falla],"Matrix Tech",disponibilidad[Gana Gana - Tolima],"SI")))/$C16)*100 -> 100 | H16: =SUMPRODUCT($D$4:$G$4,D16:G16)/$O$4 -> 100 | I16: =+(($C16-(SUMIFS(disponibilidad[Tiempo falla (en Mintuos)],disponibilidad[Apuestas - Chance],"SI",disponibilidad[Mes],$B16,disponibilidad[[Tipo de afectación ]],"caÍda total",disponibilidad[Responsable Falla],"Matrix Tech",disponibilidad[Gana Gana - Tolima],"SI")))/$C16)*100 -> 100 | J16: =+(($C16-(SUMIFS(disponibilidad[Tiempo falla (en Mintuos)],#REF!,"SI",disponibilidad[Mes],$B16,disponibilidad[[Tipo de afectación ]],"caÍda total",disponibilidad[Responsable Falla],"Matrix Tech",disponibilidad[Gana Gana - Tolima],"SI")))/$C16)*100 -> #REF! | K16: =+(($C16-(SUMIFS(disponibilidad[Tiempo falla (en Mintuos)],disponibilidad[PAGOS],"SI",disponibilidad[Mes],$B16,disponibilidad[[Tipo de afectación ]],"caÍda total",disponibilidad[Responsable Falla],"Matrix Tech",disponibilidad[Gana Gana - Tolima],"SI")))/$C16)*100 -> 100 | L16: =+(($C16-(SUMIFS(disponibilidad[Tiempo falla (en Mintuos)],disponibilidad[RECAUDOS],"SI",disponibilidad[Mes],$B16,disponibilidad[[Tipo de afectación ]],"caÍda total",disponibilidad[Responsable Falla],"Matrix Tech",disponibilidad[Gana Gana - Tolima],"SI")))/$C16)*100 -> 100 | M16: =+(($C16-(SUMIFS(disponibilidad[Tiempo falla (en Mintuos)],disponibilidad[RECARGAS],"SI",disponibilidad[Mes],$B16,disponibilidad[[Tipo de afectación ]],"caÍda total",disponibilidad[Responsable Falla],"Matrix Tech",disponibilidad[Gana Gana - Tolima],"SI")))/$C16)*100 -> 100 | N16: =+(($C16-(SUMIFS(disponibilidad[Tiempo falla (en Mintuos)],#REF!,"SI",disponibilidad[Mes],$B16,disponibilidad[[Tipo de afectación ]],"caÍda total",disponibilidad[Responsable Falla],"Matrix Tech",disponibilidad[Gana Gana - Tolima],"SI")))/$C16)*100 -> #REF! | O16: =SUMPRODUCT($I$4:$N$4,I16:N16)/$O$4 -> #REF! | P16: =+(($C16-(SUMIFS(disponibilidad[Tiempo falla (en Mintuos)],#REF!,"SI",disponibilidad[Mes],$B16,disponibilidad[[Tipo de afectación ]],"caÍda total",disponibilidad[Responsable Falla],"Aliados o terceros",disponibilidad[Gana Gana - Tolima],"SI")))/$C16)*100 -> #REF! | Q16: =+(($C16-(SUMIFS(disponibilidad[Tiempo falla (en Mintuos)],disponibilidad[PAGOS],"SI",disponibilidad[Mes],$B16,disponibilidad[[Tipo de afectación ]],"caÍda total",disponibilidad[Responsable Falla],"Aliados o terceros",disponibilidad[Gana Gana - Tolima],"SI")))/$C16)*100 -> 100 | R16: =+(($C16-(SUMIFS(disponibilidad[Tiempo falla (en Mintuos)],disponibilidad[RECAUDOS],"SI",disponibilidad[Mes],$B16,disponibilidad[[Tipo de afectación ]],"caÍda total",disponibilidad[Responsable Falla],"Aliados o terceros",disponibilidad[Gana Gana - Tolima],"SI")))/$C16)*100 -> 100 | S16: =+(($C16-(SUMIFS(disponibilidad[Tiempo falla (en Mintuos)],disponibilidad[RECARGAS],"SI",disponibilidad[Mes],$B16,disponibilidad[[Tipo de afectación ]],"caÍda total",disponibilidad[Responsable Falla],"Aliados o terceros",disponibilidad[Gana Gana - Tolima],"SI")))/$C16)*100 -> 100 | T16: =+(($C16-(SUMIFS(disponibilidad[Tiempo falla (en Mintuos)],#REF!,"SI",disponibilidad[Mes],$B16,disponibilidad[[Tipo de afectación ]],"caÍda total",disponibilidad[Responsable Falla],"Aliados o terceros",disponibilidad[Gana Gana - Tolima],"SI")))/$C16)*100 -> #REF! | U16: =AVERAGE(P16:T16) -> #REF! | V16: =SUMIFS(disponibilidad[Tiempo falla (en Mintuos)],disponibilidad[Mes],$B16,disponibilidad[[Tipo de afectación ]],"caÍda total",disponibilidad[Responsable Falla],"Matrix Tech",disponibilidad[Gana Gana - Tolima],"SI") -> 0 | W16: =+V16/C16 -> 0 | X16: =SUMIFS(disponibilidad[Tiempo falla (en Mintuos)],disponibilidad[Mes],$B16,disponibilidad[[Tipo de afectación ]],"caÍda total",disponibilidad[Responsable Falla],"Aliados o terceros",disponibilidad[Gana Gana - Tolima],"SI") -> 0 | Y16: =+$X$5/$C$5 -> 0

Sheet Hoja2
C1: Octubre | D1: JADE | E1: 715141 | F1: 45589.496 | G1: 45589.585 | H1: =+(disponibilidad[[#This Row],[Fecha y hora fin]]-disponibilidad[[#This Row],[Fecha y hora inicio]])*1440 -> #VALUE!
C4: Octubre | D4: JADE | E4: INC 2024-714651 | F4: 60 | O4: Mes​ | P4: Días Mes​ | Q4: Horas Mes​ | R4: Min Mes​
C5: Octubre | D5: PRECARGA DE ENERGIA | E5: INC 2024-300254 | F5: 10 | O5: Enero​ | P5: 31​ | Q5: 744 ​ | R5: 44640​
C6: Octubre | D6: RECARGAS TIGO | E6: INC 2024-301316 | F6: 175 | O6: Febrero​ | P6: 29​ | Q6: 696 ​ | R6: 41760​
C7: Octubre | D7: PRECARGA DE ENERGIA | E7: INC 2024-301816 | F7: 57 | O7: Marzo​ | P7: 31​ | Q7: 744 ​ | R7: 44640​
C8: Octubre | D8: PAQUETES MOVISTAR | E8: INC 2024-307898 | F8: 42 | O8: Abril​ | P8: 30​ | Q8: 720 ​ | R8: 43200​
C9: Octubre | D9: RECARGA AGUA PREPAGO EPM | E9: INC 2024-314165 | F9: 28 | O9: Mayo​ | P9: 31​ | Q9: 744 ​ | R9: 44640​
C10: Octubre | D10: PAQUETES CLARO | E10: INC 2024-314400 | F10: 62 | I10: 398 | O10: Junio​ | P10: 30​ | Q10: 720 ​ | R10: 43200​
C11: Octubre | D11: PAQUETES CLARO | E11: INC 2024-316281 | F11: 10 | O11: Julio​ | P11: 31​ | Q11: 744 ​ | R11: 44640​
C12: Octubre | D12: JADE | E12: INC 2024-317572 | F12: 114 | O12: Agosto​ | P12: 31​ | Q12: 744 ​ | R12: 44640​
C13: Octubre | D13: JADE | E13: INC 2024-319865 | F13: 142 | K13: 398 | L13: =+K13/60 -> 6.6333333 | O13: Septiembre​ | P13: 30​ | Q13: 720 ​ | R13: 43200​
C14: Octubre | D14: JADE | E14: 715121 | F14: 242 | K14: 574 | L14: =+K14/60 -> 9.5666667 | O14: Octubre​ | P14: 31​ | Q14: 744 ​ | R14: 44640​
C15: Octubre | D15: JADE | E15: 715145 | F15: 196 | O15: Noviembre​ | P15: 30​ | Q15: 720 ​ | R15: 43200​
C16: Octubre | D16: JADE | E16: 715128 | F16: 574 | O16: Diciembre​ | P16: 31​ | Q16: 744 ​ | R16: 44640​
C17: Octubre | D17: JADE | E17: 715144 | F17: 560
C18: Octubre | D18: JADE | E18: 715141 | F18: 129
C19: Octubre | D19: Recargas y Paquetes Claro | E19: INC 2024-330565 | F19: 14
D22: RED ALIADA | E22: % DISPONIBILIDAD
D23: Acertemos - Cauca | E23: 99.325269 | F23: 99.072133 | G23: 98.328405 | H23: 99.610215 | I23: 99.610215 | J23: 99.614247 | K23: 99.345699
D24: Jer - Boyaca | E24: 99.072133 | F24: 99.072133 | G24: 98.328405 | H24: 99.610215 | I24: 99.610215 | J24: 99.614247 | K24: 99.345699
D25: SuChance - Huila | E25: 98.328405 | F25: 99.072133 | G25: 98.328405 | H25: 99.610215 | I25: 99.610215 | J25: 99.614247 | K25: 99.345699 | N25: Disponibilidad | O25: 0.9918
D26: MatrixRedes | E26: 99.610215 | F26: 99.072133 | G26: 98.328405 | H26: 99.610215 | I26: 99.610215 | J26: 99.614247 | K26: 99.345699 | N26: Indisponibilidad | O26: 0.0078
D27: Gana Gana - Tolina | E27: 99.171147 | F27: 99.072133 | G27: 98.328405 | H27: 99.610215 | I27: 99.610215 | J27: 99.614247 | K27: 99.345699
D28: Santander La Perla | E28: 98.359767 | F28: 99.072133 | G28: 98.328405 | H28: 99.610215 | I28: 99.610215 | J28: 99.614247 | K28: 99.345699
D29: Gana - Antioquia | E29: 99.345699 | F29: 99.072133 | G29: 98.328405 | H29: 99.610215 | I29: 99.610215 | J29: 99.614247 | K29: 99.345699
B36: Mes | C36: % Disponibilidad
B37: Mayo | C37: 99.991
B38: Junio | C38: 99.986
B39: Julio | C39: 100
B40: Agosto | C40: 100
B41: Septiembre | C41: 99.891748 | M41: 99.325269 | N41: 99.072133 | O41: 98.328405 | P41: 99.610215 | Q41: 99.171147 | R41: 98.359767 | S41: 99.345699
B42: Octubre | C42: 99.184031
D57: Categoría | E57: Octubre | H57: Tipología | I57: Octubre
D58: Centro de Gestion > Reportes | E58: 92 | H58: HARDWARE Y SOFTWARE > Mantenimiento | I58: 7
D59: SEGURIDAD > Informacion General | E59: 44 | H59: Aguas Barrancabermeja | I59: 4
D60: Incidentes Desarrollo > Problema con Servicios | E60: 36 | H60: HARDWARE Y SOFTWARE > Bloqueo | I60: 3
D61: Mesa De Servicios > Diferencias transaccionales | E61: 29 | H61: HARDWARE Y SOFTWARE > Asignación Equipo | I61: 2
D62: Centro de Gestion > Cache Aplicaciones | E62: 29 | H62: INFRAESTRUCTURA > Actualización de aplicaciones | I62: 1
D63: Mesa De Servicios > Conciliaciones | E63: 28 | H63: CONECTIVIDAD > Accesos usuarios | I63: 1
D64: RECAUDOS > Caídas de Aplicaciones < No pueden Transar> | E64: 19 | H64: Total general | I64: 18
D65: App Su Red > Registro > Actualización de datos | E65: 12
D66: Solicitudes Administración > Mantenimiento Locativo > General | E66: 10
D67: App Su Red > Registro | E67: 10
D68: APUESTAS PERMANENTES > Raspita > PagoPremios | E68: 9
D69: Jade Pc | E69: 8
D70: Mesa De Servicios > Aplicar Cache (Redes) | E70: 8
D77: Producto afectado o aplicación | E77: Incidente
D78: Recaudo EPM en Línea | E78: REQ 2024-331076
D79: Recargas y Paquetes Exito | E79: REQ 2024-330656
D80: Incidencia Chance Bingo | E80: INC 2024-333368
D81: Precargas y recargas de EPM | E81: INC 2024-333456
D82: Civica Metro | E82: INC 2024-340213
D83: Recargas Energia | E83: INC 2024-344181
D84: JADE SIN TX | E84: INC 2024-344309
D85: Recargas Claro | E85: INC 2024-344383
D86: Precargas y recargas de EPM | E86: INC 2024-345795
D87: Precargas y recargas de EPM | E87: INC 2024-346005
D88: Recargas Conexred | E88: INC 2024-347131
D89: JADE SIN TX | E89: INC 2024-359707

Sheet MatrixRedes____
B2: Mes | C2: Minutos Mes | D2: Disponibilidad Individual Aplicación Matrix Tech | H2: Disponibilidad General Aplicación | I2: Disponibilidad Indivudual Producto Matrix Tech | O2: Disponibilidad General Producto | P2: Disponibilidad Indivudual Producto Aliados o Terceros | U2: Disponibilidad General Producto | V2: Matrix Tech | X2: Aliados - Terceros
D3: JADE | E3: SIGA | F3: MI POS - PRISMA 2 | G3: APP | I3: Apuestas - Chance | J3: GIROS | K3: PAGOS | L3: RECAUDOS | M3: RECARGAS | N3: SEGUROS | P3: GIROS | Q3: PAGOS | R3: RECAUDOS | S3: RECARGAS | T3: SEGUROS | V3: Tiempo Indisponibiliad | W3: % Indisponibiliad | X3: Tiempo Indisponibiliad | Y3: % Indisponibiliad
